Workbook

Sheet Cover Page
B2: JINDAL FERROUS LIMITED — DEBT MONITORING MODEL
B3: CREDIT COMMITTEE SUMMARY
B4: ="As of: "&TEXT('Instructions & Assumptions'!B5,"DD-MMM-YYYY") -> As of: 12-May-2026
B6: 1. PROJECT OVERVIEW
B7: Project | C7: 2.0 MTPA Greenfield Integrated Steel Plant, Kalinga Nagar, Odisha | E7: Sector | F7: Iron & Steel (Ferrochrome)
B8: Borrower | C8: Jindal Ferrous Limited (JFL) | E8: Group | F8: Jindal Stainless / Ratan Jindal Group
B9: Total Proj Cost | C9: ₹4,083.94 Cr | Debt ₹2,721.43 Cr | Equity ₹1,362.51 Cr | E9: D:E Ratio | F9: 66.64 : 33.36
B10: Sanctioned Debt | C10: ₹4,666 Cr | 9 Lenders | 44 Facilities | E10: Adj Consortium | F10: ₹3,826 Cr (nets out ICICI TL ₹840 Cr takeover)
B12: 2. KEY FINANCIAL METRICS (TEV FY29 — First Covenant Test Year)
B13: Metric | C13: Value | E13: Metric | F13: Value
B14: Revenue | C14: ₹7,541 Cr | E14: Project IRR | F14: 0.1506
B15: EBITDA | C15: ₹957 Cr | E15: WACC (model) | F15: 11.2% (TEV: 10.55%)
B16: EBITDA Margin | C16: 0.127 | E16: NPV | F16: ₹1,134 Cr
B17: PAT | C17: ₹347 Cr | E17: Payback Period | F17: 5.80 years
B18: Min DSCR | C18: 1.5505x (FY30) | E18: Avg DSCR | F18: 1.9211x
B19: ISCR (FY29) | C19: 3.6549x | E19: FACR (FY29) | F19: 1.5100x
B21: 3. COVENANT SUMMARY
B22: =COUNTIF('FY29 Covenant Compliance (TEV)'!G7:G52,"Compliant*")&" / 44 Compliant (FY29 TEV Projections) | "&COUNTIF('FY29 Covenant Compliance (TEV)'!G7:G52,"Near Breach")&" Near Breach (ICICI WC Rating — at threshold)" -> 43 / 44 Compliant (FY29 TEV Projections) | 1 Near Breach (ICICI WC Rating — at threshold)
B23: First formal covenant test year: FY29 post-COD. All 43 of 44 covenants project COMPLIANT on TEV FY29 projections; 1 Near Breach (ICICI WC Rating).
B25: 4. OPEN FLAGS REQUIRING MANAGEMENT ACTION (4 High Severity)
B26: ⚠ F-01: ICICI BG limit ambiguity | C26: Annexure I states ₹300 Cr; pp.7-8 detail suggests different amount. ACTION: confirm with ICICI treasury.
B27: ⚠ F-02: RBL bridge refinance risk | C27: ₹200 Cr bullet matures 13-Nov-2026. Refinancing plan not yet confirmed. ACTION: initiate rollover negotiations.
B28: ⚠ F-07: HSBC uncommitted status | C28: ₹1,000 Cr is NOT committed — bank can cancel at discretion. ACTION: treat as contingent, not available liquidity.
B29: ⚠ F-15: HDFC FMV cover source | C29: JSL FMV / Total Debt ≥ 2.5x in offer letter not confirmed. ACTION: obtain Treasury verification of FMV data source.
B30: See Management Flags sheet for all 18 flags — 13 Open (4 High / 7 Medium / 2 Low) | 2 Closed | 2 Acceptable | 1 Open-Linked
B32: 5. MODEL INTEGRITY
B33: ='Validation & Integrity'!B118 -> 108
B34: Sources: 9 JFL sanction letters + TEV Financial Model (Sep-2025) + Statutory Audit (N.C. Aggarwal & Co., 28-Aug-2025, UDIN: 25086622BMIBYO3693)

Sheet Dashboard
A1: JINDAL FERROUS LIMITED — DEBT MONITORING DASHBOARD
A2: ="As of "&TEXT('Instructions & Assumptions'!B5,"DD-MMM-YYYY")&" | 9 Lenders | 44 Facilities | Source: JFL sanction letters + TEV Financial Model + Statutory Audit" -> As of 12-May-2026 | 9 Lenders | 44 Facilities | Source: JFL sanction letters + TEV Financial Model + Statutory Audit
A3: ="MODEL INTEGRITY: "&'Validation & Integrity'!B118 -> MODEL INTEGRITY: 108
A4: A. SANCTIONED DEBT OVERVIEW
B5: A. SANCTIONED DEBT OVERVIEW
B6: SANCTIONED DEBT (₹ Cr) | E6: FB MAINS (₹ Cr) | H6: NFB MAINS (₹ Cr) | K6: NFB CONTINGENT (₹ Cr) | N6: ADJ CONSORTIUM (₹ Cr)
B7: ='Lender Summary'!B20 -> 4666 | E7: ='Lender Summary'!B21 -> 4116 | H7: ='Lender Summary'!B22 -> 550 | K7: ='Lender Summary'!B23 -> 2040 | N7: =AdjustedConsortiumDebt -> 3826
B8: FD-BACKED (₹ Cr) | E8: UNCOMMITTED MEMO (₹ Cr) | H8: HEDGE MEMO (₹ Cr) | K8: WAC OF FB DEBT | N8: ANNUAL RUN-RATE INTEREST (₹ Cr)
B9: ='Lender Summary'!B24 -> 150 | E9: ='Lender Summary'!B25 -> 0 | H9: ='Lender Summary'!B26 -> 75 | K9: ='Interest Schedule'!C59 -> 0.091499271 | N9: =TotalIntComm -> 393.161
B10: ACTIVE FACILITIES | E10: COVENANTS (FY29 TEV) | H10: AVG UTILIZATION | K10: TOTAL TL PRINCIPAL O/S (₹ Cr) | N10: ICICI TL TAKEOVER (₹ Cr)
B11: =COUNTA('Facility Master'!A5:A48) -> 44 | E11: =COUNTIF('FY29 Covenant Compliance (TEV)'!G7:G52,"Compliant*")&" / "&COUNTA('FY29 Covenant Compliance (TEV)'!B7:B52)&" Compliant (FY29)" -> 43 / 44 Compliant (FY29) | H11: =AVERAGEIFS('Facility Master'!N5:N48,'Facility Master'!H5:H48,">0") -> 1 | K11: =Total_TL_PrincOS -> 3816 | N11: =ICICI_TL_Takeover -> 840
B12: =COUNTIF('FY29 Covenant Compliance (TEV)'!G7:G52,"Compliant*")&" / 44 Compliant (FY29 TEV — First Covenant Test Year) | "&COUNTIF('FY29 Covenant Compliance (TEV)'!G7:G52,"Near Breach")&" Near Breach" -> 43 / 44 Compliant (FY29 TEV — First Covenant Test Year) | 1 Near Breach
B14: B. COVENANT COMPLIANCE — FY29 TEV PROJECTIONS (First Post-COD Test Year)
B15: TOTAL COVENANTS | F15: COMPLIANT (FY29) | J15: NEAR BREACH | M15: BREACHED
B16: =COUNTA('FY29 Covenant Compliance (TEV)'!B7:B52) -> 44 | F16: =COUNTIF('FY29 Covenant Compliance (TEV)'!G7:G52,"Compliant*") -> 43 | J16: =COUNTIF('FY29 Covenant Compliance (TEV)'!G7:G52,"Near Breach") -> 1 | M16: =COUNTIF('FY29 Covenant Compliance (TEV)'!G7:G52,"Breached") -> 0
B17: Source: FY29 Covenant Compliance (TEV) sheet — first formal test year for consortium covenants.
B18: C. LENDER CONCENTRATION (Sanctioned Debt = B1 + B2, ₹ Cr)
B19: Lender | E19: Sanctioned (₹ Cr) | G19: % Share | H19: Concentration Bar (normalised to UBI) | N19: NFB Contingent (₹ Cr) | O19: ='Lender Summary'!G7 -> 0
B20: UBI | E20: ='Lender Summary'!D6 -> 1361 | G20: ='Lender Summary'!E6 -> 0.29168453 | H20: =REPT("█",ROUND(G20*100,0)) -> █████████████████████████████ | N20: ='Lender Summary'!G6 -> 750 | O20: ='Lender Summary'!G8 -> 200
B21: Indian Bank | E21: ='Lender Summary'!D7 -> 235 | G21: ='Lender Summary'!E7 -> 0.050364338 | H21: =REPT("█",ROUND(G21*100,0)) -> █████ | N21: ='Lender Summary'!G7 -> 0 | O21: ='Lender Summary'!G9 -> 100
B22: RBL Bank | E22: ='Lender Summary'!D8 -> 200 | G22: ='Lender Summary'!E8 -> 0.042863266 | H22: =REPT("█",ROUND(G22*100,0)) -> ████ | N22: ='Lender Summary'!G8 -> 200 | O22: ='Lender Summary'!G10 -> 400
B23: YES Bank | E23: ='Lender Summary'!D9 -> 650 | G23: ='Lender Summary'!E9 -> 0.13930562 | H23: =REPT("█",ROUND(G23*100,0)) -> ██████████████ | N23: ='Lender Summary'!G9 -> 100 | O23: ='Lender Summary'!G11 -> 300
B24: IDFC First Bank | E24: ='Lender Summary'!D10 -> 530 | G24: ='Lender Summary'!E10 -> 0.11358766 | H24: =REPT("█",ROUND(G24*100,0)) -> ███████████ | N24: ='Lender Summary'!G10 -> 400 | O24: ='Lender Summary'!G12 -> 0
B25: ICICI Bank WC | E25: ='Lender Summary'!D11 -> 400 | G25: ='Lender Summary'!E11 -> 0.085726532 | H25: =REPT("█",ROUND(G25*100,0)) -> █████████ | N25: ='Lender Summary'!G11 -> 300 | O25: ='Lender Summary'!G13 -> 250
B26: HSBC (₹200 Cr post-haircut, B1 — see MP-13/F-18) | E26: ='Lender Summary'!D12 -> 200 | G26: ='Lender Summary'!E12 -> 0.042863266 | H26: =REPT("█",ROUND(G26*100,0)) -> ████ | N26: ='Lender Summary'!G12 -> 0 | O26: ='Lender Summary'!G14 -> 40
B27: HDFC Bank | E27: ='Lender Summary'!D13 -> 250 | G27: ='Lender Summary'!E13 -> 0.053579083 | H27: =REPT("█",ROUND(G27*100,0)) -> █████ | N27: ='Lender Summary'!G13 -> 250 | O27: =SUM(O18:O26) -> 1290
B28: ICICI Bank (TL) | E28: ='Lender Summary'!D14 -> 840 | G28: ='Lender Summary'!E14 -> 0.18002572 | H28: =REPT("█",ROUND(G28*100,0)) -> ██████████████████ | N28: ='Lender Summary'!G14 -> 40
B29: Grand Total | E29: =SUM(E20:E28) -> 4666 | G29: =SUM(G20:G28) -> 1 | N29: =SUM(N20:N28) -> 2040
B30: D. TERM LOAN MATURITY PROFILE (Principal Repayment by Fiscal Year, ₹ Cr) — excl. RBL Bridge ₹200 Cr bullet (see F-02)
B31: Fiscal Year | D31: Principal (₹ Cr) | G31: Repayment Profile Bar
B32: FY24 | D32: =SUMIFS('Repayment Schedule'!AM5:AM68,'Repayment Schedule'!B5:B68,">="&DATE(2023,4,1),'Repayment Schedule'!B5:B68,"<="&DATE(2024,3,31)) -> 0 | G32: =IFERROR(REPT("█",ROUND(D32/40,0)),"")
B33: FY25 | D33: =SUMIFS('Repayment Schedule'!AM5:AM68,'Repayment Schedule'!B5:B68,">="&DATE(2024,4,1),'Repayment Schedule'!B5:B68,"<="&DATE(2025,3,31)) -> 0 | G33: =IFERROR(REPT("█",ROUND(D33/40,0)),"")
B34: FY26 | D34: =SUMIFS('Repayment Schedule'!AM5:AM68,'Repayment Schedule'!B5:B68,">="&DATE(2025,4,1),'Repayment Schedule'!B5:B68,"<="&DATE(2026,3,31)) -> 0 | G34: =IFERROR(REPT("█",ROUND(D34/40,0)),"")
B35: FY27 | D35: =SUMIFS('Repayment Schedule'!AM5:AM68,'Repayment Schedule'!B5:B68,">="&DATE(2026,4,1),'Repayment Schedule'!B5:B68,"<="&DATE(2027,3,31)) -> 2.9375 | G35: =IFERROR(REPT("█",ROUND(D35/40,0)),"")
B36: FY28 | D36: =SUMIFS('Repayment Schedule'!AM5:AM68,'Repayment Schedule'!B5:B68,">="&DATE(2027,4,1),'Repayment Schedule'!B5:B68,"<="&DATE(2028,3,31)) -> 180.8 | G36: =IFERROR(REPT("█",ROUND(D36/40,0)),"") -> █████
B37: FY29 | D37: =SUMIFS('Repayment Schedule'!AM5:AM68,'Repayment Schedule'!B5:B68,">="&DATE(2028,4,1),'Repayment Schedule'!B5:B68,"<="&DATE(2029,3,31)) -> 183.15 | G37: =IFERROR(REPT("█",ROUND(D37/40,0)),"") -> █████
B38: FY30 | D38: =SUMIFS('Repayment Schedule'!AM5:AM68,'Repayment Schedule'!B5:B68,">="&DATE(2029,4,1),'Repayment Schedule'!B5:B68,"<="&DATE(2030,3,31)) -> 325.44 | G38: =IFERROR(REPT("█",ROUND(D38/40,0)),"") -> ████████
B39: FY31 | D39: =SUMIFS('Repayment Schedule'!AM5:AM68,'Repayment Schedule'!B5:B68,">="&DATE(2030,4,1),'Repayment Schedule'!B5:B68,"<="&DATE(2031,3,31)) -> 325.44 | G39: =IFERROR(REPT("█",ROUND(D39/40,0)),"") -> ████████
B40: FY32 | D40: =SUMIFS('Repayment Schedule'!AM5:AM68,'Repayment Schedule'!B5:B68,">="&DATE(2031,4,1),'Repayment Schedule'!B5:B68,"<="&DATE(2032,3,31)) -> 325.44 | G40: =IFERROR(REPT("█",ROUND(D40/40,0)),"") -> ████████
B41: FY33 | D41: =SUMIFS('Repayment Schedule'!AM5:AM68,'Repayment Schedule'!B5:B68,">="&DATE(2032,4,1),'Repayment Schedule'!B5:B68,"<="&DATE(2033,3,31)) -> 325.44 | G41: =IFERROR(REPT("█",ROUND(D41/40,0)),"") -> ████████
B42: FY34 | D42: =SUMIFS('Repayment Schedule'!AM5:AM68,'Repayment Schedule'!B5:B68,">="&DATE(2033,4,1),'Repayment Schedule'!B5:B68,"<="&DATE(2034,3,31)) -> 325.44 | G42: =IFERROR(REPT("█",ROUND(D42/40,0)),"") -> ████████
B43: FY35 | D43: =SUMIFS('Repayment Schedule'!AM5:AM68,'Repayment Schedule'!B5:B68,">="&DATE(2034,4,1),'Repayment Schedule'!B5:B68,"<="&DATE(2035,3,31)) -> 325.44 | G43: =IFERROR(REPT("█",ROUND(D43/40,0)),"") -> ████████
B44: FY36 | D44: =SUMIFS('Repayment Schedule'!AM5:AM68,'Repayment Schedule'!B5:B68,">="&DATE(2035,4,1),'Repayment Schedule'!B5:B68,"<="&DATE(2036,3,31)) -> 325.44 | G44: =IFERROR(REPT("█",ROUND(D44/40,0)),"") -> ████████
B45: FY37 | D45: =SUMIFS('Repayment Schedule'!AM5:AM68,'Repayment Schedule'!B5:B68,">="&DATE(2036,4,1),'Repayment Schedule'!B5:B68,"<="&DATE(2037,3,31)) -> 325.44 | G45: =IFERROR(REPT("█",ROUND(D45/40,0)),"") -> ████████
B46: FY38 | D46: =SUMIFS('Repayment Schedule'!AM5:AM68,'Repayment Schedule'!B5:B68,">="&DATE(2037,4,1),'Repayment Schedule'!B5:B68,"<="&DATE(2038,3,31)) -> 325.44 | G46: =IFERROR(REPT("█",ROUND(D46/40,0)),"") -> ████████
B47: FY39 | D47: =SUMIFS('Repayment Schedule'!AM5:AM68,'Repayment Schedule'!B5:B68,">="&DATE(2038,4,1),'Repayment Schedule'!B5:B68,"<="&DATE(2039,3,31)) -> 320.1525 | G47: =IFERROR(REPT("█",ROUND(D47/40,0)),"") -> ████████
B48: Total (16y) | D48: =SUM(D32:D47) -> 3616
B49: E. FACILITY TYPE MIX
B50: Category | E50: Count | G50: Total Sanctioned (₹ Cr) | J50: Composition Bar
B51: Term Loans (FB-Term) | E51: =COUNTIF('Facility Master'!D5:D48,"FB-Term") -> 7 | G51: =SUMIFS('Facility Master'!K5:K48,'Facility Master'!D5:D48,"FB-Term") -> 3816 | J51: =IFERROR(REPT("█",ROUND(G51/150,0)),"") -> █████████████████████████
B52: Working Capital (FB) | E52: =COUNTIF('Facility Master'!D5:D48,"FB") -> 12 | G52: =SUMIFS('Facility Master'!K5:K48,'Facility Master'!D5:D48,"FB") -> 740.832 | J52: =IFERROR(REPT("█",ROUND(G52/150,0)),"") -> █████
B53: FD-Backed Facilities | E53: =COUNTIF('Facility Master'!D5:D48,"FB-FDbacked") -> 2 | G53: =SUMIFS('Facility Master'!K5:K48,'Facility Master'!D5:D48,"FB-FDbacked") -> 150 | J53: =IFERROR(REPT("█",ROUND(G53/150,0)),"") -> █
B54: Non-Fund Based (NFB) | E54: =COUNTIF('Facility Master'!D5:D48,"NFB") -> 22 | G54: =SUMIFS('Facility Master'!K5:K48,'Facility Master'!D5:D48,"NFB") -> 3469.24 | J54: =IFERROR(REPT("█",ROUND(G54/150,0)),"") -> ███████████████████████
B55: Hedge / Memo | E55: =COUNTIF('Facility Master'!D5:D48,"Hedge") -> 1 | G55: =SUMIFS('Facility Master'!K5:K48,'Facility Master'!D5:D48,"Hedge") -> 75 | J55: =IFERROR(REPT("█",ROUND(G55/150,0)),"") -> █
B57: F. URGENT WATCH FLAGS (10 Open — 4 High / 4 Medium / 2 Other)
B58: HIGH F-01 | C58: ICICI BG limit: Annexure I ₹300 Cr vs pp.7-8 detail — ambiguity. Confirm with ICICI treasury. | J58: HIGH F-02 | K58: RBL ₹200 Cr BULLET matures 13-Nov-2026 — refinancing plan not yet confirmed.
B59: HIGH F-07 | C59: HSBC ₹200 Cr (post 20% haircut on ₹1,000 Cr face — see MP-13) is INCLUDED in Sanctioned Debt at ₹200 Cr. Face value remains uncommitted; haircut portion treated as effective committed. See F-07, F-18. | J59: HIGH F-15 | K59: HDFC JSL FMV/Total Debt ≥2.5x — covenant source not confirmed. Verify with Treasury.
B60: MED F-04 | C60: IDFC First: FY27 first test (2 yrs earlier than peers) + different DSCR formula. | J60: MED F-05 | K60: IDFC NFB: ₹400 Cr total BUT sub-limits A+B = ₹600 Cr — modelled at headline ₹400 Cr.
B61: MED F-06 | C61: Pricing TBD: RBL TL, RBL FDOD, YBL EBLR current value, HSBC, HDFC pre/post-ship rates. | J61: MED F-13 | K61: YES Bank: pre-COD ₹485 Cr cap / post-COD ₹165 Cr tranche — disbursement gate open.
B62: OTH F-08 | C62: HDFC sub-facility rates (WCDL, PSF, Pre-SF, SBLC, CC) TBD at disbursement. | J62: OTH F-14 | K62: Indian Bank: 1st repayment 31-Mar-2027 (1 quarter EARLIER than consortium peers).
B64: Model strictly source-driven from JFL sanction letters + TEV Model. Bucket framework prevents double-counting. Validation Engine confirms integrity. See Management Flags sheet for full detail.

Sheet FY29 Covenant Compliance (TEV)
A1: FY29 COVENANT COMPLIANCE — TEV-SOURCED PROJECTIONS
A2: Source: TEV Financial Model FY29 projections. Market-Practice exceptions: MP-08 (Quasi-Equity), MP-09 (JSL FMV), MP-10 (HSBC Pledge), MP-11 (IDFC DSCR). Full methodology in Notes sheet.
A3: NOTE: All 43 of 44 covenants project COMPLIANT on TEV FY29 projections (first formal test year post-COD). 1 Near Breach: ICICI WC External Rating (at threshold, not breached).
A6: # | B6: Lender | C6: Covenant | D6: Op | E6: Threshold | F6: FY29 Actual | G6: Status | H6: Headroom | L6: Source
A7: 4 | B7: UBI Consortium | C7: DSCR | D7: >= | E7: 1.25 | F7: 1.8008829 | G7: Compliant | H7: +44% | L7: TEV
A8: 5 | C8: FACR | D8: >= | E8: 1.2 | F8: 1.5100186 | G8: Compliant | H8: +26% | L8: TEV
A9: 6 | C9: ISCR | D9: >= | E9: 2 | F9: 3.6548828 | G9: Compliant | H9: +83% | L9: TEV
A10: 7 | C10: LTD/EBITDA | D10: <= | E10: 4 | F10: 2.4944117 | G10: Compliant | H10: +38% | L10: TEV
A11: 8 | C11: LTD/Equity | D11: <= | E11: 2 | F11: 1.0922542 | G11: Compliant | H11: +45% | L11: TEV
A12: 9 | B12: Indian Bank | C12: DSCR (presumed) | D12: >= | E12: 1.25 | F12: 1.8008829 | G12: Compliant | H12: +44% | L12: TEV
A13: 10 | B13: YES Bank | C13: DSCR | D13: >= | E13: 1.25 | F13: 1.8008829 | G13: Compliant | H13: +44% | L13: TEV
A14: 11 | C14: FACR | D14: >= | E14: 1.2 | F14: 1.5100186 | G14: Compliant | H14: +26% | L14: TEV
A15: 12 | C15: ISCR | D15: >= | E15: 2 | F15: 3.6548828 | G15: Compliant | H15: +83% | L15: TEV
A16: 13 | C16: LTD/EBITDA | D16: <= | E16: 4 | F16: 2.4944117 | G16: Compliant | H16: +38% | L16: TEV
A17: 14 | C17: LTD/Equity | D17: <= | E17: 2 | F17: 1.0922542 | G17: Compliant | H17: +45% | L17: TEV
A18: 15 | C18: Cash Sweep Trigger (DSCR) | D18: >= | E18: 1.5 | F18: 1.8008829 | G18: Compliant | H18: +20% | L18: TEV
A19: 16 | B19: IDFC First Bank | C19: DSCR (IDFC) | D19: >= | E19: 1.25 | F19: =('TEV Inputs'!I8 - 'TEV Inputs'!I11 - 'TEV Inputs'!I14) / ('TEV Inputs'!I40 + 'TEV Inputs'!I12) -> 2.0479877 | G19: =IFERROR(IF(D19=">=",IF(F19>=E19,IF((F19-E19)/MAX(ABS(E19),1)>0.1,"Compliant","Near Breach"),"Breached"),IF(F19<=E19,IF((E19-F19)/MAX(ABS(E19),1)>0.1,"Compliant","Near Breach"),"Breached")),"Pending") -> Compliant | H19: +64% | L19: TEV + IDFC SL p.12 (IDFC-specific DSCR formula); MP-11
A20: 17 | C20: FACR | D20: >= | E20: 1.2 | F20: 1.5100186 | G20: Compliant | H20: +26% | L20: TEV
A21: 18 | C21: ISCR | D21: >= | E21: 2 | F21: 3.6548828 | G21: Compliant | H21: +83% | L21: TEV
A22: 19 | C22: LTD/EBITDA | D22: <= | E22: 4 | F22: 2.4944117 | G22: Compliant | H22: +38% | L22: TEV
A23: 20 | C23: LTD/Equity | D23: <= | E23: 2 | F23: 1.0922542 | G23: Compliant | H23: +45% | L23: TEV
A24: 21 | C24: Quasi Equity Cap (₹ Cr) | D24: <= | E24: 337.5 | F24: 0 | G24: Compliant | H24: +100% | L24: MP-08
A25: 22 | B25: ICICI Bank (TL) | C25: DSCR | D25: >= | E25: 1.25 | F25: 1.8008829 | G25: Compliant | H25: +44% | L25: TEV
A26: 23 | C26: FACR | D26: >= | E26: 1.2 | F26: 1.5100186 | G26: Compliant | H26: +26% | L26: TEV
A27: 24 | C27: ISCR | D27: >= | E27: 2 | F27: 3.6548828 | G27: Compliant | H27: +83% | L27: TEV
A28: 25 | C28: LTD/EBITDA | D28: <= | E28: 4 | F28: 2.4944117 | G28: Compliant | H28: +38% | L28: TEV
A29: 26 | C29: LTD/Equity | D29: <= | E29: 2 | F29: 1.0922542 | G29: Compliant | H29: +45% | L29: TEV
A30: 27 | B30: RBL Bank | C30: Min Promoter Contribution (₹ Cr) | D30: >= | E30: 1363 | F30: 2186.35 | G30: Compliant | H30: +60% | L30: TEV (Equity)
A31: 28 | C31: JSL FMV Unencumbered / Total Debt | D31: >= | E31: 2.5 | F31: 11.381328 | G31: Compliant | H31: +355% | L31: MP-09 (NSE)
A32: 29 | C32: External Rating ≥ BBB | D32: >= | E32: 10 | F32: 14 | G32: Compliant | H32: +17% | L32: RBL SL p.11
A33: 30 | B33: ICICI Bank (WC) | C33: Total Debt / EBITDA | D33: <= | E33: 4 | F33: 2.8147719 | G33: Compliant | H33: +30% | L33: TEV
A34: 31 | C34: TOL / TNW | D34: <= | E34: 2.5 | F34: 1.7216136 | G34: Compliant | H34: +31% | L34: TEV
A35: 32 | C35: Current Ratio | D35: >= | E35: 1.1 | F35: 1.8878634 | G35: Compliant | H35: +72% | L35: TEV
A36: 33 | C36: External Rating ≥ A- | D36: >= | E36: 14 | F36: 14 | G36: Near Breach | H36: +0% | L36: CRISIL Jan-25
A37: 35 | B37: HDFC Bank | C37: JSL FMV / Total Debt Cover | D37: >= | E37: 2.5 | F37: 11.381328 | G37: Compliant ⚠ F-15 | H37: +355% | L37: MP-09 ⚠ F-15
A38: 36 | C38: DSCR | D38: >= | E38: 1.25 | F38: 1.8008829 | G38: Compliant | H38: +44% | L38: TEV
A39: 37 | C39: FACR | D39: >= | E39: 1.2 | F39: 1.5100186 | G39: Compliant | H39: +26% | L39: TEV
A40: 38 | C40: ISCR | D40: >= | E40: 2 | F40: 3.6548828 | G40: Compliant | H40: +83% | L40: TEV
A41: 39 | C41: LTD/EBITDA | D41: <= | E41: 4 | F41: 2.4944117 | G41: Compliant | H41: +38% | L41: TEV
A42: 40 | C42: LTD/Equity | D42: <= | E42: 2 | F42: 1.0922542 | G42: Compliant | H42: +45% | L42: TEV
A43: 41 | C43: Total Debt / EBITDA | D43: <= | E43: 4.25 | F43: 2.8147719 | G43: Compliant | H43: +34% | L43: TEV
A44: 43 | B44: HSBC | C44: JSL Listed-Securities Pledge ≤ 40% | D44: <= | E44: 0.4 | F44: 0.1241 | G44: Compliant | H44: +69% | L44: MP-10 (NSE)
A45: 45 | B45: YES Bank | C45: Total Debt / EBITDA | D45: <= | E45: 4.25 | F45: 2.8147719 | G45: Compliant | H45: +34% | L45: TEV
A46: 46 | B46: ICICI Bank (TL) | C46: Total Debt / EBITDA | D46: <= | E46: 4.25 | F46: 2.8147719 | G46: Compliant | H46: +34% | L46: TEV
A47: 47 | B47: Indian Bank | C47: FACR (presumed) | D47: >= | E47: 1.2 | F47: 1.5100186 | G47: Compliant | H47: +26% | L47: TEV
A48: 48 | C48: ISCR (presumed) | D48: >= | E48: 2 | F48: 3.6548828 | G48: Compliant | H48: +83% | L48: TEV
A49: 49 | C49: LTD/EBITDA (presumed) | D49: <= | E49: 4 | F49: 2.4944117 | G49: Compliant | H49: +38% | L49: TEV
A50: 50 | C50: LTD/Equity (presumed) | D50: <= | E50: 2 | F50: 1.0922542 | G50: Compliant | H50: +45% | L50: TEV
A53: SUMMARY
A54: Status | B54: Count | C54: Share
A55: Compliant | B55: 43 | C55: =IFERROR(B55/B59,"—") -> 0.97727273
A56: Near Breach | B56: 1 | C56: =IFERROR(B56/B59,"—") -> 0.022727273
A57: Breached | B57: 0 | C57: =IFERROR(B57/B59,"—") -> 0
A58: Pending Input | B58: 0 | C58: =IFERROR(B58/B59,"—") -> 0
A59: TOTAL | B59: =B55+B56+B57+B58 -> 44 | C59: 1

Sheet Covenant Tracker
A1: COVENANT TRACKER — Financial Covenant Compliance
A2: Actuals from active financials (toggle FinBasis). Status: Compliant / Near Breach / Breached / Not Yet Due. 44 covenants across 9 lenders.
A3: Lender | B3: Covenant | C3: Op | D3: Threshold | E3: Actual | F3: Headroom | G3: Status | H3: Risk | I3: SL Reference | J3: Source Type | K3: Frequency | L3: First Test
A4: UBI | B4: DSCR (consortium) | C4: >= | D4: 1.25 | E4: =IFERROR(INDEX('FY29 Covenant Compliance (TEV)'!F:F,MATCH(M4,'FY29 Covenant Compliance (TEV)'!A:A,0)),"—") -> 1.8008829 | F4: =IFERROR(IF(C4=">=",E4-D4,D4-E4),"—") -> 0.55088295 | G4: =IFERROR(IF(ISTEXT(E4),"Pending Input",IF(F4<0,"Breached",IF(F4<ABS(D4)*0.05,"Near Breach","Compliant"))),"—") -> Compliant | H4: =IFERROR(IF(G4="Breached","Critical",IF(G4="Near Breach","Medium",IF(G4="Compliant","Low","—"))),"—") -> Low | I4: UBI SL 20-Sep-2025 | DSCR ≥ 1.25x | J4: SL ✓ | K4: Annual | L4: FY29 (post-COD) | M4: 4
B5: FACR (consortium) | C5: >= | D5: 1.2 | E5: =IFERROR(INDEX('FY29 Covenant Compliance (TEV)'!F:F,MATCH(M5,'FY29 Covenant Compliance (TEV)'!A:A,0)),"—") -> 1.5100186 | F5: =IFERROR(IF(C5=">=",E5-D5,D5-E5),"—") -> 0.31001863 | G5: =IFERROR(IF(ISTEXT(E5),"Pending Input",IF(F5<0,"Breached",IF(F5<ABS(D5)*0.05,"Near Breach","Compliant"))),"—") -> Compliant | H5: =IFERROR(IF(G5="Breached","Critical",IF(G5="Near Breach","Medium",IF(G5="Compliant","Low","—"))),"—") -> Low | I5: UBI SL 20-Sep-2025 | FACR ≥ 1.20x | J5: SL ✓ | K5: Annual | L5: FY29 (post-COD) | M5: 5
B6: ISCR (consortium) | C6: >= | D6: 2 | E6: =IFERROR(INDEX('FY29 Covenant Compliance (TEV)'!F:F,MATCH(M6,'FY29 Covenant Compliance (TEV)'!A:A,0)),"—") -> 3.6548828 | F6: =IFERROR(IF(C6=">=",E6-D6,D6-E6),"—") -> 1.6548828 | G6: =IFERROR(IF(ISTEXT(E6),"Pending Input",IF(F6<0,"Breached",IF(F6<ABS(D6)*0.05,"Near Breach","Compliant"))),"—") -> Compliant | H6: =IFERROR(IF(G6="Breached","Critical",IF(G6="Near Breach","Medium",IF(G6="Compliant","Low","—"))),"—") -> Low | I6: UBI SL 20-Sep-2025 | ISCR ≥ 2.00x | J6: SL ✓ | K6: Annual | L6: FY29 (post-COD) | M6: 6
B7: LTD / EBITDA (consortium) | C7: <= | D7: 4 | E7: =IFERROR(INDEX('FY29 Covenant Compliance (TEV)'!F:F,MATCH(M7,'FY29 Covenant Compliance (TEV)'!A:A,0)),"—") -> 2.4944117 | F7: =IFERROR(IF(C7=">=",E7-D7,D7-E7),"—") -> 1.5055883 | G7: =IFERROR(IF(ISTEXT(E7),"Pending Input",IF(F7<0,"Breached",IF(F7<ABS(D7)*0.05,"Near Breach","Compliant"))),"—") -> Compliant | H7: =IFERROR(IF(G7="Breached","Critical",IF(G7="Near Breach","Medium",IF(G7="Compliant","Low","—"))),"—") -> Low | I7: UBI SL 20-Sep-2025 | LTD/EBITDA ≤ 4.00x | J7: SL ✓ | K7: Annual | L7: FY29 (post-COD) | M7: 7
B8: LTD / Equity (consortium) | C8: <= | D8: 2 | E8: =IFERROR(INDEX('FY29 Covenant Compliance (TEV)'!F:F,MATCH(M8,'FY29 Covenant Compliance (TEV)'!A:A,0)),"—") -> 1.0922542 | F8: =IFERROR(IF(C8=">=",E8-D8,D8-E8),"—") -> 0.90774579 | G8: =IFERROR(IF(ISTEXT(E8),"Pending Input",IF(F8<0,"Breached",IF(F8<ABS(D8)*0.05,"Near Breach","Compliant"))),"—") -> Compliant | H8: =IFERROR(IF(G8="Breached","Critical",IF(G8="Near Breach","Medium",IF(G8="Compliant","Low","—"))),"—") -> Low | I8: UBI SL 20-Sep-2025 | LTD/Equity ≤ 2.00x | J8: SL ✓ | K8: Annual | L8: FY29 (post-COD) | M8: 8
A9: Indian Bank | B9: DSCR (consortium-presumed) | C9: >= | D9: 1.25 | E9: =IFERROR(INDEX('FY29 Covenant Compliance (TEV)'!F:F,MATCH(M9,'FY29 Covenant Compliance (TEV)'!A:A,0)),"—") -> 1.8008829 | F9: =IFERROR(IF(C9=">=",E9-D9,D9-E9),"—") -> 0.55088295 | G9: =IFERROR(IF(ISTEXT(E9),"Pending Input",IF(F9<0,"Breached",IF(F9<ABS(D9)*0.05,"Near Breach","Compliant"))),"—") -> Compliant | H9: =IFERROR(IF(G9="Breached","Critical",IF(G9="Near Breach","Medium",IF(G9="Compliant","Low","—"))),"—") -> Low | I9: Indian Bank 26-Sep-2025 (amendment only). Consortium-standard DSCR assumed — CONFIRM with Indian Bank. | J9: MP | K9: Annual | L9: FY29 (presumed) | M9: 9
A10: YES Bank | B10: DSCR (consortium) | C10: >= | D10: 1.25 | E10: =IFERROR(INDEX('FY29 Covenant Compliance (TEV)'!F:F,MATCH(M10,'FY29 Covenant Compliance (TEV)'!A:A,0)),"—") -> 1.8008829 | F10: =IFERROR(IF(C10=">=",E10-D10,D10-E10),"—") -> 0.55088295 | G10: =IFERROR(IF(ISTEXT(E10),"Pending Input",IF(F10<0,"Breached",IF(F10<ABS(D10)*0.05,"Near Breach","Compliant"))),"—") -> Compliant | H10: =IFERROR(IF(G10="Breached","Critical",IF(G10="Near Breach","Medium",IF(G10="Compliant","Low","—"))),"—") -> Low | I10: YBL SL 29-Dec-2025 | DSCR ≥ 1.25x | J10: SL ✓ | K10: Annual | L10: FY29 (post-COD) | M10: 10
B11: FACR (consortium) | C11: >= | D11: 1.2 | E11: =IFERROR(INDEX('FY29 Covenant Compliance (TEV)'!F:F,MATCH(M11,'FY29 Covenant Compliance (TEV)'!A:A,0)),"—") -> 1.5100186 | F11: =IFERROR(IF(C11=">=",E11-D11,D11-E11),"—") -> 0.31001863 | G11: =IFERROR(IF(ISTEXT(E11),"Pending Input",IF(F11<0,"Breached",IF(F11<ABS(D11)*0.05,"Near Breach","Compliant"))),"—") -> Compliant | H11: =IFERROR(IF(G11="Breached","Critical",IF(G11="Near Breach","Medium",IF(G11="Compliant","Low","—"))),"—") -> Low | I11: YBL SL 29-Dec-2025 | FACR ≥ 1.20x | J11: SL ✓ | K11: Annual | L11: FY29 (post-COD) | M11: 11
B12: ISCR (consortium) | C12: >= | D12: 2 | E12: =IFERROR(INDEX('FY29 Covenant Compliance (TEV)'!F:F,MATCH(M12,'FY29 Covenant Compliance (TEV)'!A:A,0)),"—") -> 3.6548828 | F12: =IFERROR(IF(C12=">=",E12-D12,D12-E12),"—") -> 1.6548828 | G12: =IFERROR(IF(ISTEXT(E12),"Pending Input",IF(F12<0,"Breached",IF(F12<ABS(D12)*0.05,"Near Breach","Compliant"))),"—") -> Compliant | H12: =IFERROR(IF(G12="Breached","Critical",IF(G12="Near Breach","Medium",IF(G12="Compliant","Low","—"))),"—") -> Low | I12: YBL SL 29-Dec-2025 | ISCR ≥ 2.00x | J12: SL ✓ | K12: Annual | L12: FY29 (post-COD) | M12: 12
B13: LTD / EBITDA (consortium) | C13: <= | D13: 4 | E13: =IFERROR(INDEX('FY29 Covenant Compliance (TEV)'!F:F,MATCH(M13,'FY29 Covenant Compliance (TEV)'!A:A,0)),"—") -> 2.4944117 | F13: =IFERROR(IF(C13=">=",E13-D13,D13-E13),"—") -> 1.5055883 | G13: =IFERROR(IF(ISTEXT(E13),"Pending Input",IF(F13<0,"Breached",IF(F13<ABS(D13)*0.05,"Near Breach","Compliant"))),"—") -> Compliant | H13: =IFERROR(IF(G13="Breached","Critical",IF(G13="Near Breach","Medium",IF(G13="Compliant","Low","—"))),"—") -> Low | I13: YBL SL 29-Dec-2025 | LTD/EBITDA ≤ 4.00x | J13: SL ✓ | K13: Annual | L13: FY29 (post-COD) | M13: 13
B14: LTD / Equity (consortium) | C14: <= | D14: 2 | E14: =IFERROR(INDEX('FY29 Covenant Compliance (TEV)'!F:F,MATCH(M14,'FY29 Covenant Compliance (TEV)'!A:A,0)),"—") -> 1.0922542 | F14: =IFERROR(IF(C14=">=",E14-D14,D14-E14),"—") -> 0.90774579 | G14: =IFERROR(IF(ISTEXT(E14),"Pending Input",IF(F14<0,"Breached",IF(F14<ABS(D14)*0.05,"Near Breach","Compliant"))),"—") -> Compliant | H14: =IFERROR(IF(G14="Breached","Critical",IF(G14="Near Breach","Medium",IF(G14="Compliant","Low","—"))),"—") -> Low | I14: YBL SL 29-Dec-2025 | LTD/Equity ≤ 2.00x | J14: SL ✓ | K14: Annual | L14: FY29 (post-COD) | M14: 14
B15: Cash Sweep Trigger (DSCR) | C15: >= | D15: 1.5 | E15: =IFERROR(INDEX('FY29 Covenant Compliance (TEV)'!F:F,MATCH(M15,'FY29 Covenant Compliance (TEV)'!A:A,0)),"—") -> 1.8008829 | F15: =IFERROR(IF(C15=">=",E15-D15,D15-E15),"—") -> 0.30088295 | G15: =IFERROR(IF(ISTEXT(E15),"Pending Input",IF(F15<0,"Breached",IF(F15<ABS(D15)*0.05,"Near Breach","Compliant"))),"—") -> Compliant | H15: =IFERROR(IF(G15="Breached","Critical",IF(G15="Near Breach","Medium",IF(G15="Compliant","Low","—"))),"—") -> Low | I15: YBL SL 29-Dec-2025 | Cash Sweep: DSCR > 1.5x triggers ₹75 Cr/yr sweep from 01-Apr-2028 | J15: SL ✓ | K15: 12-mo rolling | L15: 01-Apr-2028 (2yr post-COD) | M15: 15
A16: IDFC First Bank | B16: DSCR (IDFC-specific) | C16: >= | D16: 1.25 | E16: =IFERROR(INDEX('FY29 Covenant Compliance (TEV)'!F:F,MATCH(M16,'FY29 Covenant Compliance (TEV)'!A:A,0)),"—") -> 2.0479877 | F16: =IFERROR(IF(C16=">=",E16-D16,D16-E16),"—") -> 0.79798767 | G16: =IFERROR(IF(ISTEXT(E16),"Pending Input",IF(F16<0,"Breached",IF(F16<ABS(D16)*0.05,"Near Breach","Compliant"))),"—") -> Compliant | H16: =IFERROR(IF(G16="Breached","Critical",IF(G16="Near Breach","Medium",IF(G16="Compliant","Low","—"))),"—") -> Low | I16: IDFC SL 09-Jan-2026 | DSCR ≥ 1.25x — IDFC-specific formula; first test FY27 (2yr earlier) — FLAG | J16: SL ✓ | K16: Annual | L16: FY27 (2yr earlier — FLAG) | M16: 16
B17: FACR (consortium) | C17: >= | D17: 1.2 | E17: =IFERROR(INDEX('FY29 Covenant Compliance (TEV)'!F:F,MATCH(M17,'FY29 Covenant Compliance (TEV)'!A:A,0)),"—") -> 1.5100186 | F17: =IFERROR(IF(C17=">=",E17-D17,D17-E17),"—") -> 0.31001863 | G17: =IFERROR(IF(ISTEXT(E17),"Pending Input",IF(F17<0,"Breached",IF(F17<ABS(D17)*0.05,"Near Breach","Compliant"))),"—") -> Compliant | H17: =IFERROR(IF(G17="Breached","Critical",IF(G17="Near Breach","Medium",IF(G17="Compliant","Low","—"))),"—") -> Low | I17: IDFC SL 09-Jan-2026 | FACR ≥ 1.20x | First test FY27 | J17: SL ✓ | K17: Annual | L17: FY27 | M17: 17
B18: ISCR (consortium) | C18: >= | D18: 2 | E18: =IFERROR(INDEX('FY29 Covenant Compliance (TEV)'!F:F,MATCH(M18,'FY29 Covenant Compliance (TEV)'!A:A,0)),"—") -> 3.6548828 | F18: =IFERROR(IF(C18=">=",E18-D18,D18-E18),"—") -> 1.6548828 | G18: =IFERROR(IF(ISTEXT(E18),"Pending Input",IF(F18<0,"Breached",IF(F18<ABS(D18)*0.05,"Near Breach","Compliant"))),"—") -> Compliant | H18: =IFERROR(IF(G18="Breached","Critical",IF(G18="Near Breach","Medium",IF(G18="Compliant","Low","—"))),"—") -> Low | I18: IDFC SL 09-Jan-2026 | ISCR ≥ 2.00x | First test FY27 | J18: SL ✓ | K18: Annual | L18: FY27 | M18: 18
B19: LTD / EBITDA (consortium) | C19: <= | D19: 4 | E19: =IFERROR(INDEX('FY29 Covenant Compliance (TEV)'!F:F,MATCH(M19,'FY29 Covenant Compliance (TEV)'!A:A,0)),"—") -> 2.4944117 | F19: =IFERROR(IF(C19=">=",E19-D19,D19-E19),"—") -> 1.5055883 | G19: =IFERROR(IF(ISTEXT(E19),"Pending Input",IF(F19<0,"Breached",IF(F19<ABS(D19)*0.05,"Near Breach","Compliant"))),"—") -> Compliant | H19: =IFERROR(IF(G19="Breached","Critical",IF(G19="Near Breach","Medium",IF(G19="Compliant","Low","—"))),"—") -> Low | I19: IDFC SL 09-Jan-2026 | LTD/EBITDA ≤ 4.00x | First test FY27 | J19: SL ✓ | K19: Annual | L19: FY27 | M19: 19
B20: LTD / Equity (consortium) | C20: <= | D20: 2 | E20: =IFERROR(INDEX('FY29 Covenant Compliance (TEV)'!F:F,MATCH(M20,'FY29 Covenant Compliance (TEV)'!A:A,0)),"—") -> 1.0922542 | F20: =IFERROR(IF(C20=">=",E20-D20,D20-E20),"—") -> 0.90774579 | G20: =IFERROR(IF(ISTEXT(E20),"Pending Input",IF(F20<0,"Breached",IF(F20<ABS(D20)*0.05,"Near Breach","Compliant"))),"—") -> Compliant | H20: =IFERROR(IF(G20="Breached","Critical",IF(G20="Near Breach","Medium",IF(G20="Compliant","Low","—"))),"—") -> Low | I20: IDFC SL 09-Jan-2026 | LTD/Equity ≤ 2.00x | First test FY27 | J20: SL ✓ | K20: Annual | L20: FY27 | M20: 20
B21: Quasi Equity Cap (Cr) | C21: <= | D21: 337.5 | E21: =IFERROR(INDEX('FY29 Covenant Compliance (TEV)'!F:F,MATCH(M21,'FY29 Covenant Compliance (TEV)'!A:A,0)),"—") -> 0 | F21: =IFERROR(IF(C21=">=",E21-D21,D21-E21),"—") -> 337.5 | G21: =IFERROR(IF(ISTEXT(E21),"Pending Input",IF(F21<0,"Breached",IF(F21<ABS(D21)*0.05,"Near Breach","Compliant"))),"—") -> Compliant | H21: =IFERROR(IF(G21="Breached","Critical",IF(G21="Near Breach","Medium",IF(G21="Compliant","Low","—"))),"—") -> Low | I21: IDFC SL 09-Jan-2026 | Quasi-Equity Cap ₹337.5 Cr. Actual ₹856.76 Cr (Audit Note 16+18: Jindal Coke ₹28.15 Cr + JSL ₹701.61 Cr + Virtuous ₹127.00 Cr). ICDs NOT formally subordinated — CONFIRM with IDFC whether bank applies equity-only test. | J21: MP ⚠ | K21: Continuous monitoring | L21: Ongoing from disbursement | M21: 21
A22: ICICI Bank (TL) | B22: DSCR (consortium) | C22: >= | D22: 1.25 | E22: =IFERROR(INDEX('FY29 Covenant Compliance (TEV)'!F:F,MATCH(M22,'FY29 Covenant Compliance (TEV)'!A:A,0)),"—") -> 1.8008829 | F22: =IFERROR(IF(C22=">=",E22-D22,D22-E22),"—") -> 0.55088295 | G22: =IFERROR(IF(ISTEXT(E22),"Pending Input",IF(F22<0,"Breached",IF(F22<ABS(D22)*0.05,"Near Breach","Compliant"))),"—") -> Compliant | H22: =IFERROR(IF(G22="Breached","Critical",IF(G22="Near Breach","Medium",IF(G22="Compliant","Low","—"))),"—") -> Low | I22: ICICI TL CAL 27-Mar-2026 | DSCR ≥ 1.25x | J22: SL ✓ | K22: Annual | L22: FY29 (within 120d of FY-end) | M22: 22
B23: FACR (consortium) | C23: >= | D23: 1.2 | E23: =IFERROR(INDEX('FY29 Covenant Compliance (TEV)'!F:F,MATCH(M23,'FY29 Covenant Compliance (TEV)'!A:A,0)),"—") -> 1.5100186 | F23: =IFERROR(IF(C23=">=",E23-D23,D23-E23),"—") -> 0.31001863 | G23: =IFERROR(IF(ISTEXT(E23),"Pending Input",IF(F23<0,"Breached",IF(F23<ABS(D23)*0.05,"Near Breach","Compliant"))),"—") -> Compliant | H23: =IFERROR(IF(G23="Breached","Critical",IF(G23="Near Breach","Medium",IF(G23="Compliant","Low","—"))),"—") -> Low | I23: ICICI TL CAL 27-Mar-2026 | FACR ≥ 1.20x | J23: SL ✓ | K23: Annual | L23: FY29 | M23: 23
B24: ISCR (consortium) | C24: >= | D24: 2 | E24: =IFERROR(INDEX('FY29 Covenant Compliance (TEV)'!F:F,MATCH(M24,'FY29 Covenant Compliance (TEV)'!A:A,0)),"—") -> 3.6548828 | F24: =IFERROR(IF(C24=">=",E24-D24,D24-E24),"—") -> 1.6548828 | G24: =IFERROR(IF(ISTEXT(E24),"Pending Input",IF(F24<0,"Breached",IF(F24<ABS(D24)*0.05,"Near Breach","Compliant"))),"—") -> Compliant | H24: =IFERROR(IF(G24="Breached","Critical",IF(G24="Near Breach","Medium",IF(G24="Compliant","Low","—"))),"—") -> Low | I24: ICICI TL CAL 27-Mar-2026 | ISCR ≥ 2.00x | J24: SL ✓ | K24: Annual | L24: FY29 | M24: 24
B25: LTD / EBITDA (consortium) | C25: <= | D25: 4 | E25: =IFERROR(INDEX('FY29 Covenant Compliance (TEV)'!F:F,MATCH(M25,'FY29 Covenant Compliance (TEV)'!A:A,0)),"—") -> 2.4944117 | F25: =IFERROR(IF(C25=">=",E25-D25,D25-E25),"—") -> 1.5055883 | G25: =IFERROR(IF(ISTEXT(E25),"Pending Input",IF(F25<0,"Breached",IF(F25<ABS(D25)*0.05,"Near Breach","Compliant"))),"—") -> Compliant | H25: =IFERROR(IF(G25="Breached","Critical",IF(G25="Near Breach","Medium",IF(G25="Compliant","Low","—"))),"—") -> Low | I25: ICICI TL CAL 27-Mar-2026 | LTD/EBITDA ≤ 4.00x | J25: SL ✓ | K25: Annual | L25: FY29 | M25: 25
B26: LTD / Equity (consortium) | C26: <= | D26: 2 | E26: =IFERROR(INDEX('FY29 Covenant Compliance (TEV)'!F:F,MATCH(M26,'FY29 Covenant Compliance (TEV)'!A:A,0)),"—") -> 1.0922542 | F26: =IFERROR(IF(C26=">=",E26-D26,D26-E26),"—") -> 0.90774579 | G26: =IFERROR(IF(ISTEXT(E26),"Pending Input",IF(F26<0,"Breached",IF(F26<ABS(D26)*0.05,"Near Breach","Compliant"))),"—") -> Compliant | H26: =IFERROR(IF(G26="Breached","Critical",IF(G26="Near Breach","Medium",IF(G26="Compliant","Low","—"))),"—") -> Low | I26: ICICI TL CAL 27-Mar-2026 | LTD/Equity ≤ 2.00x | J26: SL ✓ | K26: Annual | L26: FY29 | M26: 26
A27: RBL Bank | B27: Min Promoter Contribution (Cr) | C27: >= | D27: 1363 | E27: =IFERROR(INDEX('FY29 Covenant Compliance (TEV)'!F:F,MATCH(M27,'FY29 Covenant Compliance (TEV)'!A:A,0)),"—") -> 2186.35 | F27: =IFERROR(IF(C27=">=",E27-D27,D27-E27),"—") -> 823.35 | G27: =IFERROR(IF(ISTEXT(E27),"Pending Input",IF(F27<0,"Breached",IF(F27<ABS(D27)*0.05,"Near Breach","Compliant"))),"—") -> Compliant | H27: =IFERROR(IF(G27="Breached","Critical",IF(G27="Near Breach","Medium",IF(G27="Compliant","Low","—"))),"—") -> Low | I27: RBL SL 13-Nov-2025 | Min ₹1,363 Cr promoter contribution. Actual ₹1,850.21 Cr (equity ₹993.45 Cr + ICDs ₹856.76 Cr). CAVEAT: equity-only = ₹993.45 Cr < threshold → potential breach. CONFIRM with RBL. | J27: MP ⚠ | K27: At disbursement & periodic | L27: Within 180d of disbursement | M27: 27
B28: JSL FMV Unencumbered / Total Debt | C28: >= | D28: 2.5 | E28: =IFERROR(INDEX('FY29 Covenant Compliance (TEV)'!F:F,MATCH(M28,'FY29 Covenant Compliance (TEV)'!A:A,0)),"—") -> 11.381328 | F28: =IFERROR(IF(C28=">=",E28-D28,D28-E28),"—") -> 8.881328 | G28: =IFERROR(IF(ISTEXT(E28),"Pending Input",IF(F28<0,"Breached",IF(F28<ABS(D28)*0.05,"Near Breach","Compliant"))),"—") -> Compliant | H28: =IFERROR(IF(G28="Breached","Critical",IF(G28="Near Breach","Medium",IF(G28="Compliant","Low","—"))),"—") -> Low | I28: RBL SL 13-Nov-2025 | JSL FMV (unencumbered) ÷ Total RBL debt ≥ 2.5x. Requires live NSE data. | J28: SL ✓ | K28: Continuous monitoring | L28: Ongoing from disbursement | M28: 28
B29: Min External Rating | C29: >= | D29: 10 | E29: =IFERROR(INDEX('FY29 Covenant Compliance (TEV)'!F:F,MATCH(M29,'FY29 Covenant Compliance (TEV)'!A:A,0)),"—") -> 14 | F29: =IFERROR(IF(C29=">=",E29-D29,D29-E29),"—") -> 4 | G29: =IFERROR(IF(ISTEXT(E29),"Pending Input",IF(F29<0,"Breached",IF(F29<ABS(D29)*0.05,"Near Breach","Compliant"))),"—") -> Compliant | H29: =IFERROR(IF(G29="Breached","Critical",IF(G29="Near Breach","Medium",IF(G29="Compliant","Low","—"))),"—") -> Low | I29: RBL SL p.11 | Rating ≥ BBB (= numeric 10). NOT BBB+ (=12). Within 180d of disbursement. | J29: SL ✓ | K29: On rating event | L29: Within 180d of disbursement | M29: 29
A30: ICICI Bank | B30: Total Debt / EBITDA (WC) | C30: <= | D30: 4 | E30: =IFERROR(INDEX('FY29 Covenant Compliance (TEV)'!F:F,MATCH(M30,'FY29 Covenant Compliance (TEV)'!A:A,0)),"—") -> 2.8147719 | F30: =IFERROR(IF(C30=">=",E30-D30,D30-E30),"—") -> 1.1852281 | G30: =IFERROR(IF(ISTEXT(E30),"Pending Input",IF(F30<0,"Breached",IF(F30<ABS(D30)*0.05,"Near Breach","Compliant"))),"—") -> Compliant | H30: =IFERROR(IF(G30="Breached","Critical",IF(G30="Near Breach","Medium",IF(G30="Compliant","Low","—"))),"—") -> Low | I30: ICICI WC CAL 12-Feb-2026 | Total Debt/EBITDA ≤ 4.00x | J30: SL ✓ | K30: Annual / on review | L30: Annual review 03-Feb-2027 | M30: 30
B31: TOL / TNW (WC) | C31: <= | D31: 2.5 | E31: =IFERROR(INDEX('FY29 Covenant Compliance (TEV)'!F:F,MATCH(M31,'FY29 Covenant Compliance (TEV)'!A:A,0)),"—") -> 1.7216136 | F31: =IFERROR(IF(C31=">=",E31-D31,D31-E31),"—") -> 0.77838635 | G31: =IFERROR(IF(ISTEXT(E31),"Pending Input",IF(F31<0,"Breached",IF(F31<ABS(D31)*0.05,"Near Breach","Compliant"))),"—") -> Compliant | H31: =IFERROR(IF(G31="Breached","Critical",IF(G31="Near Breach","Medium",IF(G31="Compliant","Low","—"))),"—") -> Low | I31: ICICI WC CAL 12-Feb-2026 | TOL/TNW ≤ 2.50x | J31: SL ✓ | K31: Annual / on review | L31: Annual review 03-Feb-2027 | M31: 31
B32: Current Ratio (WC) | C32: >= | D32: 1.1 | E32: =IFERROR(INDEX('FY29 Covenant Compliance (TEV)'!F:F,MATCH(M32,'FY29 Covenant Compliance (TEV)'!A:A,0)),"—") -> 1.8878634 | F32: =IFERROR(IF(C32=">=",E32-D32,D32-E32),"—") -> 0.78786337 | G32: =IFERROR(IF(ISTEXT(E32),"Pending Input",IF(F32<0,"Breached",IF(F32<ABS(D32)*0.05,"Near Breach","Compliant"))),"—") -> Compliant | H32: =IFERROR(IF(G32="Breached","Critical",IF(G32="Near Breach","Medium",IF(G32="Compliant","Low","—"))),"—") -> Low | I32: ICICI WC CAL 12-Feb-2026 | Current Ratio ≥ 1.10x | J32: SL ✓ | K32: Annual / on review | L32: Annual review 03-Feb-2027 | M32: 32
B33: External Rating (WC) | C33: >= | D33: 14 | E33: =IFERROR(INDEX('FY29 Covenant Compliance (TEV)'!F:F,MATCH(M33,'FY29 Covenant Compliance (TEV)'!A:A,0)),"—") -> 14 | F33: =IFERROR(IF(C33=">=",E33-D33,D33-E33),"—") -> 0 | G33: =IFERROR(IF(ISTEXT(E33),"Pending Input",IF(F33<0,"Breached",IF(F33<ABS(D33)*0.05,"Near Breach","Compliant"))),"—") -> Near Breach | H33: =IFERROR(IF(G33="Breached","Critical",IF(G33="Near Breach","Medium",IF(G33="Compliant","Low","—"))),"—") -> Medium | I33: ICICI WC CAL 12-Feb-2026 | Rating ≥ A- (= numeric 14). At threshold — Near Breach. Upgrade required to clear. | J33: SL ✓ | K33: On rating event | L33: Annual review 03-Feb-2027 | M33: 33
A34: HDFC Bank | B34: JSL FMV / Total Debt Cover | C34: >= | D34: 2.5 | E34: =IFERROR(INDEX('FY29 Covenant Compliance (TEV)'!F:F,MATCH(M34,'FY29 Covenant Compliance (TEV)'!A:A,0)),"—") -> 11.381328 | F34: =IFERROR(IF(C34=">=",E34-D34,D34-E34),"—") -> 8.881328 | G34: =IFERROR(IF(ISTEXT(E34),"Pending Input",IF(F34<0,"Breached",IF(F34<ABS(D34)*0.05,"Near Breach","Compliant"))),"—") -> Compliant | H34: =IFERROR(IF(G34="Breached","Critical",IF(G34="Near Breach","Medium",IF(G34="Compliant","Low","—"))),"—") -> Low | I34: HDFC 26-Mar-2026 | JSL FMV ÷ Total HDFC debt ≥ 2.5x. Requires live NSE data. ⚠ F-15: covenant not confirmed in offer letter — Treasury to verify. | J34: SL ✓ | K34: Continuous monitoring | L34: Ongoing from disbursement | M34: 35
B35: DSCR (consortium) | C35: >= | D35: 1.25 | E35: =IFERROR(INDEX('FY29 Covenant Compliance (TEV)'!F:F,MATCH(M35,'FY29 Covenant Compliance (TEV)'!A:A,0)),"—") -> 1.8008829 | F35: =IFERROR(IF(C35=">=",E35-D35,D35-E35),"—") -> 0.55088295 | G35: =IFERROR(IF(ISTEXT(E35),"Pending Input",IF(F35<0,"Breached",IF(F35<ABS(D35)*0.05,"Near Breach","Compliant"))),"—") -> Compliant | H35: =IFERROR(IF(G35="Breached","Critical",IF(G35="Near Breach","Medium",IF(G35="Compliant","Low","—"))),"—") -> Low | I35: HDFC 26-Mar-2026 | DSCR ≥ 1.25x | J35: SL ✓ | K35: Annual | L35: FY29 (post-COD) | M35: 36
B36: FACR (consortium) | C36: >= | D36: 1.2 | E36: =IFERROR(INDEX('FY29 Covenant Compliance (TEV)'!F:F,MATCH(M36,'FY29 Covenant Compliance (TEV)'!A:A,0)),"—") -> 1.5100186 | F36: =IFERROR(IF(C36=">=",E36-D36,D36-E36),"—") -> 0.31001863 | G36: =IFERROR(IF(ISTEXT(E36),"Pending Input",IF(F36<0,"Breached",IF(F36<ABS(D36)*0.05,"Near Breach","Compliant"))),"—") -> Compliant | H36: =IFERROR(IF(G36="Breached","Critical",IF(G36="Near Breach","Medium",IF(G36="Compliant","Low","—"))),"—") -> Low | I36: HDFC 26-Mar-2026 | FACR ≥ 1.20x | J36: SL ✓ | K36: Annual | L36: FY29 (post-COD) | M36: 37
B37: ISCR (consortium) | C37: >= | D37: 2 | E37: =IFERROR(INDEX('FY29 Covenant Compliance (TEV)'!F:F,MATCH(M37,'FY29 Covenant Compliance (TEV)'!A:A,0)),"—") -> 3.6548828 | F37: =IFERROR(IF(C37=">=",E37-D37,D37-E37),"—") -> 1.6548828 | G37: =IFERROR(IF(ISTEXT(E37),"Pending Input",IF(F37<0,"Breached",IF(F37<ABS(D37)*0.05,"Near Breach","Compliant"))),"—") -> Compliant | H37: =IFERROR(IF(G37="Breached","Critical",IF(G37="Near Breach","Medium",IF(G37="Compliant","Low","—"))),"—") -> Low | I37: HDFC 26-Mar-2026 | ISCR ≥ 2.00x | J37: SL ✓ | K37: Annual | L37: FY29 (post-COD) | M37: 38
B38: LTD / EBITDA (consortium) | C38: <= | D38: 4 | E38: =IFERROR(INDEX('FY29 Covenant Compliance (TEV)'!F:F,MATCH(M38,'FY29 Covenant Compliance (TEV)'!A:A,0)),"—") -> 2.4944117 | F38: =IFERROR(IF(C38=">=",E38-D38,D38-E38),"—") -> 1.5055883 | G38: =IFERROR(IF(ISTEXT(E38),"Pending Input",IF(F38<0,"Breached",IF(F38<ABS(D38)*0.05,"Near Breach","Compliant"))),"—") -> Compliant | H38: =IFERROR(IF(G38="Breached","Critical",IF(G38="Near Breach","Medium",IF(G38="Compliant","Low","—"))),"—") -> Low | I38: HDFC 26-Mar-2026 | LTD/EBITDA ≤ 4.00x | J38: SL ✓ | K38: Annual | L38: FY29 (post-COD) | M38: 39
B39: LTD / Equity (consortium) | C39: <= | D39: 2 | E39: =IFERROR(INDEX('FY29 Covenant Compliance (TEV)'!F:F,MATCH(M39,'FY29 Covenant Compliance (TEV)'!A:A,0)),"—") -> 1.0922542 | F39: =IFERROR(IF(C39=">=",E39-D39,D39-E39),"—") -> 0.90774579 | G39: =IFERROR(IF(ISTEXT(E39),"Pending Input",IF(F39<0,"Breached",IF(F39<ABS(D39)*0.05,"Near Breach","Compliant"))),"—") -> Compliant | H39: =IFERROR(IF(G39="Breached","Critical",IF(G39="Near Breach","Medium",IF(G39="Compliant","Low","—"))),"—") -> Low | I39: HDFC 26-Mar-2026 | LTD/Equity ≤ 2.00x | J39: SL ✓ | K39: Annual | L39: FY29 (post-COD) | M39: 40
B40: Total Debt / EBITDA | C40: <= | D40: 4.25 | E40: =IFERROR(INDEX('FY29 Covenant Compliance (TEV)'!F:F,MATCH(M40,'FY29 Covenant Compliance (TEV)'!A:A,0)),"—") -> 2.8147719 | F40: =IFERROR(IF(C40=">=",E40-D40,D40-E40),"—") -> 1.4352281 | G40: =IFERROR(IF(ISTEXT(E40),"Pending Input",IF(F40<0,"Breached",IF(F40<ABS(D40)*0.05,"Near Breach","Compliant"))),"—") -> Compliant | H40: =IFERROR(IF(G40="Breached","Critical",IF(G40="Near Breach","Medium",IF(G40="Compliant","Low","—"))),"—") -> Low | I40: HDFC 26-Mar-2026 | Total Debt/EBITDA ≤ 4.25x | J40: SL ✓ | K40: Annual | L40: FY29 (post-COD) | M40: 41
A41: HSBC | B41: JSL Listed-Securities Cap (40%) | C41: <= | D41: 0.4 | E41: =IFERROR(INDEX('FY29 Covenant Compliance (TEV)'!F:F,MATCH(M41,'FY29 Covenant Compliance (TEV)'!A:A,0)),"—") -> 0.1241 | F41: =IFERROR(IF(C41=">=",E41-D41,D41-E41),"—") -> 0.2759 | G41: =IFERROR(IF(ISTEXT(E41),"Pending Input",IF(F41<0,"Breached",IF(F41<ABS(D41)*0.05,"Near Breach","Compliant"))),"—") -> Compliant | H41: =IFERROR(IF(G41="Breached","Critical",IF(G41="Near Breach","Medium",IF(G41="Compliant","Low","—"))),"—") -> Low | I41: HSBC FL 27-Feb-2026 | Pledge ≤ 40% of JSL FMV. Requires live NSE data. | J41: SL ✓ | K41: Continuous monitoring | L41: Ongoing from disbursement | M41: 43
A42: YES Bank | B42: Total Debt / EBITDA | C42: <= | D42: 4.25 | E42: =IFERROR(INDEX('FY29 Covenant Compliance (TEV)'!F:F,MATCH(M42,'FY29 Covenant Compliance (TEV)'!A:A,0)),"—") -> 2.8147719 | F42: =IFERROR(IF(C42=">=",E42-D42,D42-E42),"—") -> 1.4352281 | G42: =IFERROR(IF(ISTEXT(E42),"Pending Input",IF(F42<0,"Breached",IF(F42<ABS(D42)*0.05,"Near Breach","Compliant"))),"—") -> Compliant | H42: =IFERROR(IF(G42="Breached","Critical",IF(G42="Near Breach","Medium",IF(G42="Compliant","Low","—"))),"—") -> Low | I42: YBL FL 30-Dec-2025 | Total Debt/EBITDA ≤ 4.25x | J42: SL ✓ | K42: Annual | L42: FY29 (post-COD) | M42: 45
B43: Total Debt / EBITDA | C43: <= | D43: 4.25 | E43: =IFERROR(INDEX('FY29 Covenant Compliance (TEV)'!F:F,MATCH(M43,'FY29 Covenant Compliance (TEV)'!A:A,0)),"—") -> 2.8147719 | F43: =IFERROR(IF(C43=">=",E43-D43,D43-E43),"—") -> 1.4352281 | G43: =IFERROR(IF(ISTEXT(E43),"Pending Input",IF(F43<0,"Breached",IF(F43<ABS(D43)*0.05,"Near Breach","Compliant"))),"—") -> Compliant | H43: =IFERROR(IF(G43="Breached","Critical",IF(G43="Near Breach","Medium",IF(G43="Compliant","Low","—"))),"—") -> Low | I43: ICICI TL CAL 27-Mar-2026 | Total Debt/EBITDA ≤ 4.25x | J43: SL ✓ | K43: Annual | L43: FY29 (post-COD) | M43: 46
A44: Indian Bank | B44: FACR (consortium-presumed) | C44: >= | D44: 1.2 | E44: =IFERROR(INDEX('FY29 Covenant Compliance (TEV)'!F:F,MATCH(M44,'FY29 Covenant Compliance (TEV)'!A:A,0)),"—") -> 1.5100186 | F44: =IFERROR(IF(C44=">=",E44-D44,D44-E44),"—") -> 0.31001863 | G44: =IFERROR(IF(ISTEXT(E44),"Pending Input",IF(F44<0,"Breached",IF(F44<ABS(D44)*0.05,"Near Breach","Compliant"))),"—") -> Compliant | H44: =IFERROR(IF(G44="Breached","Critical",IF(G44="Near Breach","Medium",IF(G44="Compliant","Low","—"))),"—") -> Low | I44: Indian Bank (amendment only). Consortium-standard FACR assumed — CONFIRM with Indian Bank. | J44: MP | K44: Annual | L44: FY29 (presumed) | M44: 47
A45: Indian Bank | B45: ISCR (consortium-presumed) | C45: >= | D45: 2 | E45: =IFERROR(INDEX('FY29 Covenant Compliance (TEV)'!F:F,MATCH(M45,'FY29 Covenant Compliance (TEV)'!A:A,0)),"—") -> 3.6548828 | F45: =IFERROR(IF(C45=">=",E45-D45,D45-E45),"—") -> 1.6548828 | G45: =IFERROR(IF(ISTEXT(E45),"Pending Input",IF(F45<0,"Breached",IF(F45<ABS(D45)*0.05,"Near Breach","Compliant"))),"—") -> Compliant | H45: =IFERROR(IF(G45="Breached","Critical",IF(G45="Near Breach","Medium",IF(G45="Compliant","Low","—"))),"—") -> Low | I45: Indian Bank (amendment only). Consortium-standard ISCR assumed. | J45: MP | K45: Annual | L45: FY29 (presumed) | M45: 48
B46: LTD / EBITDA (consortium-presumed) | C46: <= | D46: 4 | E46: =IFERROR(INDEX('FY29 Covenant Compliance (TEV)'!F:F,MATCH(M46,'FY29 Covenant Compliance (TEV)'!A:A,0)),"—") -> 2.4944117 | F46: =IFERROR(IF(C46=">=",E46-D46,D46-E46),"—") -> 1.5055883 | G46: =IFERROR(IF(ISTEXT(E46),"Pending Input",IF(F46<0,"Breached",IF(F46<ABS(D46)*0.05,"Near Breach","Compliant"))),"—") -> Compliant | H46: =IFERROR(IF(G46="Breached","Critical",IF(G46="Near Breach","Medium",IF(G46="Compliant","Low","—"))),"—") -> Low | I46: Indian Bank (amendment only). Consortium-standard LTD/EBITDA assumed. | J46: MP | K46: Annual | L46: FY29 (presumed) | M46: 49
B47: LTD / Equity (consortium-presumed) | C47: <= | D47: 2 | E47: =IFERROR(INDEX('FY29 Covenant Compliance (TEV)'!F:F,MATCH(M47,'FY29 Covenant Compliance (TEV)'!A:A,0)),"—") -> 1.0922542 | F47: =IFERROR(IF(C47=">=",E47-D47,D47-E47),"—") -> 0.90774579 | G47: =IFERROR(IF(ISTEXT(E47),"Pending Input",IF(F47<0,"Breached",IF(F47<ABS(D47)*0.05,"Near Breach","Compliant"))),"—") -> Compliant | H47: =IFERROR(IF(G47="Breached","Critical",IF(G47="Near Breach","Medium",IF(G47="Compliant","Low","—"))),"—") -> Low | I47: Indian Bank (amendment only). Consortium-standard LTD/Equity assumed. | J47: MP | K47: Annual | L47: FY29 (presumed) | M47: 50
A49: COVENANT SUMMARY
A50: Category | B50: Count | C50: Share
A51: Total Covenants | B51: =COUNTA(A4:A47) -> 44 | C51: —
A52: Live — Compliant | B52: =COUNTIF(G4:G47,"Compliant") -> 43 | C52: =IFERROR(B52/B51,"—") -> 0.97727273
A53: Live — Near Breach | B53: =COUNTIF(G4:G47,"Near Breach") -> 1 | C53: =IFERROR(B53/B51,"—") -> 0.022727273
A54: Live — Breached | B54: =COUNTIF(G4:G47,"Breached") -> 0 | C54: =IFERROR(B54/B51,"—") -> 0
A55: Live — Pending | B55: =COUNTIF(G4:G47,"Pending Input") -> 0 | C55: =IFERROR(B55/B51,"—") -> 0
A56: Not Yet Due | B56: =COUNTIF(G4:G47,"Not Yet Due") -> 0 | C56: =IFERROR(B56/B51,"—") -> 0
A57: Live Compliance % | B57: =IFERROR(B52/(B52+B53+B54),0) -> 0.97727273

Sheet Lender Summary
A1: LENDER SUMMARY — Multi-Bucket Debt Profile
A2: Sanctioned Debt = Bucket 1 (FB Mains) + Bucket 2 (NFB Mains) | Adjusted Consortium = Sanctioned − ICICI TL takeover (₹840 Cr) | Bucket 3 (FD-Backed) and Bucket 4 (Uncommitted) tracked separately.
A4: A. SANCTIONED DEBT — Bucket 1 (FB Mains) + Bucket 2 (NFB Mains)
A5: Lender | B5: FB Mains (₹ Cr) | C5: NFB Mains (₹ Cr) | D5: Sanctioned (₹ Cr) | E5: % of Total | F5: Facilities (B1+B2) | G5: NFB Contingent (₹ Cr)
A6: UBI | B6: =SUMIFS('Facility Master'!$K:$K, 'Facility Master'!$B:$B, $A6, 'Facility Master'!$H:$H, 1) -> 1361 | C6: =SUMIFS('Facility Master'!$K:$K, 'Facility Master'!$B:$B, $A6, 'Facility Master'!$H:$H, 2) -> 0 | D6: =B6+C6 -> 1361 | E6: =D6/D$15 -> 0.29168453 | F6: =COUNTIFS('Facility Master'!$B:$B, $A6, 'Facility Master'!$H:$H, ">=1", 'Facility Master'!$H:$H, "<=2") -> 2 | G6: =SUMIFS('Facility Master'!$K:$K, 'Facility Master'!$B:$B, $A6, 'Facility Master'!$H:$H, 2) + SUMIFS('Facility Master'!$K:$K, 'Facility Master'!$B:$B, $A6, 'Facility Master'!$AG:$AG, TRUE()) -> 750
A7: Indian Bank | B7: =SUMIFS('Facility Master'!$K:$K, 'Facility Master'!$B:$B, $A7, 'Facility Master'!$H:$H, 1) -> 235 | C7: =SUMIFS('Facility Master'!$K:$K, 'Facility Master'!$B:$B, $A7, 'Facility Master'!$H:$H, 2) -> 0 | D7: =B7+C7 -> 235 | E7: =D7/D$15 -> 0.050364338 | F7: =COUNTIFS('Facility Master'!$B:$B, $A7, 'Facility Master'!$H:$H, ">=1", 'Facility Master'!$H:$H, "<=2") -> 1 | G7: =SUMIFS('Facility Master'!$K:$K, 'Facility Master'!$B:$B, $A7, 'Facility Master'!$H:$H, 2) + SUMIFS('Facility Master'!$K:$K, 'Facility Master'!$B:$B, $A7, 'Facility Master'!$AG:$AG, TRUE()) -> 0
A8: RBL Bank | B8: =SUMIFS('Facility Master'!$K:$K, 'Facility Master'!$B:$B, $A8, 'Facility Master'!$H:$H, 1) -> 200 | C8: =SUMIFS('Facility Master'!$K:$K, 'Facility Master'!$B:$B, $A8, 'Facility Master'!$H:$H, 2) -> 0 | D8: =B8+C8 -> 200 | E8: =D8/D$15 -> 0.042863266 | F8: =COUNTIFS('Facility Master'!$B:$B, $A8, 'Facility Master'!$H:$H, ">=1", 'Facility Master'!$H:$H, "<=2") -> 1 | G8: =SUMIFS('Facility Master'!$K:$K, 'Facility Master'!$B:$B, $A8, 'Facility Master'!$H:$H, 2) + SUMIFS('Facility Master'!$K:$K, 'Facility Master'!$B:$B, $A8, 'Facility Master'!$AG:$AG, TRUE()) -> 200
A9: YES Bank | B9: =SUMIFS('Facility Master'!$K:$K, 'Facility Master'!$B:$B, $A9, 'Facility Master'!$H:$H, 1) -> 650 | C9: =SUMIFS('Facility Master'!$K:$K, 'Facility Master'!$B:$B, $A9, 'Facility Master'!$H:$H, 2) -> 0 | D9: =B9+C9 -> 650 | E9: =D9/D$15 -> 0.13930562 | F9: =COUNTIFS('Facility Master'!$B:$B, $A9, 'Facility Master'!$H:$H, ">=1", 'Facility Master'!$H:$H, "<=2") -> 1 | G9: =SUMIFS('Facility Master'!$K:$K, 'Facility Master'!$B:$B, $A9, 'Facility Master'!$H:$H, 2) + SUMIFS('Facility Master'!$K:$K, 'Facility Master'!$B:$B, $A9, 'Facility Master'!$AG:$AG, TRUE()) -> 100
A10: IDFC First Bank | B10: =SUMIFS('Facility Master'!$K:$K, 'Facility Master'!$B:$B, $A10, 'Facility Master'!$H:$H, 1) -> 530 | C10: =SUMIFS('Facility Master'!$K:$K, 'Facility Master'!$B:$B, $A10, 'Facility Master'!$H:$H, 2) -> 0 | D10: =B10+C10 -> 530 | E10: =D10/D$15 -> 0.11358766 | F10: =COUNTIFS('Facility Master'!$B:$B, $A10, 'Facility Master'!$H:$H, ">=1", 'Facility Master'!$H:$H, "<=2") -> 1 | G10: =SUMIFS('Facility Master'!$K:$K, 'Facility Master'!$B:$B, $A10, 'Facility Master'!$H:$H, 2) + SUMIFS('Facility Master'!$K:$K, 'Facility Master'!$B:$B, $A10, 'Facility Master'!$AG:$AG, TRUE()) -> 400
A11: ICICI Bank | B11: =SUMIFS('Facility Master'!$K:$K, 'Facility Master'!$B:$B, $A11, 'Facility Master'!$H:$H, 1) -> 100 | C11: =SUMIFS('Facility Master'!$K:$K, 'Facility Master'!$B:$B, $A11, 'Facility Master'!$H:$H, 2) -> 300 | D11: =B11+C11 -> 400 | E11: =D11/D$15 -> 0.085726532 | F11: =COUNTIFS('Facility Master'!$B:$B, $A11, 'Facility Master'!$H:$H, ">=1", 'Facility Master'!$H:$H, "<=2") -> 2 | G11: =SUMIFS('Facility Master'!$K:$K, 'Facility Master'!$B:$B, $A11, 'Facility Master'!$H:$H, 2) + SUMIFS('Facility Master'!$K:$K, 'Facility Master'!$B:$B, $A11, 'Facility Master'!$AG:$AG, TRUE()) -> 300
A12: HSBC | B12: =SUMIFS('Facility Master'!$K:$K, 'Facility Master'!$B:$B, $A12, 'Facility Master'!$H:$H, 1) -> 200 | C12: =SUMIFS('Facility Master'!$K:$K, 'Facility Master'!$B:$B, $A12, 'Facility Master'!$H:$H, 2) -> 0 | D12: =B12+C12 -> 200 | E12: =D12/D$15 -> 0.042863266 | F12: =COUNTIFS('Facility Master'!$B:$B, $A12, 'Facility Master'!$H:$H, ">=1", 'Facility Master'!$H:$H, "<=2") -> 1 | G12: =SUMIFS('Facility Master'!$K:$K, 'Facility Master'!$B:$B, $A12, 'Facility Master'!$H:$H, 2) + SUMIFS('Facility Master'!$K:$K, 'Facility Master'!$B:$B, $A12, 'Facility Master'!$AG:$AG, TRUE()) -> 0
A13: HDFC Bank | B13: =SUMIFS('Facility Master'!$K:$K, 'Facility Master'!$B:$B, $A13, 'Facility Master'!$H:$H, 1) -> 0 | C13: =SUMIFS('Facility Master'!$K:$K, 'Facility Master'!$B:$B, $A13, 'Facility Master'!$H:$H, 2) -> 250 | D13: =B13+C13 -> 250 | E13: =D13/D$15 -> 0.053579083 | F13: =COUNTIFS('Facility Master'!$B:$B, $A13, 'Facility Master'!$H:$H, ">=1", 'Facility Master'!$H:$H, "<=2") -> 1 | G13: =SUMIFS('Facility Master'!$K:$K, 'Facility Master'!$B:$B, $A13, 'Facility Master'!$H:$H, 2) + SUMIFS('Facility Master'!$K:$K, 'Facility Master'!$B:$B, $A13, 'Facility Master'!$AG:$AG, TRUE()) -> 250
A14: ICICI Bank (TL) | B14: =SUMIFS('Facility Master'!$K:$K, 'Facility Master'!$B:$B, $A14, 'Facility Master'!$H:$H, 1) -> 840 | C14: =SUMIFS('Facility Master'!$K:$K, 'Facility Master'!$B:$B, $A14, 'Facility Master'!$H:$H, 2) -> 0 | D14: =B14+C14 -> 840 | E14: =D14/D$15 -> 0.18002572 | F14: =COUNTIFS('Facility Master'!$B:$B, $A14, 'Facility Master'!$H:$H, ">=1", 'Facility Master'!$H:$H, "<=2") -> 1 | G14: =SUMIFS('Facility Master'!$K:$K, 'Facility Master'!$B:$B, $A14, 'Facility Master'!$H:$H, 2) + SUMIFS('Facility Master'!$K:$K, 'Facility Master'!$B:$B, $A14, 'Facility Master'!$AG:$AG, TRUE()) -> 40
A15: Grand Total | B15: =SUM(B6:B14) -> 4116 | C15: =SUM(C6:C14) -> 550 | D15: =SUM(D6:D14) -> 4666 | E15: 1 | F15: =SUM(F6:F14) -> 11 | G15: =SUM(G6:G14) -> 2040
A16: ⚠ ICICI Bank (TL) ₹840 Cr is a takeover of existing consortium TL — netted out in Adjusted Consortium Debt. Specific take-out lender(s) not identified in the CAL.
A18: B. KEY KPIs — Dashboard Linkage
A19: KPI | B19: Amount (₹ Cr) | C19: Definition
A20: Sanctioned Debt (B1 + B2) | B20: =SUMIFS('Facility Master'!K:K,'Facility Master'!H:H,1)+SUMIFS('Facility Master'!K:K,'Facility Master'!H:H,2) -> 4666 | C20: Bucket 1 + Bucket 2 main parents — gross of ICICI TL takeover
A21: FB Mains Total (Bucket 1) | B21: =SUMIFS('Facility Master'!K:K,'Facility Master'!H:H,1) -> 4116 | C21: All fund-based main parent facilities
A22: NFB Mains Total (Bucket 2) | B22: =SUMIFS('Facility Master'!K:K,'Facility Master'!H:H,2) -> 550 | C22: All non-fund-based main parent facilities
A23: NFB Contingent Total | B23: =SUMIFS('Facility Master'!K:K,'Facility Master'!H:H,2)+SUMIFS('Facility Master'!K:K,'Facility Master'!AG:AG,TRUE()) -> 2040 | C23: B2 mains + NFB sub-limits within FB-Main parents
A24: FD-Backed Total (Bucket 3) | B24: =SUMIFS('Facility Master'!K:K,'Facility Master'!H:H,3) -> 150 | C24: Self-collateralised; economic exposure effectively nil
A25: Uncommitted Memo (Bucket 4) | B25: =SUMIFS('Facility Master'!K:K,'Facility Master'!H:H,4) -> 0 | C25: HSBC: ₹200 Cr sanctioned (post 20% haircut on ₹1,000 Cr face — see MP-13). Uncommitted on paper; treated as effective committed for modelling. Bank retains right to withdraw.
A26: Hedge Memo | B26: =SUMIFS('Facility Master'!K:K,'Facility Master'!H:H,"H") -> 75 | C26: UBI Forward Contract ₹75 Cr — outside all buckets
A27: ICICI TL Takeover (Adjustment) | B27: =SUMIFS('Facility Master'!K:K,'Facility Master'!AH:AH,TRUE(),'Facility Master'!H:H,1) -> 840 | C27: ICICI TL substitutes for existing consortium TL
A28: Adjusted Consortium Debt | B28: =B20-B27 -> 3826 | C28: Sanctioned − ICICI TL takeover = ₹4,666 − ₹840 Cr
A30: C. FD-BACKED (BUCKET 3) — Self-Collateralised
A31: Lender | B31: FD-Backed (₹ Cr) | C31: % Share
A32: RBL Bank | B32: 100 | C32: 0.667
A33: HDFC Bank | B33: 50 | C33: 0.333
A34: Grand Total | B34: 150 | C34: 1
A36: D. UNCOMMITTED MEMO (BUCKET 4) — nil after HSBC reclassification (see MP-13 / F-18)
A37: Lender | B37: Uncommitted (₹ Cr) | C37: Status / Note
A38: HSBC | B38: 0 | C38: Reclassified to Bucket 1 (Sanctioned/FB Mains) at ₹200 Cr post 20% haircut. See MP-13 / F-18.
A40: E. HEDGE MEMO — Outside All Buckets
A41: Lender | B41: Notional (₹ Cr) | C41: Status / Note
A42: UBI | B42: 75 | C42: UBI Forward Contract (memo only) — treatment ambiguous; tracked outside all buckets.

Sheet Facility Master
A1: FACILITY MASTER — JFL Debt Model (Single Source of Truth)
A2: Source: 9 JFL sanction letters | 44 facilities | All schedules aggregate from here via SUMIFS/INDEX-MATCH | Do not edit — update via sanction letters only
A3: IDENTIFICATION | G3: Flags | I3: Financial Structure | P3: PRICING | T3: REPAYMENT | X3: DATES | AC3: REFERENCE & NOTES | AG3: BUCKET FLAGS
A4: S.No | B4: Lender | C4: Facility | D4: Category | E4: Nature | F4: Sub-Limit Flag | G4: FD-Backed | H4: Bucket | I4: Currency | J4: Sanc Orig Ccy | K4: Sanc INR Cr | L4: Current O/S | M4: Eff O/S | N4: Util % | O4: Headroom | P4: Benchmark | Q4: Spread | R4: Eff Rate p.a. | S4: Rate Type | T4: Moratorium Mths | U4: Rep Frequency | V4: Tenor Mths | W4: No of Instals | X4: Drawdown Date | Y4: Rep Start Date | Z4: Maturity Date | AA4: Sanction Date | AB4: Validity Date | AC4: Purpose | AD4: Security Summary | AE4: Sanction Reference | AF4: Remarks | AG4: NFB Contingent Flag | AH4: Takeover Flag
A5: 1 | B5: UBI | C5: RTL-I (renewal) | D5: FB-Term | E5: Non-Revolving | F5: =FALSE() -> FALSE | G5: =FALSE() -> FALSE | H5: 1 | I5: INR | J5: 1125 | K5: =IFERROR(J5,0) -> 1125 | M5: =IFERROR(IF(D5="FB-Term",IF(A5=UBI_RTL1_SNo,UBI_RTL1_PrincOS,IF(A5=UBI_RTL2_SNo,UBI_RTL2_PrincOS,IF(A5=IB_TL_SNo,IB_TL_PrincOS,IF(A5=RBL_TL_SNo,RBL_TL_PrincOS,IF(A5=YBL_TL_SNo,YBL_TL_PrincOS,IF(A5=IDFC_TL_SNo,IDFC_TL_PrincOS,IF(A5=ICICI_TL_SNo,ICICI_TL_PrincOS,0))))))),IF(L5<>"",L5,IF(UseFullUtil,K5,0))),0) -> 1125 | N5: =IFERROR(M5/K5,0) -> 1 | O5: =IFERROR(K5-M5,0) -> 0 | P5: 1Y MCLR (UBI) | Q5: 0.005 | R5: =IFERROR(VLOOKUP(P5,'Instructions & Assumptions'!$A$14:$B$27,2,FALSE())+Q5,Q5) -> 0.094 | S5: Floating | T5: 48 | U5: Quarterly | V5: 192 | W5: 48 | X5: 45104 | Y5: 46568 | Z5: 50860 | AA5: 45920 | AB5: 50860 | AC5: Project capex — 2.0 MTPA Greenfield Steel Making at Kalinga Nagar | AD5: 1st p-p on FA (movable+immovable+leasehold 220.68 acres); 1st p-p on intangibles; 2nd p-p on CA; 1st p-p Escrow; Pledge 51% by OPJSTPL; OPJSTPL CG; JCL CG (till perfection); JSL DSU | AE5: UBI SL 20-Sep-2025, Ref LCBD-I:JFL:2025-26:1726 | AF5: Renewal of existing TL; 1Y MCLR 8.90% per UBI SL p.1 (RTL-I); Spread 0.50% -> effective 9.40% p.a. at present. Next MCLR reset 26-Jun-2026. (RTL-II uses 1Y MCLR 8.60% + 0.50% = 9.10%.) | AG5: =FALSE() -> FALSE | AH5: =FALSE() -> FALSE
A6: 2 | B6: UBI | C6: RTL-II (fresh) | D6: FB-Term | E6: Non-Revolving | F6: =FALSE() -> FALSE | G6: =FALSE() -> FALSE | H6: 1 | I6: INR | J6: 236 | K6: =IFERROR(J6,0) -> 236 | M6: =IFERROR(IF(D6="FB-Term",IF(A6=UBI_RTL1_SNo,UBI_RTL1_PrincOS,IF(A6=UBI_RTL2_SNo,UBI_RTL2_PrincOS,IF(A6=IB_TL_SNo,IB_TL_PrincOS,IF(A6=RBL_TL_SNo,RBL_TL_PrincOS,IF(A6=YBL_TL_SNo,YBL_TL_PrincOS,IF(A6=IDFC_TL_SNo,IDFC_TL_PrincOS,IF(A6=ICICI_TL_SNo,ICICI_TL_PrincOS,0))))))),IF(L6<>"",L6,IF(UseFullUtil,K6,0))),0) -> 236 | N6: =IFERROR(M6/K6,0) -> 1 | O6: =IFERROR(K6-M6,0) -> 0 | P6: 1Y MCLR (UBI) — RTL-II | Q6: 0.005 | R6: =IFERROR(VLOOKUP(P6,'Instructions & Assumptions'!$A$14:$B$27,2,FALSE())+Q6,Q6) -> 0.091 | S6: Floating | T6: 21 | U6: Quarterly | V6: 162 | W6: 48 | X6: 45920 | Y6: 46568 | Z6: 50860 | AA6: 45920 | AB6: 50860 | AC6: Project capex — fresh facility within UBI 20-Sep-2025 SL | AD6: 1st p-p on FA; 1st p-p on intangibles; 2nd p-p on CA; 1st p-p Escrow; Pledge 51% by OPJSTPL; OPJSTPL CG; JCL CG; JSL DSU | AE6: UBI SL 20-Sep-2025, Ref LCBD-I:JFL:2025-26:1726 | AF6: Fresh facility; 1Y MCLR 8.60% (reset basis); consortium-aligned 48 quarterly | AG6: =FALSE() -> FALSE | AH6: =FALSE() -> FALSE
A7: 3 | B7: UBI | C7: Letter of Credit (Capex LC/UPAS/SBLC) | D7: NFB | E7: Revolving | F7: =TRUE() -> TRUE | G7: =FALSE() -> FALSE | H7: 0 | I7: INR | J7: 750 | K7: =IFERROR(J7,0) -> 750 | M7: =IFERROR(IF(D7="FB-Term",IF(A7=UBI_RTL1_SNo,UBI_RTL1_PrincOS,IF(A7=UBI_RTL2_SNo,UBI_RTL2_PrincOS,IF(A7=IB_TL_SNo,IB_TL_PrincOS,IF(A7=RBL_TL_SNo,RBL_TL_PrincOS,IF(A7=YBL_TL_SNo,YBL_TL_PrincOS,IF(A7=IDFC_TL_SNo,IDFC_TL_PrincOS,IF(A7=ICICI_TL_SNo,ICICI_TL_PrincOS,0))))))),IF(L7<>"",L7,IF(UseFullUtil,K7,0))),0) -> 750 | N7: =IFERROR(M7/K7,0) -> 1 | O7: =IFERROR(K7-M7,0) -> 0 | P7: Fixed commission | Q7: 0.006 | R7: =IFERROR(VLOOKUP(P7,'Instructions & Assumptions'!$A$14:$B$27,2,FALSE())+Q7,Q7) -> 0.006 | S7: Fixed | T7: 0 | U7: On Maturity | V7: 12 | W7: 0 | X7: 45920 | Y7: =IFERROR(EDATE(X7,T7),"") -> 45920 | Z7: =IFERROR(EDATE(X7,V7),"") -> 46285 | AA7: 45920 | AB7: 46284 | AC7: NFB sub-limit; capex LC and UPAS issuance | AD7: Same as RTL primary (1st p-p on FA, 2nd on CA, Pledge 51%, OPJSTPL CG, JCL CG, JSL DSU) | AE7: UBI SL 20-Sep-2025, Ref LCBD-I:JFL:2025-26:1726 | AF7: 0.60% p.a. + GST commission; UBI branch SBLC; other-bank SBLC 0.85% | AG7: =TRUE() -> TRUE | AH7: =FALSE() -> FALSE
A8: 4 | B8: UBI | C8: Bank Guarantee | D8: NFB | E8: Revolving | F8: =TRUE() -> TRUE | G8: =FALSE() -> FALSE | H8: 0 | I8: INR | J8: 12.5 | K8: =IFERROR(J8,0) -> 12.5 | M8: =IFERROR(IF(D8="FB-Term",IF(A8=UBI_RTL1_SNo,UBI_RTL1_PrincOS,IF(A8=UBI_RTL2_SNo,UBI_RTL2_PrincOS,IF(A8=IB_TL_SNo,IB_TL_PrincOS,IF(A8=RBL_TL_SNo,RBL_TL_PrincOS,IF(A8=YBL_TL_SNo,YBL_TL_PrincOS,IF(A8=IDFC_TL_SNo,IDFC_TL_PrincOS,IF(A8=ICICI_TL_SNo,ICICI_TL_PrincOS,0))))))),IF(L8<>"",L8,IF(UseFullUtil,K8,0))),0) -> 12.5 | N8: =IFERROR(M8/K8,0) -> 1 | O8: =IFERROR(K8-M8,0) -> 0 | P8: Fixed commission | Q8: 0.006 | R8: =IFERROR(VLOOKUP(P8,'Instructions & Assumptions'!$A$14:$B$27,2,FALSE())+Q8,Q8) -> 0.006 | S8: Fixed | T8: 0 | U8: On Maturity | V8: 36 | W8: 0 | X8: 45920 | Y8: =IFERROR(EDATE(X8,T8),"") -> 45920 | Z8: =IFERROR(EDATE(X8,V8),"") -> 47016 | AA8: 45920 | AB8: 46284 | AC8: Performance/financial BG | AD8: Same as RTL primary | AE8: UBI SL 20-Sep-2025, Ref LCBD-I:JFL:2025-26:1726 | AF8: 0.60% p.a. + GST | AG8: =FALSE() -> FALSE | AH8: =FALSE() -> FALSE
A9: 5 | B9: UBI | C9: Forward Contract (credit equivalent) | D9: Hedge | E9: Revolving | F9: =FALSE() -> FALSE | G9: =FALSE() -> FALSE | H9: H | I9: INR | J9: 75 | K9: =IFERROR(J9,0) -> 75 | M9: =IFERROR(IF(D9="FB-Term",IF(A9=UBI_RTL1_SNo,UBI_RTL1_PrincOS,IF(A9=UBI_RTL2_SNo,UBI_RTL2_PrincOS,IF(A9=IB_TL_SNo,IB_TL_PrincOS,IF(A9=RBL_TL_SNo,RBL_TL_PrincOS,IF(A9=YBL_TL_SNo,YBL_TL_PrincOS,IF(A9=IDFC_TL_SNo,IDFC_TL_PrincOS,IF(A9=ICICI_TL_SNo,ICICI_TL_PrincOS,0))))))),IF(L9<>"",L9,IF(UseFullUtil,K9,0))),0) -> 75 | N9: =IFERROR(M9/K9,0) -> 1 | O9: =IFERROR(K9-M9,0) -> 0 | P9: N/A | Q9: 0 | R9: =IFERROR(VLOOKUP(P9,'Instructions & Assumptions'!$A$14:$B$27,2,FALSE())+Q9,Q9) -> 0 | S9: Fixed | T9: 0 | U9: On Settlement | V9: 12 | W9: 0 | X9: 45920 | Y9: =IFERROR(EDATE(X9,T9),"") -> 45920 | Z9: =IFERROR(EDATE(X9,V9),"") -> 46285 | AA9: 45920 | AB9: 46284 | AC9: Hedging exchange risk | AD9: Unsecured | AE9: UBI SL 20-Sep-2025, Ref LCBD-I:JFL:2025-26:1726 | AF9: MEMO ONLY. '^' superscript on UBI cover table with no footnote — treatment ambiguous; provisionally classified as hedge memo. Out of all buckets. | AG9: =FALSE() -> FALSE | AH9: =FALSE() -> FALSE
A10: 6 | B10: Indian Bank | C10: Term Loan (per amendment ticket) | D10: FB-Term | E10: Non-Revolving | F10: =FALSE() -> FALSE | G10: =FALSE() -> FALSE | H10: 1 | I10: INR | J10: 235 | K10: =IFERROR(J10,0) -> 235 | M10: =IFERROR(IF(D10="FB-Term",IF(A10=UBI_RTL1_SNo,UBI_RTL1_PrincOS,IF(A10=UBI_RTL2_SNo,UBI_RTL2_PrincOS,IF(A10=IB_TL_SNo,IB_TL_PrincOS,IF(A10=RBL_TL_SNo,RBL_TL_PrincOS,IF(A10=YBL_TL_SNo,YBL_TL_PrincOS,IF(A10=IDFC_TL_SNo,IDFC_TL_PrincOS,IF(A10=ICICI_TL_SNo,ICICI_TL_PrincOS,0))))))),IF(L10<>"",L10,IF(UseFullUtil,K10,0))),0) -> 235 | N10: =IFERROR(M10/K10,0) -> 1 | O10: =IFERROR(K10-M10,0) -> 0 | P10: 1Y MCLR (Indian Bank) | Q10: 0.005 | R10: =IFERROR(VLOOKUP(P10,'Instructions & Assumptions'!$A$14:$B$27,2,FALSE())+Q10,Q10) -> 0.094 | S10: Floating | T10: 50 | U10: Quarterly | V10: 192 | W10: 48 | X10: 44927 | Y10: 46477 | Z10: 50770 | AA10: 45926 | AB10: =Z10 -> 50770 | AC10: Project capex — long-dated consortium TL | AD10: Per original Indian Bank SL (NOT in file set). Presumed consortium-standard security. | AE10: Indian Bank Amendment Ticket 26-Sep-2025, Ref LCB/Del/JFL:2025-26 | AF10: Indian Bank: Loan ₹235 Cr DERIVED from repayment table totals (8Q × ₹2.9375 + 40Q × ₹5.2875 = ₹235 ✓). 12-yr tenor; 12-mo moratorium; graduated 1.25%/2.25% quarterly; per amendment ticket 26-Sep-2025. | AG10: =FALSE() -> FALSE | AH10: =FALSE() -> FALSE
A11: 7 | B11: RBL Bank | C11: Term Loan (12-month bullet bridge) | D11: FB-Term | E11: Non-Revolving | F11: =FALSE() -> FALSE | G11: =FALSE() -> FALSE | H11: 1 | I11: INR | J11: 200 | K11: =IFERROR(J11,0) -> 200 | M11: =IFERROR(IF(D11="FB-Term",IF(A11=UBI_RTL1_SNo,UBI_RTL1_PrincOS,IF(A11=UBI_RTL2_SNo,UBI_RTL2_PrincOS,IF(A11=IB_TL_SNo,IB_TL_PrincOS,IF(A11=RBL_TL_SNo,RBL_TL_PrincOS,IF(A11=YBL_TL_SNo,YBL_TL_PrincOS,IF(A11=IDFC_TL_SNo,IDFC_TL_PrincOS,IF(A11=ICICI_TL_SNo,ICICI_TL_PrincOS,0))))))),IF(L11<>"",L11,IF(UseFullUtil,K11,0))),0) -> 200 | N11: =IFERROR(M11/K11,0) -> 1 | O11: =IFERROR(K11-M11,0) -> 0 | P11: To be decided | Q11: 0 | R11: =IFERROR(VLOOKUP(P11,'Instructions & Assumptions'!$A$14:$B$27,2,FALSE())+Q11,Q11) -> 0.095 | S11: TBD | T11: 0 | U11: Bullet | V11: 12 | W11: 1 | X11: 45974 | Y11: 46339 | Z11: 46339 | AA11: 45974 | AB11: 46265 | AC11: Part-finance 2.0 MTPA capex + repay ICDs from JSL/Jindal Coke | AD11: Unconditional & Irrevocable CG from OPJSTPL; Shortfall Undertaking from JSL Ltd | AE11: RBL SL 13-Nov-2025, Ref CAD/DEL/0856/2025-26 | AF11: FLAG: Bridge facility — 12-month BULLET, NOT consortium amortising. Rate 'to be decided at disbursement' — FLAG. Min promoter contribution ₹1,363 Cr covenant. Min BBB rating within 180 days. | AG11: =FALSE() -> FALSE | AH11: =FALSE() -> FALSE
A12: 8 | B12: RBL Bank | C12: Letter of Credit (sub-limit of TL) | D12: NFB | E12: Revolving | F12: =TRUE() -> TRUE | G12: =FALSE() -> FALSE | H12: 0 | I12: INR | J12: 200 | K12: =IFERROR(J12,0) -> 200 | M12: =IFERROR(IF(D12="FB-Term",IF(A12=UBI_RTL1_SNo,UBI_RTL1_PrincOS,IF(A12=UBI_RTL2_SNo,UBI_RTL2_PrincOS,IF(A12=IB_TL_SNo,IB_TL_PrincOS,IF(A12=RBL_TL_SNo,RBL_TL_PrincOS,IF(A12=YBL_TL_SNo,YBL_TL_PrincOS,IF(A12=IDFC_TL_SNo,IDFC_TL_PrincOS,IF(A12=ICICI_TL_SNo,ICICI_TL_PrincOS,0))))))),IF(L12<>"",L12,IF(UseFullUtil,K12,0))),0) -> 200 | N12: =IFERROR(M12/K12,0) -> 1 | O12: =IFERROR(K12-M12,0) -> 0 | P12: Fixed commission | Q12: 0.005 | R12: =IFERROR(VLOOKUP(P12,'Instructions & Assumptions'!$A$14:$B$27,2,FALSE())+Q12,Q12) -> 0.005 | S12: Fixed | T12: 0 | U12: On Maturity | V12: 6 | W12: 0 | X12: 45974 | Y12: =IFERROR(EDATE(X12,T12),"") -> 45974 | Z12: =IFERROR(EDATE(X12,V12),"") -> 46155 | AA12: 45974 | AB12: 46265 | AC12: Procurement of raw material for testing/commissioning phase | AD12: Same as TL parent | AE12: RBL SL 13-Nov-2025, Ref CAD/DEL/0856/2025-26 | AF12: Sub-limit within ₹200 Cr TL; 0.50% p.a. commission; no LCs to sister/group companies; 6 months max per LC | AG12: =TRUE() -> TRUE | AH12: =FALSE() -> FALSE
A13: 9 | B13: RBL Bank | C13: FDOD (Overdraft against FD) | D13: FB-FDbacked | E13: Revolving | F13: =FALSE() -> FALSE | G13: =TRUE() -> TRUE | H13: 3 | I13: INR | J13: 100 | K13: =IFERROR(J13,0) -> 100 | M13: =IFERROR(IF(D13="FB-Term",IF(A13=UBI_RTL1_SNo,UBI_RTL1_PrincOS,IF(A13=UBI_RTL2_SNo,UBI_RTL2_PrincOS,IF(A13=IB_TL_SNo,IB_TL_PrincOS,IF(A13=RBL_TL_SNo,RBL_TL_PrincOS,IF(A13=YBL_TL_SNo,YBL_TL_PrincOS,IF(A13=IDFC_TL_SNo,IDFC_TL_PrincOS,IF(A13=ICICI_TL_SNo,ICICI_TL_PrincOS,0))))))),IF(L13<>"",L13,IF(UseFullUtil,K13,0))),0) -> 100 | N13: =IFERROR(M13/K13,0) -> 1 | O13: =IFERROR(K13-M13,0) -> 0 | P13: To be decided | Q13: 0 | R13: =IFERROR(VLOOKUP(P13,'Instructions & Assumptions'!$A$14:$B$27,2,FALSE())+Q13,Q13) -> 0.095 | S13: TBD | T13: 0 | U13: On Demand | V13: 12 | W13: 0 | X13: 45974 | Y13: =IFERROR(EDATE(X13,T13),"") -> 45974 | Z13: =IFERROR(EDATE(X13,V13),"") -> 46339 | AA13: 45974 | AB13: 46265 | AC13: Cash-flow mismatches | AD13: 100% lien on FD held by JFL/JSL/Jindal Coke/JUSL; up to 90% of FD value lien-marked | AE13: RBL SL 13-Nov-2025, Ref CAD/DEL/0856/2025-26 | AF13: FD-backed; economic exposure nil; rate TBD at disbursement — FLAG | AG13: =FALSE() -> FALSE | AH13: =FALSE() -> FALSE
A14: 10 | B14: YES Bank | C14: Term Loan (project, new consortium joiner) | D14: FB-Term | E14: Non-Revolving | F14: =FALSE() -> FALSE | G14: =FALSE() -> FALSE | H14: 1 | I14: INR | J14: 650 | K14: =IFERROR(J14,0) -> 650 | M14: =IFERROR(IF(D14="FB-Term",IF(A14=UBI_RTL1_SNo,UBI_RTL1_PrincOS,IF(A14=UBI_RTL2_SNo,UBI_RTL2_PrincOS,IF(A14=IB_TL_SNo,IB_TL_PrincOS,IF(A14=RBL_TL_SNo,RBL_TL_PrincOS,IF(A14=YBL_TL_SNo,YBL_TL_PrincOS,IF(A14=IDFC_TL_SNo,IDFC_TL_PrincOS,IF(A14=ICICI_TL_SNo,ICICI_TL_PrincOS,0))))))),IF(L14<>"",L14,IF(UseFullUtil,K14,0))),0) -> 650 | N14: =IFERROR(M14/K14,0) -> 1 | O14: =IFERROR(K14-M14,0) -> 0 | P14: EBLR (YES Bank) | Q14: 0.0345 | R14: =IFERROR(VLOOKUP(P14,'Instructions & Assumptions'!$A$14:$B$27,2,FALSE())+Q14,Q14) -> 0.0955 | S14: Floating | T14: 12 | U14: Quarterly | V14: 160 | W14: 48 | X14: 46020 | Y14: 46568 | Z14: 50860 | AA14: 46020 | AB14: 50860 | AC14: Project capex — new consortium TL | AD14: 1st p-p on FA (incl leasehold rights); 1st p-p on intangibles; 2nd p-p on CA; Pledge 51% by OPJSTPL; DSU JSL; LoC JSL; OPJSTPL CG; JCL CG (extinguished at perfection) | AE14: YES Bank Final Facility Letter 29-Dec-2025, Ref YBL/DEL/LC/FL/04920/12/2025 | AF14: YBL: EBLR + 3.45% (current EBLR not stated in letter). 160 mo tenor; 12-mo moratorium; quarterly P+I; per FL 30-Dec-2025. See F-06, F-13. | AG14: =FALSE() -> FALSE | AH14: =FALSE() -> FALSE
A15: 11 | B15: YES Bank | C15: Capex LC (sub-limit of TL) | D15: NFB | E15: Revolving | F15: =TRUE() -> TRUE | G15: =FALSE() -> FALSE | H15: 0 | I15: INR | J15: 100 | K15: =IFERROR(J15,0) -> 100 | M15: =IFERROR(IF(D15="FB-Term",IF(A15=UBI_RTL1_SNo,UBI_RTL1_PrincOS,IF(A15=UBI_RTL2_SNo,UBI_RTL2_PrincOS,IF(A15=IB_TL_SNo,IB_TL_PrincOS,IF(A15=RBL_TL_SNo,RBL_TL_PrincOS,IF(A15=YBL_TL_SNo,YBL_TL_PrincOS,IF(A15=IDFC_TL_SNo,IDFC_TL_PrincOS,IF(A15=ICICI_TL_SNo,ICICI_TL_PrincOS,0))))))),IF(L15<>"",L15,IF(UseFullUtil,K15,0))),0) -> 100 | N15: =IFERROR(M15/K15,0) -> 1 | O15: =IFERROR(K15-M15,0) -> 0 | P15: Fixed commission | Q15: 0.005 | R15: =IFERROR(VLOOKUP(P15,'Instructions & Assumptions'!$A$14:$B$27,2,FALSE())+Q15,Q15) -> 0.005 | S15: Fixed | T15: 0 | U15: On Maturity | V15: 36 | W15: 0 | X15: 46020 | Y15: =IFERROR(EDATE(X15,T15),"") -> 46020 | Z15: =IFERROR(EDATE(X15,V15),"") -> 47116 | AA15: 46020 | AB15: =EDATE(X15,V15) -> 47116 | AC15: Capex LC issuance | AD15: Same as YBL TL primary | AE15: YES Bank Final Facility Letter 29-Dec-2025, Ref YBL/DEL/LC/FL/04920/12/2025 | AF15: Sub-limit within ₹650 Cr TL; 0.50% p.a.; 36-month tenor incl 12-month usance; availability till 02-Mar-2026 | AG15: =TRUE() -> TRUE | AH15: =FALSE() -> FALSE
A16: 12 | B16: IDFC First Bank | C16: RTL (project, new consortium joiner) | D16: FB-Term | E16: Non-Revolving | F16: =FALSE() -> FALSE | G16: =FALSE() -> FALSE | H16: 1 | I16: INR | J16: 530 | K16: =IFERROR(J16,0) -> 530 | M16: =IFERROR(IF(D16="FB-Term",IF(A16=UBI_RTL1_SNo,UBI_RTL1_PrincOS,IF(A16=UBI_RTL2_SNo,UBI_RTL2_PrincOS,IF(A16=IB_TL_SNo,IB_TL_PrincOS,IF(A16=RBL_TL_SNo,RBL_TL_PrincOS,IF(A16=YBL_TL_SNo,YBL_TL_PrincOS,IF(A16=IDFC_TL_SNo,IDFC_TL_PrincOS,IF(A16=ICICI_TL_SNo,ICICI_TL_PrincOS,0))))))),IF(L16<>"",L16,IF(UseFullUtil,K16,0))),0) -> 530 | N16: =IFERROR(M16/K16,0) -> 1 | O16: =IFERROR(K16-M16,0) -> 0 | P16: EBLR (IDFC First) | Q16: 0.0105 | R16: =IFERROR(VLOOKUP(P16,'Instructions & Assumptions'!$A$14:$B$27,2,FALSE())+Q16,Q16) -> 0.088 | S16: Floating | T16: 12 | U16: Quarterly | V16: 156 | W16: 48 | X16: 46031 | Y16: 46568 | Z16: 50860 | AA16: 46031 | AB16: 50860 | AC16: Project capex — new consortium TL | AD16: Consortium-standard: 1st p-p on FA; 2nd p-p on CA; Pledge 51%; OPJSTPL CG; JCL CG; JSL DSU; LoC JSL. Escrow at UBI. | AE16: IDFC First SL 09-Jan-2026, Ref IDFC/CAD/REF/SL/260131 | AF16: IDFC: EBLR 7.75% + 1.05% spread = ~8.80%. 144-mo tenor; 12-mo moratorium; quarterly P+I; per SL 09-Jan-2026 accepted 14-Jan-2026. | AG16: =FALSE() -> FALSE | AH16: =FALSE() -> FALSE
A17: 13 | B17: IDFC First Bank | C17: NFB — Capex LC/SBLC (A) | D17: NFB | E17: Revolving | F17: =TRUE() -> TRUE | G17: =FALSE() -> FALSE | H17: 0 | I17: INR | J17: 400 | K17: =IFERROR(J17,0) -> 400 | M17: =IFERROR(IF(D17="FB-Term",IF(A17=UBI_RTL1_SNo,UBI_RTL1_PrincOS,IF(A17=UBI_RTL2_SNo,UBI_RTL2_PrincOS,IF(A17=IB_TL_SNo,IB_TL_PrincOS,IF(A17=RBL_TL_SNo,RBL_TL_PrincOS,IF(A17=YBL_TL_SNo,YBL_TL_PrincOS,IF(A17=IDFC_TL_SNo,IDFC_TL_PrincOS,IF(A17=ICICI_TL_SNo,ICICI_TL_PrincOS,0))))))),IF(L17<>"",L17,IF(UseFullUtil,K17,0))),0) -> 400 | N17: =IFERROR(M17/K17,0) -> 1 | O17: =IFERROR(K17-M17,0) -> 0 | P17: Fixed commission | Q17: 0.0035 | R17: =IFERROR(VLOOKUP(P17,'Instructions & Assumptions'!$A$14:$B$27,2,FALSE())+Q17,Q17) -> 0.0035 | S17: Fixed | T17: 0 | U17: On Maturity | V17: 36 | W17: 0 | X17: 46031 | Y17: =IFERROR(EDATE(X17,T17),"") -> 46031 | Z17: =IFERROR(EDATE(X17,V17),"") -> 47127 | AA17: 46031 | AB17: 46295 | AC17: Capex LC/SBLC issuance | AD17: Consortium-standard security | AE17: IDFC First SL 09-Jan-2026, Ref IDFC/CAD/REF/SL/260131 | AF17: IDFC NFB-A (Capex LC/SBLC): ₹400 Cr total NFB cap; AG=TRUE. Per SL p.2 verbatim 'Sub-Limits under Facility: Rs 400.00 Cr towards non-funded'. | AG17: =TRUE() -> TRUE | AH17: =FALSE() -> FALSE
A18: 14 | B18: IDFC First Bank | C18: NFB — BG / SBLC (B, sub-limit within ₹400 cap) | D18: NFB | E18: Revolving | F18: =TRUE() -> TRUE | G18: =FALSE() -> FALSE | H18: 0 | I18: INR | J18: 200 | K18: =IFERROR(J18,0) -> 200 | M18: =IFERROR(IF(D18="FB-Term",IF(A18=UBI_RTL1_SNo,UBI_RTL1_PrincOS,IF(A18=UBI_RTL2_SNo,UBI_RTL2_PrincOS,IF(A18=IB_TL_SNo,IB_TL_PrincOS,IF(A18=RBL_TL_SNo,RBL_TL_PrincOS,IF(A18=YBL_TL_SNo,YBL_TL_PrincOS,IF(A18=IDFC_TL_SNo,IDFC_TL_PrincOS,IF(A18=ICICI_TL_SNo,ICICI_TL_PrincOS,0))))))),IF(L18<>"",L18,IF(UseFullUtil,K18,0))),0) -> 200 | N18: =IFERROR(M18/K18,0) -> 1 | O18: =IFERROR(K18-M18,0) -> 0 | P18: Fixed commission | Q18: 0.0035 | R18: =IFERROR(VLOOKUP(P18,'Instructions & Assumptions'!$A$14:$B$27,2,FALSE())+Q18,Q18) -> 0.0035 | S18: Fixed | T18: 0 | U18: On Maturity | V18: 48 | W18: 0 | X18: 46031 | Y18: =IFERROR(EDATE(X18,T18),"") -> 46031 | Z18: =IFERROR(EDATE(X18,V18),"") -> 47492 | AA18: 46031 | AB18: 46295 | AC18: BG / SBLC issuance | AD18: Consortium-standard security | AE18: IDFC First SL 09-Jan-2026, Ref IDFC/CAD/REF/SL/260131 | AF18: IDFC NFB-B (BG/SBLC): sub-cap ₹200 Cr within A's ₹400 Cr parent. AG=FALSE — combined A+B ≤ ₹400 Cr (not additive). See F-03 (RESOLVED). | AG18: =FALSE() -> FALSE | AH18: =FALSE() -> FALSE
A19: 15 | B19: ICICI Bank | C19: Cash Credit (WC) | D19: FB | E19: Revolving | F19: =FALSE() -> FALSE | G19: =FALSE() -> FALSE | H19: 1 | I19: INR | J19: 100 | K19: =IFERROR(J19,0) -> 100 | M19: =IFERROR(IF(D19="FB-Term",IF(A19=UBI_RTL1_SNo,UBI_RTL1_PrincOS,IF(A19=UBI_RTL2_SNo,UBI_RTL2_PrincOS,IF(A19=IB_TL_SNo,IB_TL_PrincOS,IF(A19=RBL_TL_SNo,RBL_TL_PrincOS,IF(A19=YBL_TL_SNo,YBL_TL_PrincOS,IF(A19=IDFC_TL_SNo,IDFC_TL_PrincOS,IF(A19=ICICI_TL_SNo,ICICI_TL_PrincOS,0))))))),IF(L19<>"",L19,IF(UseFullUtil,K19,0))),0) -> 100 | N19: =IFERROR(M19/K19,0) -> 1 | O19: =IFERROR(K19-M19,0) -> 0 | P19: 6M I-MCLR (ICICI) | Q19: 0.002 | R19: =IFERROR(VLOOKUP(P19,'Instructions & Assumptions'!$A$14:$B$27,2,FALSE())+Q19,Q19) -> 0.085 | S19: Floating | T19: 0 | U19: On Demand | V19: 12 | W19: 0 | X19: 46065 | Y19: =IFERROR(EDATE(X19,T19),"") -> 46065 | Z19: 46421 | AA19: 46065 | AB19: 46421 | AC19: Working capital — operational | AD19: 1st p-p on CA; 2nd p-p on FA (movable+immovable+leasehold Project Land); 2nd p-p intangibles; Pledge 51%; OPJSTPL CG; JCL CG (till perfection); JSL DSU; LoC JSL | AE19: ICICI WC CAL 12-Feb-2026, Ref CAL142368928833 | AF19: I-MCLR-6M (8.30%) + 0.20% = ~8.50%. Reset every 6 mo. Interchangeable one-way to LC. Validity 03-Feb-2027. | AG19: =FALSE() -> FALSE | AH19: =FALSE() -> FALSE
A20: 16 | B20: ICICI Bank | C20: WCDL (sub-limit of CC) | D20: FB | E20: Revolving | F20: =TRUE() -> TRUE | G20: =FALSE() -> FALSE | H20: 0 | I20: INR | J20: 100 | K20: =IFERROR(J20,0) -> 100 | M20: =IFERROR(IF(D20="FB-Term",IF(A20=UBI_RTL1_SNo,UBI_RTL1_PrincOS,IF(A20=UBI_RTL2_SNo,UBI_RTL2_PrincOS,IF(A20=IB_TL_SNo,IB_TL_PrincOS,IF(A20=RBL_TL_SNo,RBL_TL_PrincOS,IF(A20=YBL_TL_SNo,YBL_TL_PrincOS,IF(A20=IDFC_TL_SNo,IDFC_TL_PrincOS,IF(A20=ICICI_TL_SNo,ICICI_TL_PrincOS,0))))))),IF(L20<>"",L20,IF(UseFullUtil,K20,0))),0) -> 100 | N20: =IFERROR(M20/K20,0) -> 1 | O20: =IFERROR(K20-M20,0) -> 0 | P20: Repo Rate | Q20: 0 | R20: =IFERROR(VLOOKUP(P20,'Instructions & Assumptions'!$A$14:$B$27,2,FALSE())+Q20,Q20) -> 0.0525 | S20: TBD | T20: 0 | U20: On Maturity | V20: 3 | W20: 0 | X20: 46065 | Y20: =IFERROR(EDATE(X20,T20),"") -> 46065 | Z20: 46421 | AA20: 46065 | AB20: 46421 | AC20: Working capital | AD20: Same as CC parent | AE20: ICICI WC CAL 12-Feb-2026, Ref CAL142368928833 | AF20: Repo Rate + Spread (TBD per drawdown — FLAG). Max 90-day tranche; default 95 days under RBI LDS. Sub of CC. | AG20: =FALSE() -> FALSE | AH20: =FALSE() -> FALSE
A21: 17 | B21: ICICI Bank | C21: Letter of Credit (WC) | D21: NFB | E21: Revolving | F21: =FALSE() -> FALSE | G21: =FALSE() -> FALSE | H21: 2 | I21: INR | J21: 300 | K21: =IFERROR(J21,0) -> 300 | M21: =IFERROR(IF(D21="FB-Term",IF(A21=UBI_RTL1_SNo,UBI_RTL1_PrincOS,IF(A21=UBI_RTL2_SNo,UBI_RTL2_PrincOS,IF(A21=IB_TL_SNo,IB_TL_PrincOS,IF(A21=RBL_TL_SNo,RBL_TL_PrincOS,IF(A21=YBL_TL_SNo,YBL_TL_PrincOS,IF(A21=IDFC_TL_SNo,IDFC_TL_PrincOS,IF(A21=ICICI_TL_SNo,ICICI_TL_PrincOS,0))))))),IF(L21<>"",L21,IF(UseFullUtil,K21,0))),0) -> 300 | N21: =IFERROR(M21/K21,0) -> 1 | O21: =IFERROR(K21-M21,0) -> 0 | P21: Fixed commission | Q21: 0.006 | R21: =IFERROR(VLOOKUP(P21,'Instructions & Assumptions'!$A$14:$B$27,2,FALSE())+Q21,Q21) -> 0.006 | S21: Fixed | T21: 0 | U21: On Maturity | V21: 12 | W21: 0 | X21: 46065 | Y21: =IFERROR(EDATE(X21,T21),"") -> 46065 | Z21: 46421 | AA21: 46065 | AB21: 46421 | AC21: Procurement of RM, consumables, spares, capital goods | AD21: Same as CC parent | AE21: ICICI WC CAL 12-Feb-2026, Ref CAL142368928833 | AF21: 0.60% p.a. commission. Foreign LC max 150 days; Inland 90 days. Group co LC cap 25% (Jindal Coke + JSL combined). | AG21: =FALSE() -> FALSE | AH21: =FALSE() -> FALSE
A22: 18 | B22: ICICI Bank | C22: BG (F+P, sub-limit of LC) | D22: NFB | E22: Revolving | F22: =TRUE() -> TRUE | G22: =FALSE() -> FALSE | H22: 0 | I22: INR | J22: 300 | K22: =IFERROR(J22,0) -> 300 | M22: =IFERROR(IF(D22="FB-Term",IF(A22=UBI_RTL1_SNo,UBI_RTL1_PrincOS,IF(A22=UBI_RTL2_SNo,UBI_RTL2_PrincOS,IF(A22=IB_TL_SNo,IB_TL_PrincOS,IF(A22=RBL_TL_SNo,RBL_TL_PrincOS,IF(A22=YBL_TL_SNo,YBL_TL_PrincOS,IF(A22=IDFC_TL_SNo,IDFC_TL_PrincOS,IF(A22=ICICI_TL_SNo,ICICI_TL_PrincOS,0))))))),IF(L22<>"",L22,IF(UseFullUtil,K22,0))),0) -> 300 | N22: =IFERROR(M22/K22,0) -> 1 | O22: =IFERROR(K22-M22,0) -> 0 | P22: Fixed commission | Q22: 0.006 | R22: =IFERROR(VLOOKUP(P22,'Instructions & Assumptions'!$A$14:$B$27,2,FALSE())+Q22,Q22) -> 0.006 | S22: Fixed | T22: 0 | U22: On Maturity | V22: 36 | W22: 0 | X22: 46065 | Y22: =IFERROR(EDATE(X22,T22),"") -> 46065 | Z22: 46421 | AA22: 46065 | AB22: 46421 | AC22: BG performance + financial | AD22: Same as CC parent | AE22: ICICI WC CAL 12-Feb-2026, Ref CAL142368928833 | AF22: BG(F) 0.85% ≤1y / 1.00% 1-3y; BG(P) 0.60% / 0.75%. Onerous BG: 12.5% private, 25% PSU. Sub of LC. | AG22: =FALSE() -> FALSE | AH22: =FALSE() -> FALSE
A23: 19 | B23: HSBC | C23: Combined Limit (Uncommitted) | D23: NFB | E23: Revolving | F23: =FALSE() -> FALSE | G23: =FALSE() -> FALSE | H23: 1 | I23: INR | J23: 200 | K23: =IFERROR(J23,0) -> 200 | M23: =IFERROR(IF(D23="FB-Term",IF(A23=UBI_RTL1_SNo,UBI_RTL1_PrincOS,IF(A23=UBI_RTL2_SNo,UBI_RTL2_PrincOS,IF(A23=IB_TL_SNo,IB_TL_PrincOS,IF(A23=RBL_TL_SNo,RBL_TL_PrincOS,IF(A23=YBL_TL_SNo,YBL_TL_PrincOS,IF(A23=IDFC_TL_SNo,IDFC_TL_PrincOS,IF(A23=ICICI_TL_SNo,ICICI_TL_PrincOS,0))))))),IF(L23<>"",L23,IF(UseFullUtil,K23,0))),0) -> 200 | N23: =IFERROR(M23/K23,0) -> 1 | O23: =IFERROR(K23-M23,0) -> 0 | P23: Mutually agreed | Q23: 0 | R23: =IFERROR(VLOOKUP(P23,'Instructions & Assumptions'!$A$14:$B$27,2,FALSE())+Q23,Q23) -> 0.09 | S23: TBD | T23: 0 | U23: Various | V23: 12 | W23: 0 | X23: 46080 | Y23: =IFERROR(EDATE(X23,T23),"") -> 46080 | Z23: =IFERROR(EDATE(X23,V23),"") -> 46445 | AA23: 46080 | AB23: 46265 | AC23: Trade finance + working capital | AD23: 1st p-p on CA; 2nd p-p on movable FA; Pledge 51% (proportionate); JSL DSU. NO charge on immovable FA — FLAG. | AE23: HSBC Facilities Letter 27-Feb-2026, Ref GBM NDH 260475 | AF23: HSBC: ₹1,000 Cr face UNCOMMITTED Combined Limit. Model carries ₹200 Cr post 20% haircut in Bucket 1 (Sanctioned/FB Mains). Bank retains discretion to cancel. All 14 sub-facilities Bucket 0. Security excludes immovable FA. See F-07, MP-13, F-18. | AG23: =FALSE() -> FALSE | AH23: =FALSE() -> FALSE
A24: 20 | B24: HSBC | C24: Working Capital Loan (Uncommitted, sub of #1) | D24: FB | E24: Revolving | F24: =TRUE() -> TRUE | G24: =FALSE() -> FALSE | H24: 0 | I24: INR | J24: 26.08 | K24: =IFERROR(J24,0) -> 26.08 | M24: =IFERROR(IF(D24="FB-Term",IF(A24=UBI_RTL1_SNo,UBI_RTL1_PrincOS,IF(A24=UBI_RTL2_SNo,UBI_RTL2_PrincOS,IF(A24=IB_TL_SNo,IB_TL_PrincOS,IF(A24=RBL_TL_SNo,RBL_TL_PrincOS,IF(A24=YBL_TL_SNo,YBL_TL_PrincOS,IF(A24=IDFC_TL_SNo,IDFC_TL_PrincOS,IF(A24=ICICI_TL_SNo,ICICI_TL_PrincOS,0))))))),IF(L24<>"",L24,IF(UseFullUtil,K24,0))),0) -> 26.08 | N24: =IFERROR(M24/K24,0) -> 1 | O24: =IFERROR(K24-M24,0) -> 0 | P24: Mutually agreed | Q24: 0 | R24: =IFERROR(VLOOKUP(P24,'Instructions & Assumptions'!$A$14:$B$27,2,FALSE())+Q24,Q24) -> 0.09 | S24: TBD | T24: 0 | U24: On Maturity | V24: 6 | W24: 0 | X24: 46080 | Y24: =IFERROR(EDATE(X24,T24),"") -> 46080 | Z24: =IFERROR(EDATE(X24,V24),"") -> 46261 | AA24: 46080 | AB24: 46265 | AC24: Working capital | AD24: Per Combined Limit | AE24: HSBC Facilities Letter 27-Feb-2026, Ref GBM NDH 260475 | AF24: 6-month tenor; rate mutually agreed | AG24: =FALSE() -> FALSE | AH24: =FALSE() -> FALSE
A25: 21 | B25: HSBC | C25: Overdraft (Uncommitted, sub of WCL) | D25: FB | E25: Revolving | F25: =TRUE() -> TRUE | G25: =FALSE() -> FALSE | H25: 0 | I25: INR | J25: 10.432 | K25: =IFERROR(J25,0) -> 10.432 | M25: =IFERROR(IF(D25="FB-Term",IF(A25=UBI_RTL1_SNo,UBI_RTL1_PrincOS,IF(A25=UBI_RTL2_SNo,UBI_RTL2_PrincOS,IF(A25=IB_TL_SNo,IB_TL_PrincOS,IF(A25=RBL_TL_SNo,RBL_TL_PrincOS,IF(A25=YBL_TL_SNo,YBL_TL_PrincOS,IF(A25=IDFC_TL_SNo,IDFC_TL_PrincOS,IF(A25=ICICI_TL_SNo,ICICI_TL_PrincOS,0))))))),IF(L25<>"",L25,IF(UseFullUtil,K25,0))),0) -> 10.432 | N25: =IFERROR(M25/K25,0) -> 1 | O25: =IFERROR(K25-M25,0) -> 0 | P25: Mutually agreed | Q25: 0 | R25: =IFERROR(VLOOKUP(P25,'Instructions & Assumptions'!$A$14:$B$27,2,FALSE())+Q25,Q25) -> 0.09 | S25: TBD | T25: 0 | U25: On Demand | V25: 12 | W25: 0 | X25: 46080 | Y25: =IFERROR(EDATE(X25,T25),"") -> 46080 | Z25: =IFERROR(EDATE(X25,V25),"") -> 46445 | AA25: 46080 | AB25: 46265 | AC25: Working capital | AD25: Per Combined Limit | AE25: HSBC Facilities Letter 27-Feb-2026, Ref GBM NDH 260475 | AF25: On demand; rate mutually agreed | AG25: =FALSE() -> FALSE | AH25: =FALSE() -> FALSE
A26: 22 | B26: HSBC | C26: Import Controlling line - 1 (Uncommitted) | D26: NFB | E26: Revolving | F26: =TRUE() -> TRUE | G26: =FALSE() -> FALSE | H26: 0 | I26: INR | J26: 26.08 | K26: =IFERROR(J26,0) -> 26.08 | M26: =IFERROR(IF(D26="FB-Term",IF(A26=UBI_RTL1_SNo,UBI_RTL1_PrincOS,IF(A26=UBI_RTL2_SNo,UBI_RTL2_PrincOS,IF(A26=IB_TL_SNo,IB_TL_PrincOS,IF(A26=RBL_TL_SNo,RBL_TL_PrincOS,IF(A26=YBL_TL_SNo,YBL_TL_PrincOS,IF(A26=IDFC_TL_SNo,IDFC_TL_PrincOS,IF(A26=ICICI_TL_SNo,ICICI_TL_PrincOS,0))))))),IF(L26<>"",L26,IF(UseFullUtil,K26,0))),0) -> 26.08 | N26: =IFERROR(M26/K26,0) -> 1 | O26: =IFERROR(K26-M26,0) -> 0 | P26: Mutually agreed | Q26: 0 | R26: =IFERROR(VLOOKUP(P26,'Instructions & Assumptions'!$A$14:$B$27,2,FALSE())+Q26,Q26) -> 0.09 | S26: TBD | T26: 0 | U26: Various | V26: 6 | W26: 0 | X26: 46080 | Y26: =IFERROR(EDATE(X26,T26),"") -> 46080 | Z26: =IFERROR(EDATE(X26,V26),"") -> 46261 | AA26: 46080 | AB26: 46265 | AC26: Import financing | AD26: Per Combined Limit | AE26: HSBC Facilities Letter 27-Feb-2026, Ref GBM NDH 260475 | AF26: Sub of OD; rate TBD | AG26: =FALSE() -> FALSE | AH26: =FALSE() -> FALSE
A27: 23 | B27: HSBC | C27: TradePay Domestic/Import (Uncommitted) | D27: NFB | E27: Revolving | F27: =TRUE() -> TRUE | G27: =FALSE() -> FALSE | H27: 0 | I27: INR | J27: 26.08 | K27: =IFERROR(J27,0) -> 26.08 | M27: =IFERROR(IF(D27="FB-Term",IF(A27=UBI_RTL1_SNo,UBI_RTL1_PrincOS,IF(A27=UBI_RTL2_SNo,UBI_RTL2_PrincOS,IF(A27=IB_TL_SNo,IB_TL_PrincOS,IF(A27=RBL_TL_SNo,RBL_TL_PrincOS,IF(A27=YBL_TL_SNo,YBL_TL_PrincOS,IF(A27=IDFC_TL_SNo,IDFC_TL_PrincOS,IF(A27=ICICI_TL_SNo,ICICI_TL_PrincOS,0))))))),IF(L27<>"",L27,IF(UseFullUtil,K27,0))),0) -> 26.08 | N27: =IFERROR(M27/K27,0) -> 1 | O27: =IFERROR(K27-M27,0) -> 0 | P27: Mutually agreed | Q27: 0 | R27: =IFERROR(VLOOKUP(P27,'Instructions & Assumptions'!$A$14:$B$27,2,FALSE())+Q27,Q27) -> 0.09 | S27: TBD | T27: 0 | U27: On Maturity | V27: 6 | W27: 0 | X27: 46080 | Y27: =IFERROR(EDATE(X27,T27),"") -> 46080 | Z27: =IFERROR(EDATE(X27,V27),"") -> 46261 | AA27: 46080 | AB27: 46265 | AC27: Buyer facility | AD27: Per Combined Limit | AE27: HSBC Facilities Letter 27-Feb-2026, Ref GBM NDH 260475 | AF27: 6 months; rate TBD | AG27: =FALSE() -> FALSE | AH27: =FALSE() -> FALSE
A28: 24 | B28: HSBC | C28: Pre-shipment Buyer Loan (Uncommitted) | D28: FB | E28: Revolving | F28: =TRUE() -> TRUE | G28: =FALSE() -> FALSE | H28: 0 | I28: INR | J28: 26.08 | K28: =IFERROR(J28,0) -> 26.08 | M28: =IFERROR(IF(D28="FB-Term",IF(A28=UBI_RTL1_SNo,UBI_RTL1_PrincOS,IF(A28=UBI_RTL2_SNo,UBI_RTL2_PrincOS,IF(A28=IB_TL_SNo,IB_TL_PrincOS,IF(A28=RBL_TL_SNo,RBL_TL_PrincOS,IF(A28=YBL_TL_SNo,YBL_TL_PrincOS,IF(A28=IDFC_TL_SNo,IDFC_TL_PrincOS,IF(A28=ICICI_TL_SNo,ICICI_TL_PrincOS,0))))))),IF(L28<>"",L28,IF(UseFullUtil,K28,0))),0) -> 26.08 | N28: =IFERROR(M28/K28,0) -> 1 | O28: =IFERROR(K28-M28,0) -> 0 | P28: Mutually agreed | Q28: 0 | R28: =IFERROR(VLOOKUP(P28,'Instructions & Assumptions'!$A$14:$B$27,2,FALSE())+Q28,Q28) -> 0.09 | S28: TBD | T28: 0 | U28: On Maturity | V28: 6 | W28: 0 | X28: 46080 | Y28: =IFERROR(EDATE(X28,T28),"") -> 46080 | Z28: =IFERROR(EDATE(X28,V28),"") -> 46261 | AA28: 46080 | AB28: 46265 | AC28: Pre-shipment finance | AD28: Per Combined Limit | AE28: HSBC Facilities Letter 27-Feb-2026, Ref GBM NDH 260475 | AF28: 6 months; rate TBD | AG28: =FALSE() -> FALSE | AH28: =FALSE() -> FALSE
A29: 25 | B29: HSBC | C29: Post-Shipment Buyer Loan / DPF / LAI (Uncommitted) | D29: FB | E29: Revolving | F29: =TRUE() -> TRUE | G29: =FALSE() -> FALSE | H29: 0 | I29: INR | J29: 26.08 | K29: =IFERROR(J29,0) -> 26.08 | M29: =IFERROR(IF(D29="FB-Term",IF(A29=UBI_RTL1_SNo,UBI_RTL1_PrincOS,IF(A29=UBI_RTL2_SNo,UBI_RTL2_PrincOS,IF(A29=IB_TL_SNo,IB_TL_PrincOS,IF(A29=RBL_TL_SNo,RBL_TL_PrincOS,IF(A29=YBL_TL_SNo,YBL_TL_PrincOS,IF(A29=IDFC_TL_SNo,IDFC_TL_PrincOS,IF(A29=ICICI_TL_SNo,ICICI_TL_PrincOS,0))))))),IF(L29<>"",L29,IF(UseFullUtil,K29,0))),0) -> 26.08 | N29: =IFERROR(M29/K29,0) -> 1 | O29: =IFERROR(K29-M29,0) -> 0 | P29: Mutually agreed | Q29: 0 | R29: =IFERROR(VLOOKUP(P29,'Instructions & Assumptions'!$A$14:$B$27,2,FALSE())+Q29,Q29) -> 0.09 | S29: TBD | T29: 0 | U29: On Maturity | V29: 6 | W29: 0 | X29: 46080 | Y29: =IFERROR(EDATE(X29,T29),"") -> 46080 | Z29: =IFERROR(EDATE(X29,V29),"") -> 46261 | AA29: 46080 | AB29: 46265 | AC29: Post-shipment / domestic purchase finance | AD29: Per Combined Limit | AE29: HSBC Facilities Letter 27-Feb-2026, Ref GBM NDH 260475 | AF29: 6 months; rate TBD | AG29: =FALSE() -> FALSE | AH29: =FALSE() -> FALSE
A30: 26 | B30: HSBC | C30: Export Controlling line (Uncommitted) | D30: NFB | E30: Revolving | F30: =TRUE() -> TRUE | G30: =FALSE() -> FALSE | H30: 0 | I30: INR | J30: 26.08 | K30: =IFERROR(J30,0) -> 26.08 | M30: =IFERROR(IF(D30="FB-Term",IF(A30=UBI_RTL1_SNo,UBI_RTL1_PrincOS,IF(A30=UBI_RTL2_SNo,UBI_RTL2_PrincOS,IF(A30=IB_TL_SNo,IB_TL_PrincOS,IF(A30=RBL_TL_SNo,RBL_TL_PrincOS,IF(A30=YBL_TL_SNo,YBL_TL_PrincOS,IF(A30=IDFC_TL_SNo,IDFC_TL_PrincOS,IF(A30=ICICI_TL_SNo,ICICI_TL_PrincOS,0))))))),IF(L30<>"",L30,IF(UseFullUtil,K30,0))),0) -> 26.08 | N30: =IFERROR(M30/K30,0) -> 1 | O30: =IFERROR(K30-M30,0) -> 0 | P30: Mutually agreed | Q30: 0 | R30: =IFERROR(VLOOKUP(P30,'Instructions & Assumptions'!$A$14:$B$27,2,FALSE())+Q30,Q30) -> 0.09 | S30: TBD | T30: 0 | U30: Various | V30: 6 | W30: 0 | X30: 46080 | Y30: =IFERROR(EDATE(X30,T30),"") -> 46080 | Z30: =IFERROR(EDATE(X30,V30),"") -> 46261 | AA30: 46080 | AB30: 46265 | AC30: Export financing | AD30: Per Combined Limit | AE30: HSBC Facilities Letter 27-Feb-2026, Ref GBM NDH 260475 | AF30: INR or FCY equivalent; rate TBD | AG30: =FALSE() -> FALSE | AH30: =FALSE() -> FALSE
A31: 27 | B31: HSBC | C31: Pre-shipment Seller Loan (Uncommitted) | D31: FB | E31: Revolving | F31: =TRUE() -> TRUE | G31: =FALSE() -> FALSE | H31: 0 | I31: INR | J31: 26.08 | K31: =IFERROR(J31,0) -> 26.08 | M31: =IFERROR(IF(D31="FB-Term",IF(A31=UBI_RTL1_SNo,UBI_RTL1_PrincOS,IF(A31=UBI_RTL2_SNo,UBI_RTL2_PrincOS,IF(A31=IB_TL_SNo,IB_TL_PrincOS,IF(A31=RBL_TL_SNo,RBL_TL_PrincOS,IF(A31=YBL_TL_SNo,YBL_TL_PrincOS,IF(A31=IDFC_TL_SNo,IDFC_TL_PrincOS,IF(A31=ICICI_TL_SNo,ICICI_TL_PrincOS,0))))))),IF(L31<>"",L31,IF(UseFullUtil,K31,0))),0) -> 26.08 | N31: =IFERROR(M31/K31,0) -> 1 | O31: =IFERROR(K31-M31,0) -> 0 | P31: Mutually agreed | Q31: 0 | R31: =IFERROR(VLOOKUP(P31,'Instructions & Assumptions'!$A$14:$B$27,2,FALSE())+Q31,Q31) -> 0.09 | S31: TBD | T31: 0 | U31: On Maturity | V31: 6 | W31: 0 | X31: 46080 | Y31: =IFERROR(EDATE(X31,T31),"") -> 46080 | Z31: =IFERROR(EDATE(X31,V31),"") -> 46261 | AA31: 46080 | AB31: 46265 | AC31: Export pre-shipment | AD31: Per Combined Limit | AE31: HSBC Facilities Letter 27-Feb-2026, Ref GBM NDH 260475 | AF31: 6 months; INR or FCY; rate TBD | AG31: =FALSE() -> FALSE | AH31: =FALSE() -> FALSE
A32: 28 | B32: HSBC | C32: Post-Shipment Seller Loan, Open Account (Uncommitted) | D32: FB | E32: Revolving | F32: =TRUE() -> TRUE | G32: =FALSE() -> FALSE | H32: 0 | I32: INR | J32: 26.08 | K32: =IFERROR(J32,0) -> 26.08 | M32: =IFERROR(IF(D32="FB-Term",IF(A32=UBI_RTL1_SNo,UBI_RTL1_PrincOS,IF(A32=UBI_RTL2_SNo,UBI_RTL2_PrincOS,IF(A32=IB_TL_SNo,IB_TL_PrincOS,IF(A32=RBL_TL_SNo,RBL_TL_PrincOS,IF(A32=YBL_TL_SNo,YBL_TL_PrincOS,IF(A32=IDFC_TL_SNo,IDFC_TL_PrincOS,IF(A32=ICICI_TL_SNo,ICICI_TL_PrincOS,0))))))),IF(L32<>"",L32,IF(UseFullUtil,K32,0))),0) -> 26.08 | N32: =IFERROR(M32/K32,0) -> 1 | O32: =IFERROR(K32-M32,0) -> 0 | P32: Mutually agreed | Q32: 0 | R32: =IFERROR(VLOOKUP(P32,'Instructions & Assumptions'!$A$14:$B$27,2,FALSE())+Q32,Q32) -> 0.09 | S32: TBD | T32: 0 | U32: On Maturity | V32: 6 | W32: 0 | X32: 46080 | Y32: =IFERROR(EDATE(X32,T32),"") -> 46080 | Z32: =IFERROR(EDATE(X32,V32),"") -> 46261 | AA32: 46080 | AB32: 46265 | AC32: Export post-shipment | AD32: Per Combined Limit | AE32: HSBC Facilities Letter 27-Feb-2026, Ref GBM NDH 260475 | AF32: 6 months; INR or FCY; rate TBD | AG32: =FALSE() -> FALSE | AH32: =FALSE() -> FALSE
A33: 29 | B33: HSBC | C33: Import Controlling line - 2 (Uncommitted) | D33: NFB | E33: Revolving | F33: =TRUE() -> TRUE | G33: =FALSE() -> FALSE | H33: 0 | I33: INR | J33: 154.58 | K33: =IFERROR(J33,0) -> 154.58 | M33: =IFERROR(IF(D33="FB-Term",IF(A33=UBI_RTL1_SNo,UBI_RTL1_PrincOS,IF(A33=UBI_RTL2_SNo,UBI_RTL2_PrincOS,IF(A33=IB_TL_SNo,IB_TL_PrincOS,IF(A33=RBL_TL_SNo,RBL_TL_PrincOS,IF(A33=YBL_TL_SNo,YBL_TL_PrincOS,IF(A33=IDFC_TL_SNo,IDFC_TL_PrincOS,IF(A33=ICICI_TL_SNo,ICICI_TL_PrincOS,0))))))),IF(L33<>"",L33,IF(UseFullUtil,K33,0))),0) -> 154.58 | N33: =IFERROR(M33/K33,0) -> 1 | O33: =IFERROR(K33-M33,0) -> 0 | P33: Mutually agreed | Q33: 0 | R33: =IFERROR(VLOOKUP(P33,'Instructions & Assumptions'!$A$14:$B$27,2,FALSE())+Q33,Q33) -> 0.09 | S33: TBD | T33: 0 | U33: Various | V33: 6 | W33: 0 | X33: 46080 | Y33: =IFERROR(EDATE(X33,T33),"") -> 46080 | Z33: =IFERROR(EDATE(X33,V33),"") -> 46261 | AA33: 46080 | AB33: 46265 | AC33: Headline LC line | AD33: Per Combined Limit | AE33: HSBC Facilities Letter 27-Feb-2026, Ref GBM NDH 260475 | AF33: Headline LC line for Letter of Credit issuance | AG33: =FALSE() -> FALSE | AH33: =FALSE() -> FALSE
A34: 30 | B34: HSBC | C34: Import Documentary Credit - 12 (Uncommitted) | D34: NFB | E34: Revolving | F34: =TRUE() -> TRUE | G34: =FALSE() -> FALSE | H34: 0 | I34: INR | J34: 154.58 | K34: =IFERROR(J34,0) -> 154.58 | M34: =IFERROR(IF(D34="FB-Term",IF(A34=UBI_RTL1_SNo,UBI_RTL1_PrincOS,IF(A34=UBI_RTL2_SNo,UBI_RTL2_PrincOS,IF(A34=IB_TL_SNo,IB_TL_PrincOS,IF(A34=RBL_TL_SNo,RBL_TL_PrincOS,IF(A34=YBL_TL_SNo,YBL_TL_PrincOS,IF(A34=IDFC_TL_SNo,IDFC_TL_PrincOS,IF(A34=ICICI_TL_SNo,ICICI_TL_PrincOS,0))))))),IF(L34<>"",L34,IF(UseFullUtil,K34,0))),0) -> 154.58 | N34: =IFERROR(M34/K34,0) -> 1 | O34: =IFERROR(K34-M34,0) -> 0 | P34: Fixed commission | Q34: 0 | R34: =IFERROR(VLOOKUP(P34,'Instructions & Assumptions'!$A$14:$B$27,2,FALSE())+Q34,Q34) -> 0 | S34: TBD | T34: 0 | U34: On Maturity | V34: 6 | W34: 0 | X34: 46080 | Y34: =IFERROR(EDATE(X34,T34),"") -> 46080 | Z34: =IFERROR(EDATE(X34,V34),"") -> 46261 | AA34: 46080 | AB34: 46265 | AC34: Import DC issuance | AD34: Per Combined Limit | AE34: HSBC Facilities Letter 27-Feb-2026, Ref GBM NDH 260475 | AF34: Sight / 180-day usance with 120-day cover; rate TBD | AG34: =FALSE() -> FALSE | AH34: =FALSE() -> FALSE
A35: 31 | B35: HSBC | C35: Import Documentary Credit - 13 (Uncommitted) | D35: NFB | E35: Revolving | F35: =TRUE() -> TRUE | G35: =FALSE() -> FALSE | H35: 0 | I35: INR | J35: 10 | K35: =IFERROR(J35,0) -> 10 | M35: =IFERROR(IF(D35="FB-Term",IF(A35=UBI_RTL1_SNo,UBI_RTL1_PrincOS,IF(A35=UBI_RTL2_SNo,UBI_RTL2_PrincOS,IF(A35=IB_TL_SNo,IB_TL_PrincOS,IF(A35=RBL_TL_SNo,RBL_TL_PrincOS,IF(A35=YBL_TL_SNo,YBL_TL_PrincOS,IF(A35=IDFC_TL_SNo,IDFC_TL_PrincOS,IF(A35=ICICI_TL_SNo,ICICI_TL_PrincOS,0))))))),IF(L35<>"",L35,IF(UseFullUtil,K35,0))),0) -> 10 | N35: =IFERROR(M35/K35,0) -> 1 | O35: =IFERROR(K35-M35,0) -> 0 | P35: Fixed commission | Q35: 0 | R35: =IFERROR(VLOOKUP(P35,'Instructions & Assumptions'!$A$14:$B$27,2,FALSE())+Q35,Q35) -> 0 | S35: TBD | T35: 0 | U35: On Maturity | V35: 6 | W35: 0 | X35: 46080 | Y35: =IFERROR(EDATE(X35,T35),"") -> 46080 | Z35: =IFERROR(EDATE(X35,V35),"") -> 46261 | AA35: 46080 | AB35: 46265 | AC35: Import DC issuance | AD35: Per Combined Limit | AE35: HSBC Facilities Letter 27-Feb-2026, Ref GBM NDH 260475 | AF35: Second LC line — relationship to ₹772.9 Cr line unclear; FLAG | AG35: =FALSE() -> FALSE | AH35: =FALSE() -> FALSE
... A37: 33 | B37: HSBC | C37: Guarantees/Bonds Financial (Uncommitted) | D37: NFB | E37: Revolving | F37: =TRUE() -> TRUE | G37: =FALSE() -> FALSE | H37: 0 | I37: INR | J37: 1.94 | K37: =IFERROR(J37,0) -> 1.94 | M37: =IFERROR(IF(D37="FB-Term",IF(A37=UBI_RTL1_SNo,UBI_RTL1_PrincOS,IF(A37=UBI_RTL2_SNo,UBI_RTL2_PrincOS,IF(A37=IB_TL_SNo,IB_TL_PrincOS,IF(A37=RBL_TL_SNo,RBL_TL_PrincOS,IF(A37=YBL_TL_SNo,YBL_TL_PrincOS,IF(A37=IDFC_TL_SNo,IDFC_TL_PrincOS,IF(A37=ICICI_TL_SNo,ICICI_TL_PrincOS,0))))))),IF(L37<>"",L37,IF(UseFullUtil,K37,0))),0) -> 1.94 | N37: =IFERROR(M37/K37,0) -> 1 | O37: =IFERROR(K37-M37,0) -> 0 | P37: Mutually agreed | Q37: 0 | R37: =IFERROR(VLOOKUP(P37,'Instructions & Assumptions'!$A$14:$B$27,2,FALSE())+Q37,Q37) -> 0.09 | S37: TBD | T37: 0 | U37: On Maturity | V37: 48 | W37: 0 | X37: 46080 | Y37: =IFERROR(EDATE(X37,T37),"") -> 46080 | Z37: =IFERROR(EDATE(X37,V37),"") -> 47541 | AA37: 46080 | AB37: 46265 | AC37: Financial BG | AD37: Per Combined Limit | AE37: HSBC Facilities Letter 27-Feb-2026, Ref GBM NDH 260475 | AF37: 3 years + 12-month claim period | AG37: =FALSE() -> FALSE | AH37: =FALSE() -> FALSE
A38: 34 | B38: HDFC Bank | C38: Letter of Credit (WC parent) | D38: NFB | E38: Revolving | F38: =FALSE() -> FALSE | G38: =FALSE() -> FALSE | H38: 2 | I38: INR | J38: 250 | K38: =IFERROR(J38,0) -> 250 | M38: =IFERROR(IF(D38="FB-Term",IF(A38=UBI_RTL1_SNo,UBI_RTL1_PrincOS,IF(A38=UBI_RTL2_SNo,UBI_RTL2_PrincOS,IF(A38=IB_TL_SNo,IB_TL_PrincOS,IF(A38=RBL_TL_SNo,RBL_TL_PrincOS,IF(A38=YBL_TL_SNo,YBL_TL_PrincOS,IF(A38=IDFC_TL_SNo,IDFC_TL_PrincOS,IF(A38=ICICI_TL_SNo,ICICI_TL_PrincOS,0))))))),IF(L38<>"",L38,IF(UseFullUtil,K38,0))),0) -> 250 | N38: =IFERROR(M38/K38,0) -> 1 | O38: =IFERROR(K38-M38,0) -> 0 | P38: Fixed commission | Q38: 0.005 | R38: =IFERROR(VLOOKUP(P38,'Instructions & Assumptions'!$A$14:$B$27,2,FALSE())+Q38,Q38) -> 0.005 | S38: Fixed | T38: 0 | U38: On Maturity | V38: 12 | W38: 0 | X38: 46107 | Y38: =IFERROR(EDATE(X38,T38),"") -> 46107 | Z38: =IFERROR(EDATE(X38,V38),"") -> 46472 | AA38: 46107 | AB38: 46265 | AC38: WC LC issuance | AD38: 1st p-p on CA; 2nd p-p on FA (incl. immovable + leasehold); 2nd p-p intangibles; Pledge 51%; OPJSTPL CG; JCL CG; JSL DSU; LoC JSL | AE38: HDFC Bank Offer Letter 26-Mar-2026, Ref CAM012101260020 | AF38: LC 0.50% (daily). Multiple sub-limits within ₹250 Cr cap. Processing 0.12% p.a.; renewal 0.10%. JSL 2.5x cover; HR coil offtake 3mo pre-DCCO. | AG38: =FALSE() -> FALSE | AH38: =FALSE() -> FALSE
A39: 35 | B39: HDFC Bank | C39: Post Shipment Finance (sub of LC) | D39: FB | E39: Revolving | F39: =TRUE() -> TRUE | G39: =FALSE() -> FALSE | H39: 0 | I39: INR | J39: 100 | K39: =IFERROR(J39,0) -> 100 | M39: =IFERROR(IF(D39="FB-Term",IF(A39=UBI_RTL1_SNo,UBI_RTL1_PrincOS,IF(A39=UBI_RTL2_SNo,UBI_RTL2_PrincOS,IF(A39=IB_TL_SNo,IB_TL_PrincOS,IF(A39=RBL_TL_SNo,RBL_TL_PrincOS,IF(A39=YBL_TL_SNo,YBL_TL_PrincOS,IF(A39=IDFC_TL_SNo,IDFC_TL_PrincOS,IF(A39=ICICI_TL_SNo,ICICI_TL_PrincOS,0))))))),IF(L39<>"",L39,IF(UseFullUtil,K39,0))),0) -> 100 | N39: =IFERROR(M39/K39,0) -> 1 | O39: =IFERROR(K39-M39,0) -> 0 | P39: To be decided | Q39: 0 | R39: =IFERROR(VLOOKUP(P39,'Instructions & Assumptions'!$A$14:$B$27,2,FALSE())+Q39,Q39) -> 0.095 | S39: TBD | T39: 0 | U39: On Maturity | V39: 6 | W39: 0 | X39: 46107 | Y39: =IFERROR(EDATE(X39,T39),"") -> 46107 | Z39: =IFERROR(EDATE(X39,V39),"") -> 46291 | AA39: 46107 | AB39: 46265 | AC39: Post-shipment finance | AD39: Same as LC parent | AE39: HDFC Bank Offer Letter 26-Mar-2026, Ref CAM012101260020 | AF39: Rate TBD at drawdown — FLAG; order-backed | AG39: =FALSE() -> FALSE | AH39: =FALSE() -> FALSE
A40: 36 | B40: HDFC Bank | C40: Pre-shipment Finance (sub of LC) | D40: FB | E40: Revolving | F40: =TRUE() -> TRUE | G40: =FALSE() -> FALSE | H40: 0 | I40: INR | J40: 200 | K40: =IFERROR(J40,0) -> 200 | M40: =IFERROR(IF(D40="FB-Term",IF(A40=UBI_RTL1_SNo,UBI_RTL1_PrincOS,IF(A40=UBI_RTL2_SNo,UBI_RTL2_PrincOS,IF(A40=IB_TL_SNo,IB_TL_PrincOS,IF(A40=RBL_TL_SNo,RBL_TL_PrincOS,IF(A40=YBL_TL_SNo,YBL_TL_PrincOS,IF(A40=IDFC_TL_SNo,IDFC_TL_PrincOS,IF(A40=ICICI_TL_SNo,ICICI_TL_PrincOS,0))))))),IF(L40<>"",L40,IF(UseFullUtil,K40,0))),0) -> 200 | N40: =IFERROR(M40/K40,0) -> 1 | O40: =IFERROR(K40-M40,0) -> 0 | P40: To be decided | Q40: 0 | R40: =IFERROR(VLOOKUP(P40,'Instructions & Assumptions'!$A$14:$B$27,2,FALSE())+Q40,Q40) -> 0.095 | S40: TBD | T40: 0 | U40: On Maturity | V40: 6 | W40: 0 | X40: 46107 | Y40: =IFERROR(EDATE(X40,T40),"") -> 46107 | Z40: =IFERROR(EDATE(X40,V40),"") -> 46291 | AA40: 46107 | AB40: 46265 | AC40: Pre-shipment finance | AD40: Same as LC parent | AE40: HDFC Bank Offer Letter 26-Mar-2026, Ref CAM012101260020 | AF40: Rate TBD at drawdown — FLAG; order-backed | AG40: =FALSE() -> FALSE | AH40: =FALSE() -> FALSE
A41: 37 | B41: HDFC Bank | C41: SBLC (sub of LC) | D41: NFB | E41: Revolving | F41: =TRUE() -> TRUE | G41: =FALSE() -> FALSE | H41: 0 | I41: INR | J41: 250 | K41: =IFERROR(J41,0) -> 250 | M41: =IFERROR(IF(D41="FB-Term",IF(A41=UBI_RTL1_SNo,UBI_RTL1_PrincOS,IF(A41=UBI_RTL2_SNo,UBI_RTL2_PrincOS,IF(A41=IB_TL_SNo,IB_TL_PrincOS,IF(A41=RBL_TL_SNo,RBL_TL_PrincOS,IF(A41=YBL_TL_SNo,YBL_TL_PrincOS,IF(A41=IDFC_TL_SNo,IDFC_TL_PrincOS,IF(A41=ICICI_TL_SNo,ICICI_TL_PrincOS,0))))))),IF(L41<>"",L41,IF(UseFullUtil,K41,0))),0) -> 250 | N41: =IFERROR(M41/K41,0) -> 1 | O41: =IFERROR(K41-M41,0) -> 0 | P41: To be decided | Q41: 0 | R41: =IFERROR(VLOOKUP(P41,'Instructions & Assumptions'!$A$14:$B$27,2,FALSE())+Q41,Q41) -> 0.095 | S41: TBD | T41: 0 | U41: On Maturity | V41: 12 | W41: 0 | X41: 46107 | Y41: =IFERROR(EDATE(X41,T41),"") -> 46107 | Z41: =IFERROR(EDATE(X41,V41),"") -> 46472 | AA41: 46107 | AB41: 46265 | AC41: SBLC for Buyers Credit | AD41: Same as LC parent | AE41: HDFC Bank Offer Letter 26-Mar-2026, Ref CAM012101260020 | AF41: Rate TBD at drawdown | AG41: =FALSE() -> FALSE | AH41: =FALSE() -> FALSE
A42: 38 | B42: HDFC Bank | C42: Cash Credit (sub of LC) | D42: FB | E42: Revolving | F42: =TRUE() -> TRUE | G42: =FALSE() -> FALSE | H42: 0 | I42: INR | J42: 50 | K42: =IFERROR(J42,0) -> 50 | M42: =IFERROR(IF(D42="FB-Term",IF(A42=UBI_RTL1_SNo,UBI_RTL1_PrincOS,IF(A42=UBI_RTL2_SNo,UBI_RTL2_PrincOS,IF(A42=IB_TL_SNo,IB_TL_PrincOS,IF(A42=RBL_TL_SNo,RBL_TL_PrincOS,IF(A42=YBL_TL_SNo,YBL_TL_PrincOS,IF(A42=IDFC_TL_SNo,IDFC_TL_PrincOS,IF(A42=ICICI_TL_SNo,ICICI_TL_PrincOS,0))))))),IF(L42<>"",L42,IF(UseFullUtil,K42,0))),0) -> 50 | N42: =IFERROR(M42/K42,0) -> 1 | O42: =IFERROR(K42-M42,0) -> 0 | P42: 14-day Repo (HDFC) | Q42: 0 | R42: =IFERROR(VLOOKUP(P42,'Instructions & Assumptions'!$A$14:$B$27,2,FALSE())+Q42,Q42) -> 0.0815 | S42: Floating | T42: 0 | U42: On Demand | V42: 12 | W42: 0 | X42: 46107 | Y42: =IFERROR(EDATE(X42,T42),"") -> 46107 | Z42: =IFERROR(EDATE(X42,V42),"") -> 46472 | AA42: 46107 | AB42: 46265 | AC42: Working capital | AD42: Same as LC parent | AE42: HDFC Bank Offer Letter 26-Mar-2026, Ref CAM012101260020 | AF42: CC = 8.15% linked to 14-day Repo | AG42: =FALSE() -> FALSE | AH42: =FALSE() -> FALSE
A43: 39 | B43: HDFC Bank | C43: WCDL (sub of LC) | D43: FB | E43: Revolving | F43: =TRUE() -> TRUE | G43: =FALSE() -> FALSE | H43: 0 | I43: INR | J43: 50 | K43: =IFERROR(J43,0) -> 50 | M43: =IFERROR(IF(D43="FB-Term",IF(A43=UBI_RTL1_SNo,UBI_RTL1_PrincOS,IF(A43=UBI_RTL2_SNo,UBI_RTL2_PrincOS,IF(A43=IB_TL_SNo,IB_TL_PrincOS,IF(A43=RBL_TL_SNo,RBL_TL_PrincOS,IF(A43=YBL_TL_SNo,YBL_TL_PrincOS,IF(A43=IDFC_TL_SNo,IDFC_TL_PrincOS,IF(A43=ICICI_TL_SNo,ICICI_TL_PrincOS,0))))))),IF(L43<>"",L43,IF(UseFullUtil,K43,0))),0) -> 50 | N43: =IFERROR(M43/K43,0) -> 1 | O43: =IFERROR(K43-M43,0) -> 0 | P43: To be decided | Q43: 0 | R43: =IFERROR(VLOOKUP(P43,'Instructions & Assumptions'!$A$14:$B$27,2,FALSE())+Q43,Q43) -> 0.095 | S43: TBD | T43: 0 | U43: On Maturity | V43: 3 | W43: 0 | X43: 46107 | Y43: =IFERROR(EDATE(X43,T43),"") -> 46107 | Z43: =IFERROR(EDATE(X43,V43),"") -> 46199 | AA43: 46107 | AB43: 46265 | AC43: Working capital | AD43: Same as LC parent | AE43: HDFC Bank Offer Letter 26-Mar-2026, Ref CAM012101260020 | AF43: Rate TBD; max 90-day tranche | AG43: =FALSE() -> FALSE | AH43: =FALSE() -> FALSE
A44: 40 | B44: HDFC Bank | C44: FD-OD (FD-Backed) | D44: FB-FDbacked | E44: Revolving | F44: =FALSE() -> FALSE | G44: =TRUE() -> TRUE | H44: 3 | I44: INR | J44: 50 | K44: =IFERROR(J44,0) -> 50 | M44: =IFERROR(IF(D44="FB-Term",IF(A44=UBI_RTL1_SNo,UBI_RTL1_PrincOS,IF(A44=UBI_RTL2_SNo,UBI_RTL2_PrincOS,IF(A44=IB_TL_SNo,IB_TL_PrincOS,IF(A44=RBL_TL_SNo,RBL_TL_PrincOS,IF(A44=YBL_TL_SNo,YBL_TL_PrincOS,IF(A44=IDFC_TL_SNo,IDFC_TL_PrincOS,IF(A44=ICICI_TL_SNo,ICICI_TL_PrincOS,0))))))),IF(L44<>"",L44,IF(UseFullUtil,K44,0))),0) -> 50 | N44: =IFERROR(M44/K44,0) -> 1 | O44: =IFERROR(K44-M44,0) -> 0 | P44: FD Rate (HDFC) | Q44: 0.01 | R44: =IFERROR(VLOOKUP(P44,'Instructions & Assumptions'!$A$14:$B$27,2,FALSE())+Q44,Q44) -> 0.08 | S44: Floating | T44: 0 | U44: On Demand | V44: 12 | W44: 0 | X44: 46107 | Y44: =IFERROR(EDATE(X44,T44),"") -> 46107 | Z44: =IFERROR(EDATE(X44,V44),"") -> 46472 | AA44: 46107 | AB44: 46265 | AC44: Cash flow mismatch | AD44: 100% margin via lien on FD held by JFL/group | AE44: HDFC Bank Offer Letter 26-Mar-2026, Ref CAM012101260020 | AF44: FD Rate + 1% spread; monthly rests | AG44: =FALSE() -> FALSE | AH44: =FALSE() -> FALSE
A45: 41 | B45: HDFC Bank | C45: BG (sub of FD-OD) | D45: NFB | E45: Revolving | F45: =TRUE() -> TRUE | G45: =FALSE() -> FALSE | H45: 0 | I45: INR | J45: 50 | K45: =IFERROR(J45,0) -> 50 | M45: =IFERROR(IF(D45="FB-Term",IF(A45=UBI_RTL1_SNo,UBI_RTL1_PrincOS,IF(A45=UBI_RTL2_SNo,UBI_RTL2_PrincOS,IF(A45=IB_TL_SNo,IB_TL_PrincOS,IF(A45=RBL_TL_SNo,RBL_TL_PrincOS,IF(A45=YBL_TL_SNo,YBL_TL_PrincOS,IF(A45=IDFC_TL_SNo,IDFC_TL_PrincOS,IF(A45=ICICI_TL_SNo,ICICI_TL_PrincOS,0))))))),IF(L45<>"",L45,IF(UseFullUtil,K45,0))),0) -> 50 | N45: =IFERROR(M45/K45,0) -> 1 | O45: =IFERROR(K45-M45,0) -> 0 | P45: Fixed commission | Q45: 0 | R45: =IFERROR(VLOOKUP(P45,'Instructions & Assumptions'!$A$14:$B$27,2,FALSE())+Q45,Q45) -> 0 | S45: TBD | T45: 0 | U45: On Maturity | V45: 36 | W45: 0 | X45: 46107 | Y45: =IFERROR(EDATE(X45,T45),"") -> 46107 | Z45: =IFERROR(EDATE(X45,V45),"") -> 47203 | AA45: 46107 | AB45: 46265 | AC45: BG within FD-OD | AD45: 100% FD margin | AE45: HDFC Bank Offer Letter 26-Mar-2026, Ref CAM012101260020 | AF45: Sub of FD-OD; 36 months incl claim | AG45: =FALSE() -> FALSE | AH45: =FALSE() -> FALSE
A46: 42 | B46: ICICI Bank (TL) | C46: Term Loan — TAKEOVER of disbursed consortium | D46: FB-Term | E46: Non-Revolving | F46: =FALSE() -> FALSE | G46: =FALSE() -> FALSE | H46: 1 | I46: INR | J46: 840 | K46: =IFERROR(J46,0) -> 840 | M46: =IFERROR(IF(D46="FB-Term",IF(A46=UBI_RTL1_SNo,UBI_RTL1_PrincOS,IF(A46=UBI_RTL2_SNo,UBI_RTL2_PrincOS,IF(A46=IB_TL_SNo,IB_TL_PrincOS,IF(A46=RBL_TL_SNo,RBL_TL_PrincOS,IF(A46=YBL_TL_SNo,YBL_TL_PrincOS,IF(A46=IDFC_TL_SNo,IDFC_TL_PrincOS,IF(A46=ICICI_TL_SNo,ICICI_TL_PrincOS,0))))))),IF(L46<>"",L46,IF(UseFullUtil,K46,0))),0) -> 840 | N46: =IFERROR(M46/K46,0) -> 1 | O46: =IFERROR(K46-M46,0) -> 0 | P46: 3M I-MCLR (ICICI) | Q46: 0.006 | R46: =IFERROR(VLOOKUP(P46,'Instructions & Assumptions'!$A$14:$B$27,2,FALSE())+Q46,Q46) -> 0.087 | S46: Floating | T46: 12 | U46: Quarterly | V46: 156 | W46: 48 | X46: 46108 | Y46: 46568 | Z46: 50860 | AA46: 46108 | AB46: =Z46 -> 50860 | AC46: TAKEOVER of disbursed consortium TL only (excludes cost overrun and undisbursed) | AD46: Consortium-standard: 1st p-p on FA; 2nd p-p on CA; Pledge 51%; OPJSTPL CG; JCL CG; JSL DSU; LoC JSL; 1st pari-passu Escrow at UBI | AE46: ICICI TL CAL 27-Mar-2026, Ref CAL504005729787 | AF46: ICICI TL: TAKEOVER of disbursed debt — NOT additive. Adj Cons = ₹4,666 − ₹840 = ₹3,826 Cr. Put Option every 5y from DCCO (first Apr-2031, 90-day notice). Moratorium 31-Mar-2027. See F-05. | AG46: =FALSE() -> FALSE | AH46: =TRUE() -> TRUE
A47: 43 | B47: ICICI Bank (TL) | C47: BG Financial (sub of RTL) | D47: NFB | E47: Revolving | F47: =TRUE() -> TRUE | G47: =FALSE() -> FALSE | H47: 0 | I47: INR | J47: 20 | K47: =IFERROR(J47,0) -> 20 | M47: =IFERROR(IF(D47="FB-Term",IF(A47=UBI_RTL1_SNo,UBI_RTL1_PrincOS,IF(A47=UBI_RTL2_SNo,UBI_RTL2_PrincOS,IF(A47=IB_TL_SNo,IB_TL_PrincOS,IF(A47=RBL_TL_SNo,RBL_TL_PrincOS,IF(A47=YBL_TL_SNo,YBL_TL_PrincOS,IF(A47=IDFC_TL_SNo,IDFC_TL_PrincOS,IF(A47=ICICI_TL_SNo,ICICI_TL_PrincOS,0))))))),IF(L47<>"",L47,IF(UseFullUtil,K47,0))),0) -> 20 | N47: =IFERROR(M47/K47,0) -> 1 | O47: =IFERROR(K47-M47,0) -> 0 | P47: Fixed commission | Q47: 0.0075 | R47: =IFERROR(VLOOKUP(P47,'Instructions & Assumptions'!$A$14:$B$27,2,FALSE())+Q47,Q47) -> 0.0075 | S47: Fixed | T47: 0 | U47: On Maturity | V47: 36 | W47: 0 | X47: 46108 | Y47: =IFERROR(EDATE(X47,T47),"") -> 46108 | Z47: =IFERROR(EDATE(X47,V47),"") -> 47204 | AA47: 46108 | AB47: =EDATE(X47,V47) -> 47204 | AC47: Financial BG | AD47: Same as RTL parent | AE47: ICICI TL CAL 27-Mar-2026, Ref CAL504005729787 | AF47: 0.75% commission; min ₹500/instrument; upfront | AG47: =TRUE() -> TRUE | AH47: =FALSE() -> FALSE
A48: 44 | B48: ICICI Bank (TL) | C48: SBLC Buyers Credit (sub of RTL) | D48: NFB | E48: Revolving | F48: =TRUE() -> TRUE | G48: =FALSE() -> FALSE | H48: 0 | I48: INR | J48: 20 | K48: =IFERROR(J48,0) -> 20 | M48: =IFERROR(IF(D48="FB-Term",IF(A48=UBI_RTL1_SNo,UBI_RTL1_PrincOS,IF(A48=UBI_RTL2_SNo,UBI_RTL2_PrincOS,IF(A48=IB_TL_SNo,IB_TL_PrincOS,IF(A48=RBL_TL_SNo,RBL_TL_PrincOS,IF(A48=YBL_TL_SNo,YBL_TL_PrincOS,IF(A48=IDFC_TL_SNo,IDFC_TL_PrincOS,IF(A48=ICICI_TL_SNo,ICICI_TL_PrincOS,0))))))),IF(L48<>"",L48,IF(UseFullUtil,K48,0))),0) -> 20 | N48: =IFERROR(M48/K48,0) -> 1 | O48: =IFERROR(K48-M48,0) -> 0 | P48: Fixed commission | Q48: 0.0075 | R48: =IFERROR(VLOOKUP(P48,'Instructions & Assumptions'!$A$14:$B$27,2,FALSE())+Q48,Q48) -> 0.0075 | S48: Fixed | T48: 0 | U48: On Maturity | V48: 36 | W48: 0 | X48: 46108 | Y48: =IFERROR(EDATE(X48,T48),"") -> 46108 | Z48: =IFERROR(EDATE(X48,V48),"") -> 47204 | AA48: 46108 | AB48: =EDATE(X48,V48) -> 47204 | AC48: SBLC for Buyers Credit | AD48: Same as RTL parent | AE48: ICICI TL CAL 27-Mar-2026, Ref CAL504005729787 | AF48: 0.75% commission | AG48: =TRUE() -> TRUE | AH48: =FALSE() -> FALSE
A50: KPIs → See Lender Summary sheet for all computed KPI totals (Sanctioned Debt, Bucket splits, Adjusted Consortium, WAC, Run-rate interest).

Sheet Term Loans
A1: TERM LOANS — Consortium & Bridge Summary Panel
A2: Side-by-side parameter comparison of all 7 term loans | Figures pulled from Facility Master | As of: 21-May-2026
A3: Parameter | B3: UBI RTL-I | C3: UBI RTL-II | D3: Indian Bank | E3: RBL Bank (Bridge) | F3: YES Bank | G3: IDFC First | H3: ICICI TL (Takeover) | I3: Combined
A4: Sanctioned (₹ Cr) | B4: 1125 | C4: 236 | D4: 235 | E4: 200 | F4: 650 | G4: 530 | H4: 840 | I4: =B4+C4+D4+E4+F4+G4+H4 -> 3816
A5: Effective O/S (₹ Cr) | B5: 1125 | C5: 236 | D5: 235 | E5: 200 | F5: 650 | G5: 530 | H5: 840 | I5: =B5+C5+D5+E5+F5+G5+H5 -> 3816
A6: Drawdown Date | B6: 45104 | C6: 45920 | D6: 44927 | E6: 45974 | F6: 46020 | G6: 46031 | H6: 46108
A7: Rep Start Date | B7: 46568 | C7: 46568 | D7: 46477 | E7: 46339 | F7: 46568 | G7: 46568 | H7: 46568
A8: Maturity Date | B8: 50860 | C8: 50860 | D8: =INDEX('Facility Master'!Z:Z, MATCH(IB_TL_SNo,'Facility Master'!A:A,0)) -> 50770 | E8: 46339 | F8: 50860 | G8: 50860 | H8: 50860
A9: Moratorium (Months) | B9: 48 | C9: =INDEX('Facility Master'!T:T, MATCH(UBI_RTL2_SNo,'Facility Master'!A:A,0)) -> 21 | D9: =INDEX('Facility Master'!T:T, MATCH(IB_TL_SNo,'Facility Master'!A:A,0)) -> 50 | E9: 0 | F9: 12 | G9: 12 | H9: 12
A10: Repayment Frequency | B10: Quarterly | C10: Quarterly | D10: Quarterly | E10: Bullet ⚠ | F10: Quarterly | G10: Quarterly | H10: Quarterly
A11: Tenor (Months) | B11: 192 | C11: 162 | D11: =INDEX('Facility Master'!V:V, MATCH(IB_TL_SNo,'Facility Master'!A:A,0)) -> 192 | E11: 12 | F11: 160 | G11: =INDEX('Facility Master'!V:V, MATCH(IDFC_TL_SNo,'Facility Master'!A:A,0)) -> 156 | H11: 156
A12: No. of Instalments | B12: 48 | C12: 48 | D12: 48 | E12: 1 | F12: 48 | G12: 48 | H12: 48
A13: Benchmark Rate | B13: 1Y MCLR | C13: 1Y MCLR | D13: =INDEX('Facility Master'!P:P, MATCH(IB_TL_SNo,'Facility Master'!A:A,0)) -> 1Y MCLR (Indian Bank) | E13: TBD ⚠ | F13: EBLR | G13: EBLR | H13: 3M I-MCLR
A14: Spread (p.a.) | B14: 0.005 | C14: 0.005 | D14: 0.005 | E14: 0 | F14: 0.0345 | G14: 0.0105 | H14: 0.006
A15: Effective Rate p.a. | B15: =IFERROR(INDEX('Facility Master'!R:R,MATCH(UBI_RTL1_SNo,'Facility Master'!A:A,0)),0) -> 0.094 | C15: =IFERROR(INDEX('Facility Master'!R:R,MATCH(UBI_RTL2_SNo,'Facility Master'!A:A,0)),0) -> 0.091 | D15: =IFERROR(INDEX('Facility Master'!R:R,MATCH(IB_TL_SNo,'Facility Master'!A:A,0)),0) -> 0.094 | E15: =IFERROR(INDEX('Facility Master'!R:R,MATCH(RBL_TL_SNo,'Facility Master'!A:A,0)),0) -> 0.095 | F15: =IFERROR(INDEX('Facility Master'!R:R,MATCH(YBL_TL_SNo,'Facility Master'!A:A,0)),0) -> 0.0955 | G15: =IFERROR(INDEX('Facility Master'!R:R,MATCH(IDFC_TL_SNo,'Facility Master'!A:A,0)),0) -> 0.088 | H15: =IFERROR(INDEX('Facility Master'!R:R,MATCH(ICICI_TL_SNo,'Facility Master'!A:A,0)),0) -> 0.087 | I15: =SUMPRODUCT(B4:H4,B15:H15)/I4 -> 0.091748166
A16: Rate Type | B16: Floating | C16: Floating | D16: Floating | E16: TBD ⚠ | F16: Floating | G16: Floating | H16: Floating
A17: Sanction Reference | B17: UBI SL 20-Sep-2025 | C17: UBI SL 20-Sep-2025 | D17: IB Amend 26-Sep-2025 | E17: RBL SL 13-Nov-2025 | F17: YBL FL 29-Dec-2025 | G17: IDFC SL 09-Jan-2026 | H17: ICICI TL 27-Mar-2026
A18: Combined Total | B18: =SUM(B4:H4) -> 3816 | C18: — | D18: 7 TLs | E18: 48 Instals | F18: (excl. RBL bullet) | G18: =SUMPRODUCT(B4:H4,B15:H15)/SUM(B4:H4) -> 0.091748166
A20: MODEL NOTES
A21: UBI RTL-I | B21: Renewal of existing consortium TL (first drawdown 27-Jun-2023). 4-year moratorium ends 26-Jun-2027. 1Y MCLR (UBI) 8.90% + 0.50% = 9.40% p.a.
A22: UBI RTL-II | B22: Fresh facility within the 20-Sep-2025 UBI sanction letter. Same consortium 16yr/48-qtr structure. 1Y MCLR (UBI) 8.60% + 0.50% = 9.10% p.a.
A23: ⚠ Indian Bank | B23: ₹235 Cr DERIVED from 26-Sep-2025 amendment ticket (8Q × ₹2.9375 + 40Q × ₹5.2875 = ₹235 ✓). First instalment 31-Mar-2027 — ONE QUARTER EARLIER than consortium peers.
A24: ⚠ RBL Bank | B24: ₹200 Cr 12-MONTH BULLET bridge (NOT amortising). Drawn 13-Nov-2025; matures 13-Nov-2026. Rate TBD at disbursement. REFINANCE EVENT required Q3 FY27 — see Flag F-02.
A25: ⚠ YES Bank | B25: EBLR + 3.45% (current EBLR not stated in letter). Disbursement caps: ₹485 Cr pre-COD / ₹165 Cr post-COD. Cash Sweep: DSCR > 1.5x triggers ₹75 Cr/yr from 01-Apr-2028.
A26: ⚠ IDFC First | B26: EBLR 7.75% + 1.05% = 8.80%. First covenant test FY27 — 2 YEARS EARLIER than consortium peers. IDFC-specific DSCR definition differs from consortium standard — see Flag F-04.
A27: ⚠ ICICI TL | B27: ₹840 Cr TAKEOVER of disbursed consortium TL (NOT additive). I-MCLR-3M + 0.60% = 8.70%. 5-YEAR PUT OPTION from DCCO (first: 01-Apr-2031). Adjusted Consortium = ₹4,666 − ₹840 = ₹3,826 Cr.

Sheet Working Capital Facilities
A1: WORKING CAPITAL FACILITIES — Fund-Based WC Lines
A2: Filtered view of fund-based WC lines (FB / FB-FDbacked) — all values linked from Facility Master via INDEX. Includes HSBC uncommitted lines (Bucket 4, sub-limits).
A3: S.No | B3: Lender | C3: Facility | D3: Category | E3: Sub-Limit? | F3: Ccy | G3: Sanc (₹ Cr) | H3: Eff O/S | I3: Util % | J3: Headroom | K3: Benchmark | L3: Spread | M3: Eff Rate p.a. | N3: Validity
A4: =IFERROR('Facility Master'!A13,"") -> 9 | B4: =IFERROR('Facility Master'!B13,"") -> RBL Bank | C4: =IFERROR('Facility Master'!C13,"") -> FDOD (Overdraft against FD) | D4: =IFERROR('Facility Master'!D13,"") -> FB-FDbacked | E4: =IFERROR(IF('Facility Master'!F13,"Sub-limit","Standalone"),"") -> Standalone | F4: =IFERROR('Facility Master'!I13,"") -> INR | G4: =IFERROR('Facility Master'!K13,0) -> 100 | H4: =IFERROR('Facility Master'!M13,0) -> 100 | I4: =IFERROR('Facility Master'!N13,0) -> 1 | J4: =IFERROR('Facility Master'!O13,0) -> 0 | K4: =IFERROR('Facility Master'!P13,"") -> To be decided | L4: =IFERROR('Facility Master'!Q13,0) -> 0 | M4: =IFERROR('Facility Master'!R13,0) -> 0.095 | N4: =IFERROR('Facility Master'!AB13,"") -> 46265
A5: =IFERROR('Facility Master'!A19,"") -> 15 | B5: =IFERROR('Facility Master'!B19,"") -> ICICI Bank | C5: =IFERROR('Facility Master'!C19,"") -> Cash Credit (WC) | D5: =IFERROR('Facility Master'!D19,"") -> FB | E5: =IFERROR(IF('Facility Master'!F19,"Sub-limit","Standalone"),"") -> Standalone | F5: =IFERROR('Facility Master'!I19,"") -> INR | G5: =IFERROR('Facility Master'!K19,0) -> 100 | H5: =IFERROR('Facility Master'!M19,0) -> 100 | I5: =IFERROR('Facility Master'!N19,0) -> 1 | J5: =IFERROR('Facility Master'!O19,0) -> 0 | K5: =IFERROR('Facility Master'!P19,"") -> 6M I-MCLR (ICICI) | L5: =IFERROR('Facility Master'!Q19,0) -> 0.002 | M5: =IFERROR('Facility Master'!R19,0) -> 0.085 | N5: =IFERROR('Facility Master'!AB19,"") -> 46421
A6: =IFERROR('Facility Master'!A20,"") -> 16 | B6: =IFERROR('Facility Master'!B20,"") -> ICICI Bank | C6: =IFERROR('Facility Master'!C20,"") -> WCDL (sub-limit of CC) | D6: =IFERROR('Facility Master'!D20,"") -> FB | E6: =IFERROR(IF('Facility Master'!F20,"Sub-limit","Standalone"),"") -> Sub-limit | F6: =IFERROR('Facility Master'!I20,"") -> INR | G6: =IFERROR('Facility Master'!K20,0) -> 100 | H6: =IFERROR('Facility Master'!M20,0) -> 100 | I6: =IFERROR('Facility Master'!N20,0) -> 1 | J6: =IFERROR('Facility Master'!O20,0) -> 0 | K6: =IFERROR('Facility Master'!P20,"") -> Repo Rate | L6: =IFERROR('Facility Master'!Q20,0) -> 0 | M6: =IFERROR('Facility Master'!R20,0) -> 0.0525 | N6: =IFERROR('Facility Master'!AB20,"") -> 46421
A7: =IFERROR('Facility Master'!A24,"") -> 20 | B7: =IFERROR('Facility Master'!B24,"") -> HSBC | C7: =IFERROR('Facility Master'!C24,"") -> Working Capital Loan (Uncommitted, sub of #1) | D7: =IFERROR('Facility Master'!D24,"") -> FB | E7: =IFERROR(IF('Facility Master'!F24,"Sub-limit","Standalone"),"") -> Sub-limit | F7: =IFERROR('Facility Master'!I24,"") -> INR | G7: =IFERROR('Facility Master'!K24,0) -> 26.08 | H7: =IFERROR('Facility Master'!M24,0) -> 26.08 | I7: =IFERROR('Facility Master'!N24,0) -> 1 | J7: =IFERROR('Facility Master'!O24,0) -> 0 | K7: =IFERROR('Facility Master'!P24,"") -> Mutually agreed | L7: =IFERROR('Facility Master'!Q24,0) -> 0 | M7: =IFERROR('Facility Master'!R24,0) -> 0.09 | N7: =IFERROR('Facility Master'!AB24,"") -> 46265
A8: =IFERROR('Facility Master'!A25,"") -> 21 | B8: =IFERROR('Facility Master'!B25,"") -> HSBC | C8: =IFERROR('Facility Master'!C25,"") -> Overdraft (Uncommitted, sub of WCL) | D8: =IFERROR('Facility Master'!D25,"") -> FB | E8: =IFERROR(IF('Facility Master'!F25,"Sub-limit","Standalone"),"") -> Sub-limit | F8: =IFERROR('Facility Master'!I25,"") -> INR | G8: =IFERROR('Facility Master'!K25,0) -> 10.432 | H8: =IFERROR('Facility Master'!M25,0) -> 10.432 | I8: =IFERROR('Facility Master'!N25,0) -> 1 | J8: =IFERROR('Facility Master'!O25,0) -> 0 | K8: =IFERROR('Facility Master'!P25,"") -> Mutually agreed | L8: =IFERROR('Facility Master'!Q25,0) -> 0 | M8: =IFERROR('Facility Master'!R25,0) -> 0.09 | N8: =IFERROR('Facility Master'!AB25,"") -> 46265
A9: =IFERROR('Facility Master'!A28,"") -> 24 | B9: =IFERROR('Facility Master'!B28,"") -> HSBC | C9: =IFERROR('Facility Master'!C28,"") -> Pre-shipment Buyer Loan (Uncommitted) | D9: =IFERROR('Facility Master'!D28,"") -> FB | E9: =IFERROR(IF('Facility Master'!F28,"Sub-limit","Standalone"),"") -> Sub-limit | F9: =IFERROR('Facility Master'!I28,"") -> INR | G9: =IFERROR('Facility Master'!K28,0) -> 26.08 | H9: =IFERROR('Facility Master'!M28,0) -> 26.08 | I9: =IFERROR('Facility Master'!N28,0) -> 1 | J9: =IFERROR('Facility Master'!O28,0) -> 0 | K9: =IFERROR('Facility Master'!P28,"") -> Mutually agreed | L9: =IFERROR('Facility Master'!Q28,0) -> 0 | M9: =IFERROR('Facility Master'!R28,0) -> 0.09 | N9: =IFERROR('Facility Master'!AB28,"") -> 46265
A10: =IFERROR('Facility Master'!A29,"") -> 25 | B10: =IFERROR('Facility Master'!B29,"") -> HSBC | C10: =IFERROR('Facility Master'!C29,"") -> Post-Shipment Buyer Loan / DPF / LAI (Uncommitted) | D10: =IFERROR('Facility Master'!D29,"") -> FB | E10: =IFERROR(IF('Facility Master'!F29,"Sub-limit","Standalone"),"") -> Sub-limit | F10: =IFERROR('Facility Master'!I29,"") -> INR | G10: =IFERROR('Facility Master'!K29,0) -> 26.08 | H10: =IFERROR('Facility Master'!M29,0) -> 26.08 | I10: =IFERROR('Facility Master'!N29,0) -> 1 | J10: =IFERROR('Facility Master'!O29,0) -> 0 | K10: =IFERROR('Facility Master'!P29,"") -> Mutually agreed | L10: =IFERROR('Facility Master'!Q29,0) -> 0 | M10: =IFERROR('Facility Master'!R29,0) -> 0.09 | N10: =IFERROR('Facility Master'!AB29,"") -> 46265
A11: =IFERROR('Facility Master'!A31,"") -> 27 | B11: =IFERROR('Facility Master'!B31,"") -> HSBC | C11: =IFERROR('Facility Master'!C31,"") -> Pre-shipment Seller Loan (Uncommitted) | D11: =IFERROR('Facility Master'!D31,"") -> FB | E11: =IFERROR(IF('Facility Master'!F31,"Sub-limit","Standalone"),"") -> Sub-limit | F11: =IFERROR('Facility Master'!I31,"") -> INR | G11: =IFERROR('Facility Master'!K31,0) -> 26.08 | H11: =IFERROR('Facility Master'!M31,0) -> 26.08 | I11: =IFERROR('Facility Master'!N31,0) -> 1 | J11: =IFERROR('Facility Master'!O31,0) -> 0 | K11: =IFERROR('Facility Master'!P31,"") -> Mutually agreed | L11: =IFERROR('Facility Master'!Q31,0) -> 0 | M11: =IFERROR('Facility Master'!R31,0) -> 0.09 | N11: =IFERROR('Facility Master'!AB31,"") -> 46265
A12: =IFERROR('Facility Master'!A32,"") -> 28 | B12: =IFERROR('Facility Master'!B32,"") -> HSBC | C12: =IFERROR('Facility Master'!C32,"") -> Post-Shipment Seller Loan, Open Account (Uncommitted) | D12: =IFERROR('Facility Master'!D32,"") -> FB | E12: =IFERROR(IF('Facility Master'!F32,"Sub-limit","Standalone"),"") -> Sub-limit | F12: =IFERROR('Facility Master'!I32,"") -> INR | G12: =IFERROR('Facility Master'!K32,0) -> 26.08 | H12: =IFERROR('Facility Master'!M32,0) -> 26.08 | I12: =IFERROR('Facility Master'!N32,0) -> 1 | J12: =IFERROR('Facility Master'!O32,0) -> 0 | K12: =IFERROR('Facility Master'!P32,"") -> Mutually agreed | L12: =IFERROR('Facility Master'!Q32,0) -> 0 | M12: =IFERROR('Facility Master'!R32,0) -> 0.09 | N12: =IFERROR('Facility Master'!AB32,"") -> 46265
A13: =IFERROR('Facility Master'!A39,"") -> 35 | B13: =IFERROR('Facility Master'!B39,"") -> HDFC Bank | C13: =IFERROR('Facility Master'!C39,"") -> Post Shipment Finance (sub of LC) | D13: =IFERROR('Facility Master'!D39,"") -> FB | E13: =IFERROR(IF('Facility Master'!F39,"Sub-limit","Standalone"),"") -> Sub-limit | F13: =IFERROR('Facility Master'!I39,"") -> INR | G13: =IFERROR('Facility Master'!K39,0) -> 100 | H13: =IFERROR('Facility Master'!M39,0) -> 100 | I13: =IFERROR('Facility Master'!N39,0) -> 1 | J13: =IFERROR('Facility Master'!O39,0) -> 0 | K13: =IFERROR('Facility Master'!P39,"") -> To be decided | L13: =IFERROR('Facility Master'!Q39,0) -> 0 | M13: =IFERROR('Facility Master'!R39,0) -> 0.095 | N13: =IFERROR('Facility Master'!AB39,"") -> 46265
A14: =IFERROR('Facility Master'!A40,"") -> 36 | B14: =IFERROR('Facility Master'!B40,"") -> HDFC Bank | C14: =IFERROR('Facility Master'!C40,"") -> Pre-shipment Finance (sub of LC) | D14: =IFERROR('Facility Master'!D40,"") -> FB | E14: =IFERROR(IF('Facility Master'!F40,"Sub-limit","Standalone"),"") -> Sub-limit | F14: =IFERROR('Facility Master'!I40,"") -> INR | G14: =IFERROR('Facility Master'!K40,0) -> 200 | H14: =IFERROR('Facility Master'!M40,0) -> 200 | I14: =IFERROR('Facility Master'!N40,0) -> 1 | J14: =IFERROR('Facility Master'!O40,0) -> 0 | K14: =IFERROR('Facility Master'!P40,"") -> To be decided | L14: =IFERROR('Facility Master'!Q40,0) -> 0 | M14: =IFERROR('Facility Master'!R40,0) -> 0.095 | N14: =IFERROR('Facility Master'!AB40,"") -> 46265
A15: =IFERROR('Facility Master'!A42,"") -> 38 | B15: =IFERROR('Facility Master'!B42,"") -> HDFC Bank | C15: =IFERROR('Facility Master'!C42,"") -> Cash Credit (sub of LC) | D15: =IFERROR('Facility Master'!D42,"") -> FB | E15: =IFERROR(IF('Facility Master'!F42,"Sub-limit","Standalone"),"") -> Sub-limit | F15: =IFERROR('Facility Master'!I42,"") -> INR | G15: =IFERROR('Facility Master'!K42,0) -> 50 | H15: =IFERROR('Facility Master'!M42,0) -> 50 | I15: =IFERROR('Facility Master'!N42,0) -> 1 | J15: =IFERROR('Facility Master'!O42,0) -> 0 | K15: =IFERROR('Facility Master'!P42,"") -> 14-day Repo (HDFC) | L15: =IFERROR('Facility Master'!Q42,0) -> 0 | M15: =IFERROR('Facility Master'!R42,0) -> 0.0815 | N15: =IFERROR('Facility Master'!AB42,"") -> 46265
A16: =IFERROR('Facility Master'!A43,"") -> 39 | B16: =IFERROR('Facility Master'!B43,"") -> HDFC Bank | C16: =IFERROR('Facility Master'!C43,"") -> WCDL (sub of LC) | D16: =IFERROR('Facility Master'!D43,"") -> FB | E16: =IFERROR(IF('Facility Master'!F43,"Sub-limit","Standalone"),"") -> Sub-limit | F16: =IFERROR('Facility Master'!I43,"") -> INR | G16: =IFERROR('Facility Master'!K43,0) -> 50 | H16: =IFERROR('Facility Master'!M43,0) -> 50 | I16: =IFERROR('Facility Master'!N43,0) -> 1 | J16: =IFERROR('Facility Master'!O43,0) -> 0 | K16: =IFERROR('Facility Master'!P43,"") -> To be decided | L16: =IFERROR('Facility Master'!Q43,0) -> 0 | M16: =IFERROR('Facility Master'!R43,0) -> 0.095 | N16: =IFERROR('Facility Master'!AB43,"") -> 46265
A17: =IFERROR('Facility Master'!A44,"") -> 40 | B17: =IFERROR('Facility Master'!B44,"") -> HDFC Bank | C17: =IFERROR('Facility Master'!C44,"") -> FD-OD (FD-Backed) | D17: =IFERROR('Facility Master'!D44,"") -> FB-FDbacked | E17: =IFERROR(IF('Facility Master'!F44,"Sub-limit","Standalone"),"") -> Standalone | F17: =IFERROR('Facility Master'!I44,"") -> INR | G17: =IFERROR('Facility Master'!K44,0) -> 50 | H17: =IFERROR('Facility Master'!M44,0) -> 50 | I17: =IFERROR('Facility Master'!N44,0) -> 1 | J17: =IFERROR('Facility Master'!O44,0) -> 0 | K17: =IFERROR('Facility Master'!P44,"") -> FD Rate (HDFC) | L17: =IFERROR('Facility Master'!Q44,0) -> 0.01 | M17: =IFERROR('Facility Master'!R44,0) -> 0.08 | N17: =IFERROR('Facility Master'!AB44,"") -> 46265
A18: TOTALS | G18: =SUM(G4:G17) -> 890.832 | H18: =SUM(H4:H17) -> 890.832
A19: ⚠ HSBC ₹200 Cr (post 20% haircut on ₹1,000 Cr face — see MP-13) is classified in Bucket 1 (Sanctioned / FB Mains). Sub-facilities remain Bucket 0 (sub-limits, not additive). Bank retains unrestricted discretion to cancel — see F-07.

Sheet Non-Fund Based Facilities
A1: NON-FUND BASED FACILITIES — LC / SBLC / BG
A2: Filtered view of NFB lines (LC / SBLC / BG) — all values linked from Facility Master. Commission run-rate = Sanc × Commission %. HSBC lines are UNCOMMITTED (Bucket 4).
A3: S.No | B3: Lender | C3: Facility | D3: Category | E3: Sub-Limit? | F3: Sanc (₹ Cr) | G3: Eff O/S | H3: Util % | I3: Commission % | J3: Annual Comm (₹ Cr) | K3: Validity | L3: Bucket
A4: =IFERROR('Facility Master'!A7,"") -> 3 | B4: =IFERROR('Facility Master'!B7,"") -> UBI | C4: =IFERROR('Facility Master'!C7,"") -> Letter of Credit (Capex LC/UPAS/SBLC) | D4: =IFERROR('Facility Master'!D7,"") -> NFB | E4: =IFERROR(IF('Facility Master'!F7,"Sub-limit","Standalone"),"") -> Sub-limit | F4: =IFERROR('Facility Master'!K7,0) -> 750 | G4: =IFERROR('Facility Master'!M7,0) -> 750 | H4: =IFERROR('Facility Master'!N7,0) -> 1 | I4: =IFERROR('Facility Master'!Q7,0) -> 0.006 | J4: =IFERROR(F4*I4,0) -> 4.5 | K4: =IFERROR('Facility Master'!AB7,"") -> 46284 | L4: =IFERROR('Facility Master'!H7,0) -> 0
A5: =IFERROR('Facility Master'!A8,"") -> 4 | B5: =IFERROR('Facility Master'!B8,"") -> UBI | C5: =IFERROR('Facility Master'!C8,"") -> Bank Guarantee | D5: =IFERROR('Facility Master'!D8,"") -> NFB | E5: =IFERROR(IF('Facility Master'!F8,"Sub-limit","Standalone"),"") -> Sub-limit | F5: =IFERROR('Facility Master'!K8,0) -> 12.5 | G5: =IFERROR('Facility Master'!M8,0) -> 12.5 | H5: =IFERROR('Facility Master'!N8,0) -> 1 | I5: =IFERROR('Facility Master'!Q8,0) -> 0.006 | J5: =IFERROR(F5*I5,0) -> 0.075 | K5: =IFERROR('Facility Master'!AB8,"") -> 46284 | L5: =IFERROR('Facility Master'!H8,0) -> 0
A6: =IFERROR('Facility Master'!A12,"") -> 8 | B6: =IFERROR('Facility Master'!B12,"") -> RBL Bank | C6: =IFERROR('Facility Master'!C12,"") -> Letter of Credit (sub-limit of TL) | D6: =IFERROR('Facility Master'!D12,"") -> NFB | E6: =IFERROR(IF('Facility Master'!F12,"Sub-limit","Standalone"),"") -> Sub-limit | F6: =IFERROR('Facility Master'!K12,0) -> 200 | G6: =IFERROR('Facility Master'!M12,0) -> 200 | H6: =IFERROR('Facility Master'!N12,0) -> 1 | I6: =IFERROR('Facility Master'!Q12,0) -> 0.005 | J6: =IFERROR(F6*I6,0) -> 1 | K6: =IFERROR('Facility Master'!AB12,"") -> 46265 | L6: =IFERROR('Facility Master'!H12,0) -> 0
A7: =IFERROR('Facility Master'!A15,"") -> 11 | B7: =IFERROR('Facility Master'!B15,"") -> YES Bank | C7: =IFERROR('Facility Master'!C15,"") -> Capex LC (sub-limit of TL) | D7: =IFERROR('Facility Master'!D15,"") -> NFB | E7: =IFERROR(IF('Facility Master'!F15,"Sub-limit","Standalone"),"") -> Sub-limit | F7: =IFERROR('Facility Master'!K15,0) -> 100 | G7: =IFERROR('Facility Master'!M15,0) -> 100 | H7: =IFERROR('Facility Master'!N15,0) -> 1 | I7: =IFERROR('Facility Master'!Q15,0) -> 0.005 | J7: =IFERROR(F7*I7,0) -> 0.5 | K7: =IFERROR('Facility Master'!AB15,"") -> 47116 | L7: =IFERROR('Facility Master'!H15,0) -> 0
A8: =IFERROR('Facility Master'!A17,"") -> 13 | B8: =IFERROR('Facility Master'!B17,"") -> IDFC First Bank | C8: =IFERROR('Facility Master'!C17,"") -> NFB — Capex LC/SBLC (A) | D8: =IFERROR('Facility Master'!D17,"") -> NFB | E8: =IFERROR(IF('Facility Master'!F17,"Sub-limit","Standalone"),"") -> Sub-limit | F8: =IFERROR('Facility Master'!K17,0) -> 400 | G8: =IFERROR('Facility Master'!M17,0) -> 400 | H8: =IFERROR('Facility Master'!N17,0) -> 1 | I8: =IFERROR('Facility Master'!Q17,0) -> 0.0035 | J8: =IFERROR(F8*I8,0) -> 1.4 | K8: =IFERROR('Facility Master'!AB17,"") -> 46295 | L8: =IFERROR('Facility Master'!H17,0) -> 0
A9: =IFERROR('Facility Master'!A18,"") -> 14 | B9: =IFERROR('Facility Master'!B18,"") -> IDFC First Bank | C9: =IFERROR('Facility Master'!C18,"") -> NFB — BG / SBLC (B, sub-limit within ₹400 cap) | D9: =IFERROR('Facility Master'!D18,"") -> NFB | E9: =IFERROR(IF('Facility Master'!F18,"Sub-limit","Standalone"),"") -> Sub-limit | F9: =IFERROR('Facility Master'!K18,0) -> 200 | G9: =IFERROR('Facility Master'!M18,0) -> 200 | H9: =IFERROR('Facility Master'!N18,0) -> 1 | I9: =IFERROR('Facility Master'!Q18,0) -> 0.0035 | J9: =IFERROR(F9*I9,0) -> 0.7 | K9: =IFERROR('Facility Master'!AB18,"") -> 46295 | L9: =IFERROR('Facility Master'!H18,0) -> 0
A10: =IFERROR('Facility Master'!A21,"") -> 17 | B10: =IFERROR('Facility Master'!B21,"") -> ICICI Bank | C10: =IFERROR('Facility Master'!C21,"") -> Letter of Credit (WC) | D10: =IFERROR('Facility Master'!D21,"") -> NFB | E10: =IFERROR(IF('Facility Master'!F21,"Sub-limit","Standalone"),"") -> Standalone | F10: =IFERROR('Facility Master'!K21,0) -> 300 | G10: =IFERROR('Facility Master'!M21,0) -> 300 | H10: =IFERROR('Facility Master'!N21,0) -> 1 | I10: =IFERROR('Facility Master'!Q21,0) -> 0.006 | J10: =IFERROR(F10*I10,0) -> 1.8 | K10: =IFERROR('Facility Master'!AB21,"") -> 46421 | L10: =IFERROR('Facility Master'!H21,0) -> 2
A11: =IFERROR('Facility Master'!A22,"") -> 18 | B11: =IFERROR('Facility Master'!B22,"") -> ICICI Bank | C11: =IFERROR('Facility Master'!C22,"") -> BG (F+P, sub-limit of LC) | D11: =IFERROR('Facility Master'!D22,"") -> NFB | E11: =IFERROR(IF('Facility Master'!F22,"Sub-limit","Standalone"),"") -> Sub-limit | F11: =IFERROR('Facility Master'!K22,0) -> 300 | G11: =IFERROR('Facility Master'!M22,0) -> 300 | H11: =IFERROR('Facility Master'!N22,0) -> 1 | I11: =IFERROR('Facility Master'!Q22,0) -> 0.006 | J11: =IFERROR(F11*I11,0) -> 1.8 | K11: =IFERROR('Facility Master'!AB22,"") -> 46421 | L11: =IFERROR('Facility Master'!H22,0) -> 0
A12: =IFERROR('Facility Master'!A23,"") -> 19 | B12: =IFERROR('Facility Master'!B23,"") -> HSBC | C12: =IFERROR('Facility Master'!C23,"") -> Combined Limit (Uncommitted) | D12: =IFERROR('Facility Master'!D23,"") -> NFB | E12: =IFERROR(IF('Facility Master'!F23,"Sub-limit","Standalone"),"") -> Standalone | F12: =IFERROR('Facility Master'!K23,0) -> 200 | G12: =IFERROR('Facility Master'!M23,0) -> 200 | H12: =IFERROR('Facility Master'!N23,0) -> 1 | I12: =IFERROR('Facility Master'!Q23,0) -> 0 | J12: =IFERROR(F12*I12,0) -> 0 | K12: =IFERROR('Facility Master'!AB23,"") -> 46265 | L12: =IFERROR('Facility Master'!H23,0) -> 1
A13: =IFERROR('Facility Master'!A26,"") -> 22 | B13: =IFERROR('Facility Master'!B26,"") -> HSBC | C13: =IFERROR('Facility Master'!C26,"") -> Import Controlling line - 1 (Uncommitted) | D13: =IFERROR('Facility Master'!D26,"") -> NFB | E13: =IFERROR(IF('Facility Master'!F26,"Sub-limit","Standalone"),"") -> Sub-limit | F13: =IFERROR('Facility Master'!K26,0) -> 26.08 | G13: =IFERROR('Facility Master'!M26,0) -> 26.08 | H13: =IFERROR('Facility Master'!N26,0) -> 1 | I13: =IFERROR('Facility Master'!Q26,0) -> 0 | J13: =IFERROR(F13*I13,0) -> 0 | K13: =IFERROR('Facility Master'!AB26,"") -> 46265 | L13: =IFERROR('Facility Master'!H26,0) -> 0
A14: =IFERROR('Facility Master'!A27,"") -> 23 | B14: =IFERROR('Facility Master'!B27,"") -> HSBC | C14: =IFERROR('Facility Master'!C27,"") -> TradePay Domestic/Import (Uncommitted) | D14: =IFERROR('Facility Master'!D27,"") -> NFB | E14: =IFERROR(IF('Facility Master'!F27,"Sub-limit","Standalone"),"") -> Sub-limit | F14: =IFERROR('Facility Master'!K27,0) -> 26.08 | G14: =IFERROR('Facility Master'!M27,0) -> 26.08 | H14: =IFERROR('Facility Master'!N27,0) -> 1 | I14: =IFERROR('Facility Master'!Q27,0) -> 0 | J14: =IFERROR(F14*I14,0) -> 0 | K14: =IFERROR('Facility Master'!AB27,"") -> 46265 | L14: =IFERROR('Facility Master'!H27,0) -> 0
A15: =IFERROR('Facility Master'!A30,"") -> 26 | B15: =IFERROR('Facility Master'!B30,"") -> HSBC | C15: =IFERROR('Facility Master'!C30,"") -> Export Controlling line (Uncommitted) | D15: =IFERROR('Facility Master'!D30,"") -> NFB | E15: =IFERROR(IF('Facility Master'!F30,"Sub-limit","Standalone"),"") -> Sub-limit | F15: =IFERROR('Facility Master'!K30,0) -> 26.08 | G15: =IFERROR('Facility Master'!M30,0) -> 26.08 | H15: =IFERROR('Facility Master'!N30,0) -> 1 | I15: =IFERROR('Facility Master'!Q30,0) -> 0 | J15: =IFERROR(F15*I15,0) -> 0 | K15: =IFERROR('Facility Master'!AB30,"") -> 46265 | L15: =IFERROR('Facility Master'!H30,0) -> 0
A16: =IFERROR('Facility Master'!A33,"") -> 29 | B16: =IFERROR('Facility Master'!B33,"") -> HSBC | C16: =IFERROR('Facility Master'!C33,"") -> Import Controlling line - 2 (Uncommitted) | D16: =IFERROR('Facility Master'!D33,"") -> NFB | E16: =IFERROR(IF('Facility Master'!F33,"Sub-limit","Standalone"),"") -> Sub-limit | F16: =IFERROR('Facility Master'!K33,0) -> 154.58 | G16: =IFERROR('Facility Master'!M33,0) -> 154.58 | H16: =IFERROR('Facility Master'!N33,0) -> 1 | I16: =IFERROR('Facility Master'!Q33,0) -> 0 | J16: =IFERROR(F16*I16,0) -> 0 | K16: =IFERROR('Facility Master'!AB33,"") -> 46265 | L16: =IFERROR('Facility Master'!H33,0) -> 0
A17: =IFERROR('Facility Master'!A34,"") -> 30 | B17: =IFERROR('Facility Master'!B34,"") -> HSBC | C17: =IFERROR('Facility Master'!C34,"") -> Import Documentary Credit - 12 (Uncommitted) | D17: =IFERROR('Facility Master'!D34,"") -> NFB | E17: =IFERROR(IF('Facility Master'!F34,"Sub-limit","Standalone"),"") -> Sub-limit | F17: =IFERROR('Facility Master'!K34,0) -> 154.58 | G17: =IFERROR('Facility Master'!M34,0) -> 154.58 | H17: =IFERROR('Facility Master'!N34,0) -> 1 | I17: =IFERROR('Facility Master'!Q34,0) -> 0 | J17: =IFERROR(F17*I17,0) -> 0 | K17: =IFERROR('Facility Master'!AB34,"") -> 46265 | L17: =IFERROR('Facility Master'!H34,0) -> 0
A18: =IFERROR('Facility Master'!A35,"") -> 31 | B18: =IFERROR('Facility Master'!B35,"") -> HSBC | C18: =IFERROR('Facility Master'!C35,"") -> Import Documentary Credit - 13 (Uncommitted) | D18: =IFERROR('Facility Master'!D35,"") -> NFB | E18: =IFERROR(IF('Facility Master'!F35,"Sub-limit","Standalone"),"") -> Sub-limit | F18: =IFERROR('Facility Master'!K35,0) -> 10 | G18: =IFERROR('Facility Master'!M35,0) -> 10 | H18: =IFERROR('Facility Master'!N35,0) -> 1 | I18: =IFERROR('Facility Master'!Q35,0) -> 0 | J18: =IFERROR(F18*I18,0) -> 0 | K18: =IFERROR('Facility Master'!AB35,"") -> 46265 | L18: =IFERROR('Facility Master'!H35,0) -> 0
A19: =IFERROR('Facility Master'!A36,"") -> 32 | B19: =IFERROR('Facility Master'!B36,"") -> HSBC | C19: =IFERROR('Facility Master'!C36,"") -> Guarantees/Bonds Non-Financial (Uncommitted) | D19: =IFERROR('Facility Master'!D36,"") -> NFB | E19: =IFERROR(IF('Facility Master'!F36,"Sub-limit","Standalone"),"") -> Sub-limit | F19: =IFERROR('Facility Master'!K36,0) -> 17.4 | G19: =IFERROR('Facility Master'!M36,0) -> 17.4 | H19: =IFERROR('Facility Master'!N36,0) -> 1 | I19: =IFERROR('Facility Master'!Q36,0) -> 0 | J19: =IFERROR(F19*I19,0) -> 0 | K19: =IFERROR('Facility Master'!AB36,"") -> 46265 | L19: =IFERROR('Facility Master'!H36,0) -> 0
A20: =IFERROR('Facility Master'!A37,"") -> 33 | B20: =IFERROR('Facility Master'!B37,"") -> HSBC | C20: =IFERROR('Facility Master'!C37,"") -> Guarantees/Bonds Financial (Uncommitted) | D20: =IFERROR('Facility Master'!D37,"") -> NFB | E20: =IFERROR(IF('Facility Master'!F37,"Sub-limit","Standalone"),"") -> Sub-limit | F20: =IFERROR('Facility Master'!K37,0) -> 1.94 | G20: =IFERROR('Facility Master'!M37,0) -> 1.94 | H20: =IFERROR('Facility Master'!N37,0) -> 1 | I20: =IFERROR('Facility Master'!Q37,0) -> 0 | J20: =IFERROR(F20*I20,0) -> 0 | K20: =IFERROR('Facility Master'!AB37,"") -> 46265 | L20: =IFERROR('Facility Master'!H37,0) -> 0
A21: =IFERROR('Facility Master'!A38,"") -> 34 | B21: =IFERROR('Facility Master'!B38,"") -> HDFC Bank | C21: =IFERROR('Facility Master'!C38,"") -> Letter of Credit (WC parent) | D21: =IFERROR('Facility Master'!D38,"") -> NFB | E21: =IFERROR(IF('Facility Master'!F38,"Sub-limit","Standalone"),"") -> Standalone | F21: =IFERROR('Facility Master'!K38,0) -> 250 | G21: =IFERROR('Facility Master'!M38,0) -> 250 | H21: =IFERROR('Facility Master'!N38,0) -> 1 | I21: =IFERROR('Facility Master'!Q38,0) -> 0.005 | J21: =IFERROR(F21*I21,0) -> 1.25 | K21: =IFERROR('Facility Master'!AB38,"") -> 46265 | L21: =IFERROR('Facility Master'!H38,0) -> 2
A22: =IFERROR('Facility Master'!A41,"") -> 37 | C22: =IFERROR('Facility Master'!C41,"") -> SBLC (sub of LC) | D22: =IFERROR('Facility Master'!D41,"") -> NFB | E22: =IFERROR(IF('Facility Master'!F41,"Sub-limit","Standalone"),"") -> Sub-limit | F22: =IFERROR('Facility Master'!K41,0) -> 250 | G22: =IFERROR('Facility Master'!M41,0) -> 250 | H22: =IFERROR('Facility Master'!N41,0) -> 1 | I22: =IFERROR('Facility Master'!Q41,0) -> 0 | J22: =IFERROR(F22*I22,0) -> 0 | K22: =IFERROR('Facility Master'!AB41,"") -> 46265 | L22: =IFERROR('Facility Master'!H41,0) -> 0
A23: =IFERROR('Facility Master'!A45,"") -> 41 | C23: =IFERROR('Facility Master'!C45,"") -> BG (sub of FD-OD) | D23: =IFERROR('Facility Master'!D45,"") -> NFB | E23: =IFERROR(IF('Facility Master'!F45,"Sub-limit","Standalone"),"") -> Sub-limit | F23: =IFERROR('Facility Master'!K45,0) -> 50 | G23: =IFERROR('Facility Master'!M45,0) -> 50 | H23: =IFERROR('Facility Master'!N45,0) -> 1 | I23: =IFERROR('Facility Master'!Q45,0) -> 0 | J23: =IFERROR(F23*I23,0) -> 0 | K23: =IFERROR('Facility Master'!AB45,"") -> 46265 | L23: =IFERROR('Facility Master'!H45,0) -> 0
A24: =IFERROR('Facility Master'!A47,"") -> 43 | B24: =IFERROR('Facility Master'!B47,"") -> ICICI Bank (TL) | C24: =IFERROR('Facility Master'!C47,"") -> BG Financial (sub of RTL) | D24: =IFERROR('Facility Master'!D47,"") -> NFB | E24: =IFERROR(IF('Facility Master'!F47,"Sub-limit","Standalone"),"") -> Sub-limit | F24: =IFERROR('Facility Master'!K47,0) -> 20 | G24: =IFERROR('Facility Master'!M47,0) -> 20 | H24: =IFERROR('Facility Master'!N47,0) -> 1 | I24: =IFERROR('Facility Master'!Q47,0) -> 0.0075 | J24: =IFERROR(F24*I24,0) -> 0.15 | K24: =IFERROR('Facility Master'!AB47,"") -> 47204 | L24: =IFERROR('Facility Master'!H47,0) -> 0
A25: =IFERROR('Facility Master'!A48,"") -> 44 | B25: =IFERROR('Facility Master'!B48,"") -> ICICI Bank (TL) | C25: =IFERROR('Facility Master'!C48,"") -> SBLC Buyers Credit (sub of RTL) | D25: =IFERROR('Facility Master'!D48,"") -> NFB | E25: =IFERROR(IF('Facility Master'!F48,"Sub-limit","Standalone"),"") -> Sub-limit | F25: =IFERROR('Facility Master'!K48,0) -> 20 | G25: =IFERROR('Facility Master'!M48,0) -> 20 | H25: =IFERROR('Facility Master'!N48,0) -> 1 | I25: =IFERROR('Facility Master'!Q48,0) -> 0.0075 | J25: =IFERROR(F25*I25,0) -> 0.15 | K25: =IFERROR('Facility Master'!AB48,"") -> 47204 | L25: =IFERROR('Facility Master'!H48,0) -> 0
A26: TOTALS | F26: =SUM(F4:F25) -> 3469.24 | G26: =SUM(G4:G25) -> 3469.24 | J26: =SUM(J4:J25) -> 13.325
A27: ⚠ Bucket 2 NFB Mains = ₹550 Cr (ICICI LC ₹300 Cr + HDFC LC ₹250 Cr). All other NFB lines are contingent sub-limits (Bucket 0) or UNCOMMITTED (Bucket 4, HSBC). Annual commission is indicative run-rate at full utilisation.
A28: * Sanc/O/S totals above include sub-limits (not additive with parent). Bucket 2 Mains = ₹550 Cr. NFB Contingent (Bucket 0 sub-limits) = ₹2,040 Cr. HSBC ₹200 Cr (post 20% haircut) is classified Bucket 1 (see MP-13 / F-18). Sub-limits remain Bucket 0.

Sheet Repayment Schedule
A1: REPAYMENT SCHEDULE — Quarterly (Q1 FY24 to Q4 FY39)
A2: All 7 TLs modelled. Note: Repayment Schedule shows CONTRACTUAL amortization assuming full sanctioned drawdown. Aggregate FY29 OS (excl. RBL) = ~₹3,249 Cr vs TEV's planned LT debt of ₹2,388 Cr (TEV assumes partial drawdown / earlier prepayment). Covenants in FY29 Compliance use TEV figures; the schedule above is a contractual max-utilization view. RBL bullet (₹200 Cr) repays Q3 FY27 (13-Nov-2026 maturity); post-COD refinance assumed.
A3: PERIOD | D3: UBI RTL-I | ₹1,125 Cr | 9.40% | I3: UBI RTL-II | ₹236 Cr | 9.10% | N3: INDIAN BANK | ₹235 Cr | 9.40% | S3: RBL BRIDGE | ₹200 Cr | BULLET ⚠ | X3: YES BANK | ₹650 Cr | EBLR+3.45% | AC3: IDFC FIRST | ₹530 Cr | EBLR+1.05% | AH3: ICICI TL | ₹840 Cr | TAKEOVER ↺ | AM3: CONSOLIDATED (excl. RBL)
A4: # | B4: Period End | C4: Label | D4: Opening | E4: Drawdown | F4: Prin Rep | G4: Interest | H4: Closing | I4: Opening | J4: Drawdown | K4: Prin Rep | L4: Interest | M4: Closing | N4: Opening | O4: Drawdown | P4: Prin Rep | Q4: Interest | R4: Closing | S4: Opening | T4: Drawdown | U4: Prin Rep | V4: Interest | W4: Closing | X4: Opening | Y4: Drawdown | Z4: Prin Rep | AA4: Interest | AB4: Closing | AC4: Opening | AD4: Drawdown | AE4: Prin Rep | AF4: Interest | AG4: Closing | AH4: Opening | AI4: Drawdown | AJ4: Prin Rep | AK4: Interest | AL4: Closing | AM4: Total Prin | AN4: Total Int | AO4: Total DS | AP4: Combined O/S
A5: 1 | B5: 45107 | C5: Q1 FY24 | D5: =0 -> 0 | E5: =IFERROR(IF(INDEX('Facility Master'!X:X,MATCH(UBI_RTL1_SNo,'Facility Master'!A:A,0))<=B5,INDEX('Facility Master'!K:K,MATCH(UBI_RTL1_SNo,'Facility Master'!A:A,0)),0),0) -> 1125 | F5: =IFERROR(IF(B5<UBI_RTL1_RepStart,0,IF(B5>UBI_RTL1_Maturity,0,IF(COUNTIFS($B$5:$B5,">="&UBI_RTL1_RepStart,$B$5:$B5,"<="&UBI_RTL1_Maturity)<=8,INDEX('Facility Master'!K:K,MATCH(UBI_RTL1_SNo,'Facility Master'!A:A,0))*0.0125,IF(COUNTIFS($B$5:$B5,">="&UBI_RTL1_RepStart,$B$5:$B5,"<="&UBI_RTL1_Maturity)<=48,INDEX('Facility Master'!K:K,MATCH(UBI_RTL1_SNo,'Facility Master'!A:A,0))*0.0225,0)))),0) -> 0 | G5: =IFERROR((D5+(E5-F5)/2)*INDEX('Facility Master'!R:R,MATCH(UBI_RTL1_SNo,'Facility Master'!A:A,0))*91/DaysInYear,0) -> 13.182534 | H5: =IFERROR(ROUND(MAX(D5+E5-F5,0),6),0) -> 1125 | I5: =0 -> 0 | J5: =IFERROR(IF(INDEX('Facility Master'!X:X,MATCH(UBI_RTL2_SNo,'Facility Master'!A:A,0))<=B5,INDEX('Facility Master'!K:K,MATCH(UBI_RTL2_SNo,'Facility Master'!A:A,0)),0),0) -> 0 | K5: =IFERROR(IF(B5<UBI_RTL2_RepStart,0,IF(B5>UBI_RTL2_Maturity,0,IF(COUNTIFS($B$5:$B5,">="&UBI_RTL2_RepStart,$B$5:$B5,"<="&UBI_RTL2_Maturity)<=8,INDEX('Facility Master'!K:K,MATCH(UBI_RTL2_SNo,'Facility Master'!A:A,0))*0.0125,IF(COUNTIFS($B$5:$B5,">="&UBI_RTL2_RepStart,$B$5:$B5,"<="&UBI_RTL2_Maturity)<=48,INDEX('Facility Master'!K:K,MATCH(UBI_RTL2_SNo,'Facility Master'!A:A,0))*0.0225,0)))),0) -> 0 | L5: =IFERROR((I5+(J5-K5)/2)*INDEX('Facility Master'!R:R,MATCH(UBI_RTL2_SNo,'Facility Master'!A:A,0))*91/DaysInYear,0) -> 0 | M5: =IFERROR(ROUND(MAX(I5+J5-K5,0),6),0) -> 0 | N5: =0 -> 0 | O5: =IFERROR(IF(INDEX('Facility Master'!X:X,MATCH(IB_TL_SNo,'Facility Master'!A:A,0))<=B5,INDEX('Facility Master'!K:K,MATCH(IB_TL_SNo,'Facility Master'!A:A,0)),0),0) -> 235 | P5: =IFERROR(IF(B5<IB_TL_RepStart,0,IF(B5>IB_TL_Maturity,0,IF(COUNTIFS($B$5:$B5,">="&IB_TL_RepStart,$B$5:$B5,"<="&IB_TL_Maturity)<=8,INDEX('Facility Master'!K:K,MATCH(IB_TL_SNo,'Facility Master'!A:A,0))*0.0125,IF(COUNTIFS($B$5:$B5,">="&IB_TL_RepStart,$B$5:$B5,"<="&IB_TL_Maturity)<=48,INDEX('Facility Master'!K:K,MATCH(IB_TL_SNo,'Facility Master'!A:A,0))*0.0225,0)))),0) -> 0 | Q5: =IFERROR((N5+(O5-P5)/2)*INDEX('Facility Master'!R:R,MATCH(IB_TL_SNo,'Facility Master'!A:A,0))*91/DaysInYear,0) -> 2.7536849 | R5: =IFERROR(ROUND(MAX(N5+O5-P5,0),6),0) -> 235 | S5: =0 -> 0 | T5: =IFERROR(IF(INDEX('Facility Master'!X:X,MATCH(RBL_TL_SNo,'Facility Master'!A:A,0))<=B5,INDEX('Facility Master'!K:K,MATCH(RBL_TL_SNo,'Facility Master'!A:A,0)),0),0) -> 0 | U5: =IFERROR(IF(AND(RBL_TL_Maturity<=B5,RBL_TL_Maturity>B4),INDEX('Facility Master'!K:K,MATCH(RBL_TL_SNo,'Facility Master'!A:A,0)),0),0) -> 0 | V5: =IFERROR((S5+(T5-U5)/2)*INDEX('Facility Master'!R:R,MATCH(RBL_TL_SNo,'Facility Master'!A:A,0))*91/DaysInYear,0) -> 0 | W5: =IFERROR(ROUND(MAX(S5+T5-U5,0),6),0) -> 0 | X5: =0 -> 0 | Y5: =IFERROR(IF(INDEX('Facility Master'!X:X,MATCH(YBL_TL_SNo,'Facility Master'!A:A,0))<=B5,INDEX('Facility Master'!K:K,MATCH(YBL_TL_SNo,'Facility Master'!A:A,0)),0),0) -> 0 | Z5: =IFERROR(IF(B5<YBL_TL_RepStart,0,IF(B5>YBL_TL_Maturity,0,IF(COUNTIFS($B$5:$B5,">="&YBL_TL_RepStart,$B$5:$B5,"<="&YBL_TL_Maturity)<=8,INDEX('Facility Master'!K:K,MATCH(YBL_TL_SNo,'Facility Master'!A:A,0))*0.0125,IF(COUNTIFS($B$5:$B5,">="&YBL_TL_RepStart,$B$5:$B5,"<="&YBL_TL_Maturity)<=48,INDEX('Facility Master'!K:K,MATCH(YBL_TL_SNo,'Facility Master'!A:A,0))*0.0225,0)))),0) -> 0 | AA5: =IFERROR((X5+(Y5-Z5)/2)*INDEX('Facility Master'!R:R,MATCH(YBL_TL_SNo,'Facility Master'!A:A,0))*91/DaysInYear,0) -> 0 | AB5: =IFERROR(ROUND(MAX(X5+Y5-Z5,0),6),0) -> 0 | AC5: =0 -> 0 | AD5: =IFERROR(IF(INDEX('Facility Master'!X:X,MATCH(IDFC_TL_SNo,'Facility Master'!A:A,0))<=B5,INDEX('Facility Master'!K:K,MATCH(IDFC_TL_SNo,'Facility Master'!A:A,0)),0),0) -> 0 | AE5: =IFERROR(IF(B5<IDFC_TL_RepStart,0,IF(B5>IDFC_TL_Maturity,0,IF(COUNTIFS($B$5:$B5,">="&IDFC_TL_RepStart,$B$5:$B5,"<="&IDFC_TL_Maturity)<=8,INDEX('Facility Master'!K:K,MATCH(IDFC_TL_SNo,'Facility Master'!A:A,0))*0.0125,IF(COUNTIFS($B$5:$B5,">="&IDFC_TL_RepStart,$B$5:$B5,"<="&IDFC_TL_Maturity)<=48,INDEX('Facility Master'!K:K,MATCH(IDFC_TL_SNo,'Facility Master'!A:A,0))*0.0225,0)))),0) -> 0 | AF5: =IFERROR((AC5+(AD5-AE5)/2)*INDEX('Facility Master'!R:R,MATCH(IDFC_TL_SNo,'Facility Master'!A:A,0))*91/DaysInYear,0) -> 0 | AG5: =IFERROR(ROUND(MAX(AC5+AD5-AE5,0),6),0) -> 0 | AH5: =0 -> 0 | AI5: =IFERROR(IF(INDEX('Facility Master'!X:X,MATCH(ICICI_TL_SNo,'Facility Master'!A:A,0))<=B5,INDEX('Facility Master'!K:K,MATCH(ICICI_TL_SNo,'Facility Master'!A:A,0)),0),0) -> 0 | AJ5: =IFERROR(IF(B5<ICICI_TL_RepStart,0,IF(B5>ICICI_TL_Maturity,0,IF(COUNTIFS($B$5:$B5,">="&ICICI_TL_RepStart,$B$5:$B5,"<="&ICICI_TL_Maturity)<=8,INDEX('Facility Master'!K:K,MATCH(ICICI_TL_SNo,'Facility Master'!A:A,0))*0.0125,IF(COUNTIFS($B$5:$B5,">="&ICICI_TL_RepStart,$B$5:$B5,"<="&ICICI_TL_Maturity)<=48,INDEX('Facility Master'!K:K,MATCH(ICICI_TL_SNo,'Facility Master'!A:A,0))*0.0225,0)))),0) -> 0 | AK5: =IFERROR((AH5+(AI5-AJ5)/2)*INDEX('Facility Master'!R:R,MATCH(ICICI_TL_SNo,'Facility Master'!A:A,0))*91/DaysInYear,0) -> 0 | AL5: =IFERROR(ROUND(MAX(AH5+AI5-AJ5,0),6),0) -> 0 | AM5: =F5+K5+P5+Z5+AE5+AJ5 -> 0 | AN5: =G5+L5+Q5+AA5+AF5+AK5 -> 15.936219 | AO5: =AM5+AN5 -> 15.936219 | AP5: =H5+M5+R5+AB5+AG5+AL5 -> 1360
A6: 2 | B6: 45199 | C6: Q2 FY24 | D6: =IFERROR(MAX(H5,0),0) -> 1125 | E6: =IFERROR(IF(AND(INDEX('Facility Master'!X:X,MATCH(UBI_RTL1_SNo,'Facility Master'!A:A,0))<=B6,INDEX('Facility Master'!X:X,MATCH(UBI_RTL1_SNo,'Facility Master'!A:A,0))>B5),INDEX('Facility Master'!K:K,MATCH(UBI_RTL1_SNo,'Facility Master'!A:A,0)),0),0) -> 0 | F6: =IFERROR(IF(B6<UBI_RTL1_RepStart,0,IF(B6>UBI_RTL1_Maturity,0,IF(COUNTIFS($B$5:$B6,">="&UBI_RTL1_RepStart,$B$5:$B6,"<="&UBI_RTL1_Maturity)<=8,INDEX('Facility Master'!K:K,MATCH(UBI_RTL1_SNo,'Facility Master'!A:A,0))*0.0125,IF(COUNTIFS($B$5:$B6,">="&UBI_RTL1_RepStart,$B$5:$B6,"<="&UBI_RTL1_Maturity)<=48,INDEX('Facility Master'!K:K,MATCH(UBI_RTL1_SNo,'Facility Master'!A:A,0))*0.0225,0)))),0) -> 0 | G6: =IFERROR((D6+(E6-F6)/2)*INDEX('Facility Master'!R:R,MATCH(UBI_RTL1_SNo,'Facility Master'!A:A,0))*(B6-B5)/DaysInYear,0) -> 26.654795 | H6: =IFERROR(ROUND(MAX(D6+E6-F6,0),6),0) -> 1125 | I6: =IFERROR(MAX(M5,0),0) -> 0 | J6: =IFERROR(IF(AND(INDEX('Facility Master'!X:X,MATCH(UBI_RTL2_SNo,'Facility Master'!A:A,0))<=B6,INDEX('Facility Master'!X:X,MATCH(UBI_RTL2_SNo,'Facility Master'!A:A,0))>B5),INDEX('Facility Master'!K:K,MATCH(UBI_RTL2_SNo,'Facility Master'!A:A,0)),0),0) -> 0 | K6: =IFERROR(IF(B6<UBI_RTL2_RepStart,0,IF(B6>UBI_RTL2_Maturity,0,IF(COUNTIFS($B$5:$B6,">="&UBI_RTL2_RepStart,$B$5:$B6,"<="&UBI_RTL2_Maturity)<=8,INDEX('Facility Master'!K:K,MATCH(UBI_RTL2_SNo,'Facility Master'!A:A,0))*0.0125,IF(COUNTIFS($B$5:$B6,">="&UBI_RTL2_RepStart,$B$5:$B6,"<="&UBI_RTL2_Maturity)<=48,INDEX('Facility Master'!K:K,MATCH(UBI_RTL2_SNo,'Facility Master'!A:A,0))*0.0225,0)))),0) -> 0 | L6: =IFERROR((I6+(J6-K6)/2)*INDEX('Facility Master'!R:R,MATCH(UBI_RTL2_SNo,'Facility Master'!A:A,0))*(B6-B5)/DaysInYear,0) -> 0 | M6: =IFERROR(ROUND(MAX(I6+J6-K6,0),6),0) -> 0 | N6: =IFERROR(MAX(R5,0),0) -> 235 | O6: =IFERROR(IF(AND(INDEX('Facility Master'!X:X,MATCH(IB_TL_SNo,'Facility Master'!A:A,0))<=B6,INDEX('Facility Master'!X:X,MATCH(IB_TL_SNo,'Facility Master'!A:A,0))>B5),INDEX('Facility Master'!K:K,MATCH(IB_TL_SNo,'Facility Master'!A:A,0)),0),0) -> 0 | P6: =IFERROR(IF(B6<IB_TL_RepStart,0,IF(B6>IB_TL_Maturity,0,IF(COUNTIFS($B$5:$B6,">="&IB_TL_RepStart,$B$5:$B6,"<="&IB_TL_Maturity)<=8,INDEX('Facility Master'!K:K,MATCH(IB_TL_SNo,'Facility Master'!A:A,0))*0.0125,IF(COUNTIFS($B$5:$B6,">="&IB_TL_RepStart,$B$5:$B6,"<="&IB_TL_Maturity)<=48,INDEX('Facility Master'!K:K,MATCH(IB_TL_SNo,'Facility Master'!A:A,0))*0.0225,0)))),0) -> 0 | Q6: =IFERROR((N6+(O6-P6)/2)*INDEX('Facility Master'!R:R,MATCH(IB_TL_SNo,'Facility Master'!A:A,0))*(B6-B5)/DaysInYear,0) -> 5.5678904 | R6: =IFERROR(ROUND(MAX(N6+O6-P6,0),6),0) -> 235 | S6: =IFERROR(MAX(W5,0),0) -> 0 | T6: =IFERROR(IF(AND(INDEX('Facility Master'!X:X,MATCH(RBL_TL_SNo,'Facility Master'!A:A,0))<=B6,INDEX('Facility Master'!X:X,MATCH(RBL_TL_SNo,'Facility Master'!A:A,0))>B5),INDEX('Facility Master'!K:K,MATCH(RBL_TL_SNo,'Facility Master'!A:A,0)),0),0) -> 0 | U6: =IFERROR(IF(AND(RBL_TL_Maturity<=B6,RBL_TL_Maturity>B5),INDEX('Facility Master'!K:K,MATCH(RBL_TL_SNo,'Facility Master'!A:A,0)),0),0) -> 0 | V6: =IFERROR((S6+(T6-U6)/2)*INDEX('Facility Master'!R:R,MATCH(RBL_TL_SNo,'Facility Master'!A:A,0))*(B6-B5)/DaysInYear,0) -> 0 | W6: =IFERROR(ROUND(MAX(S6+T6-U6,0),6),0) -> 0 | X6: =IFERROR(MAX(AB5,0),0) -> 0 | Y6: =IFERROR(IF(AND(INDEX('Facility Master'!X:X,MATCH(YBL_TL_SNo,'Facility Master'!A:A,0))<=B6,INDEX('Facility Master'!X:X,MATCH(YBL_TL_SNo,'Facility Master'!A:A,0))>B5),INDEX('Facility Master'!K:K,MATCH(YBL_TL_SNo,'Facility Master'!A:A,0)),0),0) -> 0 | Z6: =IFERROR(IF(B6<YBL_TL_RepStart,0,IF(B6>YBL_TL_Maturity,0,IF(COUNTIFS($B$5:$B6,">="&YBL_TL_RepStart,$B$5:$B6,"<="&YBL_TL_Maturity)<=8,INDEX('Facility Master'!K:K,MATCH(YBL_TL_SNo,'Facility Master'!A:A,0))*0.0125,IF(COUNTIFS($B$5:$B6,">="&YBL_TL_RepStart,$B$5:$B6,"<="&YBL_TL_Maturity)<=48,INDEX('Facility Master'!K:K,MATCH(YBL_TL_SNo,'Facility Master'!A:A,0))*0.0225,0)))),0) -> 0 | AA6: =IFERROR((X6+(Y6-Z6)/2)*INDEX('Facility Master'!R:R,MATCH(YBL_TL_SNo,'Facility Master'!A:A,0))*(B6-B5)/DaysInYear,0) -> 0 | AB6: =IFERROR(ROUND(MAX(X6+Y6-Z6,0),6),0) -> 0 | AC6: =IFERROR(MAX(AG5,0),0) -> 0 | AD6: =IFERROR(IF(AND(INDEX('Facility Master'!X:X,MATCH(IDFC_TL_SNo,'Facility Master'!A:A,0))<=B6,INDEX('Facility Master'!X:X,MATCH(IDFC_TL_SNo,'Facility Master'!A:A,0))>B5),INDEX('Facility Master'!K:K,MATCH(IDFC_TL_SNo,'Facility Master'!A:A,0)),0),0) -> 0 | AE6: =IFERROR(IF(B6<IDFC_TL_RepStart,0,IF(B6>IDFC_TL_Maturity,0,IF(COUNTIFS($B$5:$B6,">="&IDFC_TL_RepStart,$B$5:$B6,"<="&IDFC_TL_Maturity)<=8,INDEX('Facility Master'!K:K,MATCH(IDFC_TL_SNo,'Facility Master'!A:A,0))*0.0125,IF(COUNTIFS($B$5:$B6,">="&IDFC_TL_RepStart,$B$5:$B6,"<="&IDFC_TL_Maturity)<=48,INDEX('Facility Master'!K:K,MATCH(IDFC_TL_SNo,'Facility Master'!A:A,0))*0.0225,0)))),0) -> 0 | AF6: =IFERROR((AC6+(AD6-AE6)/2)*INDEX('Facility Master'!R:R,MATCH(IDFC_TL_SNo,'Facility Master'!A:A,0))*(B6-B5)/DaysInYear,0) -> 0 | AG6: =IFERROR(ROUND(MAX(AC6+AD6-AE6,0),6),0) -> 0 | AH6: =IFERROR(MAX(AL5,0),0) -> 0 | AI6: =IFERROR(IF(AND(INDEX('Facility Master'!X:X,MATCH(ICICI_TL_SNo,'Facility Master'!A:A,0))<=B6,INDEX('Facility Master'!X:X,MATCH(ICICI_TL_SNo,'Facility Master'!A:A,0))>B5),INDEX('Facility Master'!K:K,MATCH(ICICI_TL_SNo,'Facility Master'!A:A,0)),0),0) -> 0 | AJ6: =IFERROR(IF(B6<ICICI_TL_RepStart,0,IF(B6>ICICI_TL_Maturity,0,IF(COUNTIFS($B$5:$B6,">="&ICICI_TL_RepStart,$B$5:$B6,"<="&ICICI_TL_Maturity)<=8,INDEX('Facility Master'!K:K,MATCH(ICICI_TL_SNo,'Facility Master'!A:A,0))*0.0125,IF(COUNTIFS($B$5:$B6,">="&ICICI_TL_RepStart,$B$5:$B6,"<="&ICICI_TL_Maturity)<=48,INDEX('Facility Master'!K:K,MATCH(ICICI_TL_SNo,'Facility Master'!A:A,0))*0.0225,0)))),0) -> 0 | AK6: =IFERROR((AH6+(AI6-AJ6)/2)*INDEX('Facility Master'!R:R,MATCH(ICICI_TL_SNo,'Facility Master'!A:A,0))*(B6-B5)/DaysInYear,0) -> 0 | AL6: =IFERROR(ROUND(MAX(AH6+AI6-AJ6,0),6),0) -> 0 | AM6: =F6+K6+P6+Z6+AE6+AJ6 -> 0 | AN6: =G6+L6+Q6+AA6+AF6+AK6 -> 32.222685 | AO6: =AM6+AN6 -> 32.222685 | AP6: =H6+M6+R6+AB6+AG6+AL6 -> 1360
A7: 3 | B7: 45291 | C7: Q3 FY24 | D7: =IFERROR(MAX(H6,0),0) -> 1125 | E7: =IFERROR(IF(AND(INDEX('Facility Master'!X:X,MATCH(UBI_RTL1_SNo,'Facility Master'!A:A,0))<=B7,INDEX('Facility Master'!X:X,MATCH(UBI_RTL1_SNo,'Facility Master'!A:A,0))>B6),INDEX('Facility Master'!K:K,MATCH(UBI_RTL1_SNo,'Facility Master'!A:A,0)),0),0) -> 0 | F7: =IFERROR(IF(B7<UBI_RTL1_RepStart,0,IF(B7>UBI_RTL1_Maturity,0,IF(COUNTIFS($B$5:$B7,">="&UBI_RTL1_RepStart,$B$5:$B7,"<="&UBI_RTL1_Maturity)<=8,INDEX('Facility Master'!K:K,MATCH(UBI_RTL1_SNo,'Facility Master'!A:A,0))*0.0125,IF(COUNTIFS($B$5:$B7,">="&UBI_RTL1_RepStart,$B$5:$B7,"<="&UBI_RTL1_Maturity)<=48,INDEX('Facility Master'!K:K,MATCH(UBI_RTL1_SNo,'Facility Master'!A:A,0))*0.0225,0)))),0) -> 0 | G7: =IFERROR((D7+(E7-F7)/2)*INDEX('Facility Master'!R:R,MATCH(UBI_RTL1_SNo,'Facility Master'!A:A,0))*(B7-B6)/DaysInYear,0) -> 26.654795 | H7: =IFERROR(ROUND(MAX(D7+E7-F7,0),6),0) -> 1125 | I7: =IFERROR(MAX(M6,0),0) -> 0 | J7: =IFERROR(IF(AND(INDEX('Facility Master'!X:X,MATCH(UBI_RTL2_SNo,'Facility Master'!A:A,0))<=B7,INDEX('Facility Master'!X:X,MATCH(UBI_RTL2_SNo,'Facility Master'!A:A,0))>B6),INDEX('Facility Master'!K:K,MATCH(UBI_RTL2_SNo,'Facility Master'!A:A,0)),0),0) -> 0 | K7: =IFERROR(IF(B7<UBI_RTL2_RepStart,0,IF(B7>UBI_RTL2_Maturity,0,IF(COUNTIFS($B$5:$B7,">="&UBI_RTL2_RepStart,$B$5:$B7,"<="&UBI_RTL2_Maturity)<=8,INDEX('Facility Master'!K:K,MATCH(UBI_RTL2_SNo,'Facility Master'!A:A,0))*0.0125,IF(COUNTIFS($B$5:$B7,">="&UBI_RTL2_RepStart,$B$5:$B7,"<="&UBI_RTL2_Maturity)<=48,INDEX('Facility Master'!K:K,MATCH(UBI_RTL2_SNo,'Facility Master'!A:A,0))*0.0225,0)))),0) -> 0 | L7: =IFERROR((I7+(J7-K7)/2)*INDEX('Facility Master'!R:R,MATCH(UBI_RTL2_SNo,'Facility Master'!A:A,0))*(B7-B6)/DaysInYear,0) -> 0 | M7: =IFERROR(ROUND(MAX(I7+J7-K7,0),6),0) -> 0 | N7: =IFERROR(MAX(R6,0),0) -> 235 | O7: =IFERROR(IF(AND(INDEX('Facility Master'!X:X,MATCH(IB_TL_SNo,'Facility Master'!A:A,0))<=B7,INDEX('Facility Master'!X:X,MATCH(IB_TL_SNo,'Facility Master'!A:A,0))>B6),INDEX('Facility Master'!K:K,MATCH(IB_TL_SNo,'Facility Master'!A:A,0)),0),0) -> 0 | P7: =IFERROR(IF(B7<IB_TL_RepStart,0,IF(B7>IB_TL_Maturity,0,IF(COUNTIFS($B$5:$B7,">="&IB_TL_RepStart,$B$5:$B7,"<="&IB_TL_Maturity)<=8,INDEX('Facility Master'!K:K,MATCH(IB_TL_SNo,'Facility Master'!A:A,0))*0.0125,IF(COUNTIFS($B$5:$B7,">="&IB_TL_RepStart,$B$5:$B7,"<="&IB_TL_Maturity)<=48,INDEX('Facility Master'!K:K,MATCH(IB_TL_SNo,'Facility Master'!A:A,0))*0.0225,0)))),0) -> 0 | Q7: =IFERROR((N7+(O7-P7)/2)*INDEX('Facility Master'!R:R,MATCH(IB_TL_SNo,'Facility Master'!A:A,0))*(B7-B6)/DaysInYear,0) -> 5.5678904 | R7: =IFERROR(ROUND(MAX(N7+O7-P7,0),6),0) -> 235 | S7: =IFERROR(MAX(W6,0),0) -> 0 | T7: =IFERROR(IF(AND(INDEX('Facility Master'!X:X,MATCH(RBL_TL_SNo,'Facility Master'!A:A,0))<=B7,INDEX('Facility Master'!X:X,MATCH(RBL_TL_SNo,'Facility Master'!A:A,0))>B6),INDEX('Facility Master'!K:K,MATCH(RBL_TL_SNo,'Facility Master'!A:A,0)),0),0) -> 0 | U7: =IFERROR(IF(AND(RBL_TL_Maturity<=B7,RBL_TL_Maturity>B6),INDEX('Facility Master'!K:K,MATCH(RBL_TL_SNo,'Facility Master'!A:A,0)),0),0) -> 0 | V7: =IFERROR((S7+(T7-U7)/2)*INDEX('Facility Master'!R:R,MATCH(RBL_TL_SNo,'Facility Master'!A:A,0))*(B7-B6)/DaysInYear,0) -> 0 | W7: =IFERROR(ROUND(MAX(S7+T7-U7,0),6),0) -> 0 | X7: =IFERROR(MAX(AB6,0),0) -> 0 | Y7: =IFERROR(IF(AND(INDEX('Facility Master'!X:X,MATCH(YBL_TL_SNo,'Facility Master'!A:A,0))<=B7,INDEX('Facility Master'!X:X,MATCH(YBL_TL_SNo,'Facility Master'!A:A,0))>B6),INDEX('Facility Master'!K:K,MATCH(YBL_TL_SNo,'Facility Master'!A:A,0)),0),0) -> 0 | Z7: =IFERROR(IF(B7<YBL_TL_RepStart,0,IF(B7>YBL_TL_Maturity,0,IF(COUNTIFS($B$5:$B7,">="&YBL_TL_RepStart,$B$5:$B7,"<="&YBL_TL_Maturity)<=8,INDEX('Facility Master'!K:K,MATCH(YBL_TL_SNo,'Facility Master'!A:A,0))*0.0125,IF(COUNTIFS($B$5:$B7,">="&YBL_TL_RepStart,$B$5:$B7,"<="&YBL_TL_Maturity)<=48,INDEX('Facility Master'!K:K,MATCH(YBL_TL_SNo,'Facility Master'!A:A,0))*0.0225,0)))),0) -> 0 | AA7: =IFERROR((X7+(Y7-Z7)/2)*INDEX('Facility Master'!R:R,MATCH(YBL_TL_SNo,'Facility Master'!A:A,0))*(B7-B6)/DaysInYear,0) -> 0 | AB7: =IFERROR(ROUND(MAX(X7+Y7-Z7,0),6),0) -> 0 | AC7: =IFERROR(MAX(AG6,0),0) -> 0 | AD7: =IFERROR(IF(AND(INDEX('Facility Master'!X:X,MATCH(IDFC_TL_SNo,'Facility Master'!A:A,0))<=B7,INDEX('Facility Master'!X:X,MATCH(IDFC_TL_SNo,'Facility Master'!A:A,0))>B6),INDEX('Facility Master'!K:K,MATCH(IDFC_TL_SNo,'Facility Master'!A:A,0)),0),0) -> 0 | AE7: =IFERROR(IF(B7<IDFC_TL_RepStart,0,IF(B7>IDFC_TL_Maturity,0,IF(COUNTIFS($B$5:$B7,">="&IDFC_TL_RepStart,$B$5:$B7,"<="&IDFC_TL_Maturity)<=8,INDEX('Facility Master'!K:K,MATCH(IDFC_TL_SNo,'Facility Master'!A:A,0))*0.0125,IF(COUNTIFS($B$5:$B7,">="&IDFC_TL_RepStart,$B$5:$B7,"<="&IDFC_TL_Maturity)<=48,INDEX('Facility Master'!K:K,MATCH(IDFC_TL_SNo,'Facility Master'!A:A,0))*0.0225,0)))),0) -> 0 | AF7: =IFERROR((AC7+(AD7-AE7)/2)*INDEX('Facility Master'!R:R,MATCH(IDFC_TL_SNo,'Facility Master'!A:A,0))*(B7-B6)/DaysInYear,0) -> 0 | AG7: =IFERROR(ROUND(MAX(AC7+AD7-AE7,0),6),0) -> 0 | AH7: =IFERROR(MAX(AL6,0),0) -> 0 | AI7: =IFERROR(IF(AND(INDEX('Facility Master'!X:X,MATCH(ICICI_TL_SNo,'Facility Master'!A:A,0))<=B7,INDEX('Facility Master'!X:X,MATCH(ICICI_TL_SNo,'Facility Master'!A:A,0))>B6),INDEX('Facility Master'!K:K,MATCH(ICICI_TL_SNo,'Facility Master'!A:A,0)),0),0) -> 0 | AJ7: =IFERROR(IF(B7<ICICI_TL_RepStart,0,IF(B7>ICICI_TL_Maturity,0,IF(COUNTIFS($B$5:$B7,">="&ICICI_TL_RepStart,$B$5:$B7,"<="&ICICI_TL_Maturity)<=8,INDEX('Facility Master'!K:K,MATCH(ICICI_TL_SNo,'Facility Master'!A:A,0))*0.0125,IF(COUNTIFS($B$5:$B7,">="&ICICI_TL_RepStart,$B$5:$B7,"<="&ICICI_TL_Maturity)<=48,INDEX('Facility Master'!K:K,MATCH(ICICI_TL_SNo,'Facility Master'!A:A,0))*0.0225,0)))),0) -> 0 | AK7: =IFERROR((AH7+(AI7-AJ7)/2)*INDEX('Facility Master'!R:R,MATCH(ICICI_TL_SNo,'Facility Master'!A:A,0))*(B7-B6)/DaysInYear,0) -> 0 | AL7: =IFERROR(ROUND(MAX(AH7+AI7-AJ7,0),6),0) -> 0 | AM7: =F7+K7+P7+Z7+AE7+AJ7 -> 0 | AN7: =G7+L7+Q7+AA7+AF7+AK7 -> 32.222685 | AO7: =AM7+AN7 -> 32.222685 | AP7: =H7+M7+R7+AB7+AG7+AL7 -> 1360
A8: 4 | B8: 45382 | C8: Q4 FY24 | D8: =IFERROR(MAX(H7,0),0) -> 1125 | E8: =IFERROR(IF(AND(INDEX('Facility Master'!X:X,MATCH(UBI_RTL1_SNo,'Facility Master'!A:A,0))<=B8,INDEX('Facility Master'!X:X,MATCH(UBI_RTL1_SNo,'Facility Master'!A:A,0))>B7),INDEX('Facility Master'!K:K,MATCH(UBI_RTL1_SNo,'Facility Master'!A:A,0)),0),0) -> 0 | F8: =IFERROR(IF(B8<UBI_RTL1_RepStart,0,IF(B8>UBI_RTL1_Maturity,0,IF(COUNTIFS($B$5:$B8,">="&UBI_RTL1_RepStart,$B$5:$B8,"<="&UBI_RTL1_Maturity)<=8,INDEX('Facility Master'!K:K,MATCH(UBI_RTL1_SNo,'Facility Master'!A:A,0))*0.0125,IF(COUNTIFS($B$5:$B8,">="&UBI_RTL1_RepStart,$B$5:$B8,"<="&UBI_RTL1_Maturity)<=48,INDEX('Facility Master'!K:K,MATCH(UBI_RTL1_SNo,'Facility Master'!A:A,0))*0.0225,0)))),0) -> 0 | G8: =IFERROR((D8+(E8-F8)/2)*INDEX('Facility Master'!R:R,MATCH(UBI_RTL1_SNo,'Facility Master'!A:A,0))*(B8-B7)/DaysInYear,0) -> 26.365068 | H8: =IFERROR(ROUND(MAX(D8+E8-F8,0),6),0) -> 1125 | I8: =IFERROR(MAX(M7,0),0) -> 0 | J8: =IFERROR(IF(AND(INDEX('Facility Master'!X:X,MATCH(UBI_RTL2_SNo,'Facility Master'!A:A,0))<=B8,INDEX('Facility Master'!X:X,MATCH(UBI_RTL2_SNo,'Facility Master'!A:A,0))>B7),INDEX('Facility Master'!K:K,MATCH(UBI_RTL2_SNo,'Facility Master'!A:A,0)),0),0) -> 0 | K8: =IFERROR(IF(B8<UBI_RTL2_RepStart,0,IF(B8>UBI_RTL2_Maturity,0,IF(COUNTIFS($B$5:$B8,">="&UBI_RTL2_RepStart,$B$5:$B8,"<="&UBI_RTL2_Maturity)<=8,INDEX('Facility Master'!K:K,MATCH(UBI_RTL2_SNo,'Facility Master'!A:A,0))*0.0125,IF(COUNTIFS($B$5:$B8,">="&UBI_RTL2_RepStart,$B$5:$B8,"<="&UBI_RTL2_Maturity)<=48,INDEX('Facility Master'!K:K,MATCH(UBI_RTL2_SNo,'Facility Master'!A:A,0))*0.0225,0)))),0) -> 0 | L8: =IFERROR((I8+(J8-K8)/2)*INDEX('Facility Master'!R:R,MATCH(UBI_RTL2_SNo,'Facility Master'!A:A,0))*(B8-B7)/DaysInYear,0) -> 0 | M8: =IFERROR(ROUND(MAX(I8+J8-K8,0),6),0) -> 0 | N8: =IFERROR(MAX(R7,0),0) -> 235 | O8: =IFERROR(IF(AND(INDEX('Facility Master'!X:X,MATCH(IB_TL_SNo,'Facility Master'!A:A,0))<=B8,INDEX('Facility Master'!X:X,MATCH(IB_TL_SNo,'Facility Master'!A:A,0))>B7),INDEX('Facility Master'!K:K,MATCH(IB_TL_SNo,'Facility Master'!A:A,0)),0),0) -> 0 | P8: =IFERROR(IF(B8<IB_TL_RepStart,0,IF(B8>IB_TL_Maturity,0,IF(COUNTIFS($B$5:$B8,">="&IB_TL_RepStart,$B$5:$B8,"<="&IB_TL_Maturity)<=8,INDEX('Facility Master'!K:K,MATCH(IB_TL_SNo,'Facility Master'!A:A,0))*0.0125,IF(COUNTIFS($B$5:$B8,">="&IB_TL_RepStart,$B$5:$B8,"<="&IB_TL_Maturity)<=48,INDEX('Facility Master'!K:K,MATCH(IB_TL_SNo,'Facility Master'!A:A,0))*0.0225,0)))),0) -> 0 | Q8: =IFERROR((N8+(O8-P8)/2)*INDEX('Facility Master'!R:R,MATCH(IB_TL_SNo,'Facility Master'!A:A,0))*(B8-B7)/DaysInYear,0) -> 5.5073699 | R8: =IFERROR(ROUND(MAX(N8+O8-P8,0),6),0) -> 235 | S8: =IFERROR(MAX(W7,0),0) -> 0 | T8: =IFERROR(IF(AND(INDEX('Facility Master'!X:X,MATCH(RBL_TL_SNo,'Facility Master'!A:A,0))<=B8,INDEX('Facility Master'!X:X,MATCH(RBL_TL_SNo,'Facility Master'!A:A,0))>B7),INDEX('Facility Master'!K:K,MATCH(RBL_TL_SNo,'Facility Master'!A:A,0)),0),0) -> 0 | U8: =IFERROR(IF(AND(RBL_TL_Maturity<=B8,RBL_TL_Maturity>B7),INDEX('Facility Master'!K:K,MATCH(RBL_TL_SNo,'Facility Master'!A:A,0)),0),0) -> 0 | V8: =IFERROR((S8+(T8-U8)/2)*INDEX('Facility Master'!R:R,MATCH(RBL_TL_SNo,'Facility Master'!A:A,0))*(B8-B7)/DaysInYear,0) -> 0 | W8: =IFERROR(ROUND(MAX(S8+T8-U8,0),6),0) -> 0 | X8: =IFERROR(MAX(AB7,0),0) -> 0 | Y8: =IFERROR(IF(AND(INDEX('Facility Master'!X:X,MATCH(YBL_TL_SNo,'Facility Master'!A:A,0))<=B8,INDEX('Facility Master'!X:X,MATCH(YBL_TL_SNo,'Facility Master'!A:A,0))>B7),INDEX('Facility Master'!K:K,MATCH(YBL_TL_SNo,'Facility Master'!A:A,0)),0),0) -> 0 | Z8: =IFERROR(IF(B8<YBL_TL_RepStart,0,IF(B8>YBL_TL_Maturity,0,IF(COUNTIFS($B$5:$B8,">="&YBL_TL_RepStart,$B$5:$B8,"<="&YBL_TL_Maturity)<=8,INDEX('Facility Master'!K:K,MATCH(YBL_TL_SNo,'Facility Master'!A:A,0))*0.0125,IF(COUNTIFS($B$5:$B8,">="&YBL_TL_RepStart,$B$5:$B8,"<="&YBL_TL_Maturity)<=48,INDEX('Facility Master'!K:K,MATCH(YBL_TL_SNo,'Facility Master'!A:A,0))*0.0225,0)))),0) -> 0 | AA8: =IFERROR((X8+(Y8-Z8)/2)*INDEX('Facility Master'!R:R,MATCH(YBL_TL_SNo,'Facility Master'!A:A,0))*(B8-B7)/DaysInYear,0) -> 0 | AB8: =IFERROR(ROUND(MAX(X8+Y8-Z8,0),6),0) -> 0 | AC8: =IFERROR(MAX(AG7,0),0) -> 0 | AD8: =IFERROR(IF(AND(INDEX('Facility Master'!X:X,MATCH(IDFC_TL_SNo,'Facility Master'!A:A,0))<=B8,INDEX('Facility Master'!X:X,MATCH(IDFC_TL_SNo,'Facility Master'!A:A,0))>B7),INDEX('Facility Master'!K:K,MATCH(IDFC_TL_SNo,'Facility Master'!A:A,0)),0),0) -> 0 | AE8: =IFERROR(IF(B8<IDFC_TL_RepStart,0,IF(B8>IDFC_TL_Maturity,0,IF(COUNTIFS($B$5:$B8,">="&IDFC_TL_RepStart,$B$5:$B8,"<="&IDFC_TL_Maturity)<=8,INDEX('Facility Master'!K:K,MATCH(IDFC_TL_SNo,'Facility Master'!A:A,0))*0.0125,IF(COUNTIFS($B$5:$B8,">="&IDFC_TL_RepStart,$B$5:$B8,"<="&IDFC_TL_Maturity)<=48,INDEX('Facility Master'!K:K,MATCH(IDFC_TL_SNo,'Facility Master'!A:A,0))*0.0225,0)))),0) -> 0 | AF8: =IFERROR((AC8+(AD8-AE8)/2)*INDEX('Facility Master'!R:R,MATCH(IDFC_TL_SNo,'Facility Master'!A:A,0))*(B8-B7)/DaysInYear,0) -> 0 | AG8: =IFERROR(ROUND(MAX(AC8+AD8-AE8,0),6),0) -> 0 | AH8: =IFERROR(MAX(AL7,0),0) -> 0 | AI8: =IFERROR(IF(AND(INDEX('Facility Master'!X:X,MATCH(ICICI_TL_SNo,'Facility Master'!A:A,0))<=B8,INDEX('Facility Master'!X:X,MATCH(ICICI_TL_SNo,'Facility Master'!A:A,0))>B7),INDEX('Facility Master'!K:K,MATCH(ICICI_TL_SNo,'Facility Master'!A:A,0)),0),0) -> 0 | AJ8: =IFERROR(IF(B8<ICICI_TL_RepStart,0,IF(B8>ICICI_TL_Maturity,0,IF(COUNTIFS($B$5:$B8,">="&ICICI_TL_RepStart,$B$5:$B8,"<="&ICICI_TL_Maturity)<=8,INDEX('Facility Master'!K:K,MATCH(ICICI_TL_SNo,'Facility Master'!A:A,0))*0.0125,IF(COUNTIFS($B$5:$B8,">="&ICICI_TL_RepStart,$B$5:$B8,"<="&ICICI_TL_Maturity)<=48,INDEX('Facility Master'!K:K,MATCH(ICICI_TL_SNo,'Facility Master'!A:A,0))*0.0225,0)))),0) -> 0 | AK8: =IFERROR((AH8+(AI8-AJ8)/2)*INDEX('Facility Master'!R:R,MATCH(ICICI_TL_SNo,'Facility Master'!A:A,0))*(B8-B7)/DaysInYear,0) -> 0 | AL8: =IFERROR(ROUND(MAX(AH8+AI8-AJ8,0),6),0) -> 0 | AM8: =F8+K8+P8+Z8+AE8+AJ8 -> 0 | AN8: =G8+L8+Q8+AA8+AF8+AK8 -> 31.872438 | AO8: =AM8+AN8 -> 31.872438 | AP8: =H8+M8+R8+AB8+AG8+AL8 -> 1360
A9: 5 | B9: 45473 | C9: Q1 FY25 | D9: =IFERROR(MAX(H8,0),0) -> 1125 | E9: =IFERROR(IF(AND(INDEX('Facility Master'!X:X,MATCH(UBI_RTL1_SNo,'Facility Master'!A:A,0))<=B9,INDEX('Facility Master'!X:X,MATCH(UBI_RTL1_SNo,'Facility Master'!A:A,0))>B8),INDEX('Facility Master'!K:K,MATCH(UBI_RTL1_SNo,'Facility Master'!A:A,0)),0),0) -> 0 | F9: =IFERROR(IF(B9<UBI_RTL1_RepStart,0,IF(B9>UBI_RTL1_Maturity,0,IF(COUNTIFS($B$5:$B9,">="&UBI_RTL1_RepStart,$B$5:$B9,"<="&UBI_RTL1_Maturity)<=8,INDEX('Facility Master'!K:K,MATCH(UBI_RTL1_SNo,'Facility Master'!A:A,0))*0.0125,IF(COUNTIFS($B$5:$B9,">="&UBI_RTL1_RepStart,$B$5:$B9,"<="&UBI_RTL1_Maturity)<=48,INDEX('Facility Master'!K:K,MATCH(UBI_RTL1_SNo,'Facility Master'!A:A,0))*0.0225,0)))),0) -> 0 | G9: =IFERROR((D9+(E9-F9)/2)*INDEX('Facility Master'!R:R,MATCH(UBI_RTL1_SNo,'Facility Master'!A:A,0))*(B9-B8)/DaysInYear,0) -> 26.365068 | H9: =IFERROR(ROUND(MAX(D9+E9-F9,0),6),0) -> 1125 | I9: =IFERROR(MAX(M8,0),0) -> 0 | J9: =IFERROR(IF(AND(INDEX('Facility Master'!X:X,MATCH(UBI_RTL2_SNo,'Facility Master'!A:A,0))<=B9,INDEX('Facility Master'!X:X,MATCH(UBI_RTL2_SNo,'Facility Master'!A:A,0))>B8),INDEX('Facility Master'!K:K,MATCH(UBI_RTL2_SNo,'Facility Master'!A:A,0)),0),0) -> 0 | K9: =IFERROR(IF(B9<UBI_RTL2_RepStart,0,IF(B9>UBI_RTL2_Maturity,0,IF(COUNTIFS($B$5:$B9,">="&UBI_RTL2_RepStart,$B$5:$B9,"<="&UBI_RTL2_Maturity)<=8,INDEX('Facility Master'!K:K,MATCH(UBI_RTL2_SNo,'Facility Master'!A:A,0))*0.0125,IF(COUNTIFS($B$5:$B9,">="&UBI_RTL2_RepStart,$B$5:$B9,"<="&UBI_RTL2_Maturity)<=48,INDEX('Facility Master'!K:K,MATCH(UBI_RTL2_SNo,'Facility Master'!A:A,0))*0.0225,0)))),0) -> 0 | L9: =IFERROR((I9+(J9-K9)/2)*INDEX('Facility Master'!R:R,MATCH(UBI_RTL2_SNo,'Facility Master'!A:A,0))*(B9-B8)/DaysInYear,0) -> 0 | M9: =IFERROR(ROUND(MAX(I9+J9-K9,0),6),0) -> 0 | N9: =IFERROR(MAX(R8,0),0) -> 235 | O9: =IFERROR(IF(AND(INDEX('Facility Master'!X:X,MATCH(IB_TL_SNo,'Facility Master'!A:A,0))<=B9,INDEX('Facility Master'!X:X,MATCH(IB_TL_SNo,'Facility Master'!A:A,0))>B8),INDEX('Facility Master'!K:K,MATCH(IB_TL_SNo,'Facility Master'!A:A,0)),0),0) -> 0 | P9: =IFERROR(IF(B9<IB_TL_RepStart,0,IF(B9>IB_TL_Maturity,0,IF(COUNTIFS($B$5:$B9,">="&IB_TL_RepStart,$B$5:$B9,"<="&IB_TL_Maturity)<=8,INDEX('Facility Master'!K:K,MATCH(IB_TL_SNo,'Facility Master'!A:A,0))*0.0125,IF(COUNTIFS($B$5:$B9,">="&IB_TL_RepStart,$B$5:$B9,"<="&IB_TL_Maturity)<=48,INDEX('Facility Master'!K:K,MATCH(IB_TL_SNo,'Facility Master'!A:A,0))*0.0225,0)))),0) -> 0 | Q9: =IFERROR((N9+(O9-P9)/2)*INDEX('Facility Master'!R:R,MATCH(IB_TL_SNo,'Facility Master'!A:A,0))*(B9-B8)/DaysInYear,0) -> 5.5073699 | R9: =IFERROR(ROUND(MAX(N9+O9-P9,0),6),0) -> 235 | S9: =IFERROR(MAX(W8,0),0) -> 0 | T9: =IFERROR(IF(AND(INDEX('Facility Master'!X:X,MATCH(RBL_TL_SNo,'Facility Master'!A:A,0))<=B9,INDEX('Facility Master'!X:X,MATCH(RBL_TL_SNo,'Facility Master'!A:A,0))>B8),INDEX('Facility Master'!K:K,MATCH(RBL_TL_SNo,'Facility Master'!A:A,0)),0),0) -> 0 | U9: =IFERROR(IF(AND(RBL_TL_Maturity<=B9,RBL_TL_Maturity>B8),INDEX('Facility Master'!K:K,MATCH(RBL_TL_SNo,'Facility Master'!A:A,0)),0),0) -> 0 | V9: =IFERROR((S9+(T9-U9)/2)*INDEX('Facility Master'!R:R,MATCH(RBL_TL_SNo,'Facility Master'!A:A,0))*(B9-B8)/DaysInYear,0) -> 0 | W9: =IFERROR(ROUND(MAX(S9+T9-U9,0),6),0) -> 0 | X9: =IFERROR(MAX(AB8,0),0) -> 0 | Y9: =IFERROR(IF(AND(INDEX('Facility Master'!X:X,MATCH(YBL_TL_SNo,'Facility Master'!A:A,0))<=B9,INDEX('Facility Master'!X:X,MATCH(YBL_TL_SNo,'Facility Master'!A:A,0))>B8),INDEX('Facility Master'!K:K,MATCH(YBL_TL_SNo,'Facility Master'!A:A,0)),0),0) -> 0 | Z9: =IFERROR(IF(B9<YBL_TL_RepStart,0,IF(B9>YBL_TL_Maturity,0,IF(COUNTIFS($B$5:$B9,">="&YBL_TL_RepStart,$B$5:$B9,"<="&YBL_TL_Maturity)<=8,INDEX('Facility Master'!K:K,MATCH(YBL_TL_SNo,'Facility Master'!A:A,0))*0.0125,IF(COUNTIFS($B$5:$B9,">="&YBL_TL_RepStart,$B$5:$B9,"<="&YBL_TL_Maturity)<=48,INDEX('Facility Master'!K:K,MATCH(YBL_TL_SNo,'Facility Master'!A:A,0))*0.0225,0)))),0) -> 0 | AA9: =IFERROR((X9+(Y9-Z9)/2)*INDEX('Facility Master'!R:R,MATCH(YBL_TL_SNo,'Facility Master'!A:A,0))*(B9-B8)/DaysInYear,0) -> 0 | AB9: =IFERROR(ROUND(MAX(X9+Y9-Z9,0),6),0) -> 0 | AC9: =IFERROR(MAX(AG8,0),0) -> 0 | AD9: =IFERROR(IF(AND(INDEX('Facility Master'!X:X,MATCH(IDFC_TL_SNo,'Facility Master'!A:A,0))<=B9,INDEX('Facility Master'!X:X,MATCH(IDFC_TL_SNo,'Facility Master'!A:A,0))>B8),INDEX('Facility Master'!K:K,MATCH(IDFC_TL_SNo,'Facility Master'!A:A,0)),0),0) -> 0 | AE9: =IFERROR(IF(B9<IDFC_TL_RepStart,0,IF(B9>IDFC_TL_Maturity,0,IF(COUNTIFS($B$5:$B9,">="&IDFC_TL_RepStart,$B$5:$B9,"<="&IDFC_TL_Maturity)<=8,INDEX('Facility Master'!K:K,MATCH(IDFC_TL_SNo,'Facility Master'!A:A,0))*0.0125,IF(COUNTIFS($B$5:$B9,">="&IDFC_TL_RepStart,$B$5:$B9,"<="&IDFC_TL_Maturity)<=48,INDEX('Facility Master'!K:K,MATCH(IDFC_TL_SNo,'Facility Master'!A:A,0))*0.0225,0)))),0) -> 0 | AF9: =IFERROR((AC9+(AD9-AE9)/2)*INDEX('Facility Master'!R:R,MATCH(IDFC_TL_SNo,'Facility Master'!A:A,0))*(B9-B8)/DaysInYear,0) -> 0 | AG9: =IFERROR(ROUND(MAX(AC9+AD9-AE9,0),6),0) -> 0 | AH9: =IFERROR(MAX(AL8,0),0) -> 0 | AI9: =IFERROR(IF(AND(INDEX('Facility Master'!X:X,MATCH(ICICI_TL_SNo,'Facility Master'!A:A,0))<=B9,INDEX('Facility Master'!X:X,MATCH(ICICI_TL_SNo,'Facility Master'!A:A,0))>B8),INDEX('Facility Master'!K:K,MATCH(ICICI_TL_SNo,'Facility Master'!A:A,0)),0),0) -> 0 | AJ9: =IFERROR(IF(B9<ICICI_TL_RepStart,0,IF(B9>ICICI_TL_Maturity,0,IF(COUNTIFS($B$5:$B9,">="&ICICI_TL_RepStart,$B$5:$B9,"<="&ICICI_TL_Maturity)<=8,INDEX('Facility Master'!K:K,MATCH(ICICI_TL_SNo,'Facility Master'!A:A,0))*0.0125,IF(COUNTIFS($B$5:$B9,">="&ICICI_TL_RepStart,$B$5:$B9,"<="&ICICI_TL_Maturity)<=48,INDEX('Facility Master'!K:K,MATCH(ICICI_TL_SNo,'Facility Master'!A:A,0))*0.0225,0)))),0) -> 0 | AK9: =IFERROR((AH9+(AI9-AJ9)/2)*INDEX('Facility Master'!R:R,MATCH(ICICI_TL_SNo,'Facility Master'!A:A,0))*(B9-B8)/DaysInYear,0) -> 0 | AL9: =IFERROR(ROUND(MAX(AH9+AI9-AJ9,0),6),0) -> 0 | AM9: =F9+K9+P9+Z9+AE9+AJ9 -> 0 | AN9: =G9+L9+Q9+AA9+AF9+AK9 -> 31.872438 | AO9: =AM9+AN9 -> 31.872438 | AP9: =H9+M9+R9+AB9+AG9+AL9 -> 1360
A10: 6 | B10: 45565 | C10: Q2 FY25 | D10: =IFERROR(MAX(H9,0),0) -> 1125 | E10: =IFERROR(IF(AND(INDEX('Facility Master'!X:X,MATCH(UBI_RTL1_SNo,'Facility Master'!A:A,0))<=B10,INDEX('Facility Master'!X:X,MATCH(UBI_RTL1_SNo,'Facility Master'!A:A,0))>B9),INDEX('Facility Master'!K:K,MATCH(UBI_RTL1_SNo,'Facility Master'!A:A,0)),0),0) -> 0 | F10: =IFERROR(IF(B10<UBI_RTL1_RepStart,0,IF(B10>UBI_RTL1_Maturity,0,IF(COUNTIFS($B$5:$B10,">="&UBI_RTL1_RepStart,$B$5:$B10,"<="&UBI_RTL1_Maturity)<=8,INDEX('Facility Master'!K:K,MATCH(UBI_RTL1_SNo,'Facility Master'!A:A,0))*0.0125,IF(COUNTIFS($B$5:$B10,">="&UBI_RTL1_RepStart,$B$5:$B10,"<="&UBI_RTL1_Maturity)<=48,INDEX('Facility Master'!K:K,MATCH(UBI_RTL1_SNo,'Facility Master'!A:A,0))*0.0225,0)))),0) -> 0 | G10: =IFERROR((D10+(E10-F10)/2)*INDEX('Facility Master'!R:R,MATCH(UBI_RTL1_SNo,'Facility Master'!A:A,0))*(B10-B9)/DaysInYear,0) -> 26.654795 | H10: =IFERROR(ROUND(MAX(D10+E10-F10,0),6),0) -> 1125 | I10: =IFERROR(MAX(M9,0),0) -> 0 | J10: =IFERROR(IF(AND(INDEX('Facility Master'!X:X,MATCH(UBI_RTL2_SNo,'Facility Master'!A:A,0))<=B10,INDEX('Facility Master'!X:X,MATCH(UBI_RTL2_SNo,'Facility Master'!A:A,0))>B9),INDEX('Facility Master'!K:K,MATCH(UBI_RTL2_SNo,'Facility Master'!A:A,0)),0),0) -> 0 | K10: =IFERROR(IF(B10<UBI_RTL2_RepStart,0,IF(B10>UBI_RTL2_Maturity,0,IF(COUNTIFS($B$5:$B10,">="&UBI_RTL2_RepStart,$B$5:$B10,"<="&UBI_RTL2_Maturity)<=8,INDEX('Facility Master'!K:K,MATCH(UBI_RTL2_SNo,'Facility Master'!A:A,0))*0.0125,IF(COUNTIFS($B$5:$B10,">="&UBI_RTL2_RepStart,$B$5:$B10,"<="&UBI_RTL2_Maturity)<=48,INDEX('Facility Master'!K:K,MATCH(UBI_RTL2_SNo,'Facility Master'!A:A,0))*0.0225,0)))),0) -> 0 | L10: =IFERROR((I10+(J10-K10)/2)*INDEX('Facility Master'!R:R,MATCH(UBI_RTL2_SNo,'Facility Master'!A:A,0))*(B10-B9)/DaysInYear,0) -> 0 | M10: =IFERROR(ROUND(MAX(I10+J10-K10,0),6),0) -> 0 | N10: =IFERROR(MAX(R9,0),0) -> 235 | O10: =IFERROR(IF(AND(INDEX('Facility Master'!X:X,MATCH(IB_TL_SNo,'Facility Master'!A:A,0))<=B10,INDEX('Facility Master'!X:X,MATCH(IB_TL_SNo,'Facility Master'!A:A,0))>B9),INDEX('Facility Master'!K:K,MATCH(IB_TL_SNo,'Facility Master'!A:A,0)),0),0) -> 0 | P10: =IFERROR(IF(B10<IB_TL_RepStart,0,IF(B10>IB_TL_Maturity,0,IF(COUNTIFS($B$5:$B10,">="&IB_TL_RepStart,$B$5:$B10,"<="&IB_TL_Maturity)<=8,INDEX('Facility Master'!K:K,MATCH(IB_TL_SNo,'Facility Master'!A:A,0))*0.0125,IF(COUNTIFS($B$5:$B10,">="&IB_TL_RepStart,$B$5:$B10,"<="&IB_TL_Maturity)<=48,INDEX('Facility Master'!K:K,MATCH(IB_TL_SNo,'Facility Master'!A:A,0))*0.0225,0)))),0) -> 0 | Q10: =IFERROR((N10+(O10-P10)/2)*INDEX('Facility Master'!R:R,MATCH(IB_TL_SNo,'Facility Master'!A:A,0))*(B10-B9)/DaysInYear,0) -> 5.5678904 | R10: =IFERROR(ROUND(MAX(N10+O10-P10,0),6),0) -> 235 | S10: =IFERROR(MAX(W9,0),0) -> 0 | T10: =IFERROR(IF(AND(INDEX('Facility Master'!X:X,MATCH(RBL_TL_SNo,'Facility Master'!A:A,0))<=B10,INDEX('Facility Master'!X:X,MATCH(RBL_TL_SNo,'Facility Master'!A:A,0))>B9),INDEX('Facility Master'!K:K,MATCH(RBL_TL_SNo,'Facility Master'!A:A,0)),0),0) -> 0 | U10: =IFERROR(IF(AND(RBL_TL_Maturity<=B10,RBL_TL_Maturity>B9),INDEX('Facility Master'!K:K,MATCH(RBL_TL_SNo,'Facility Master'!A:A,0)),0),0) -> 0 | V10: =IFERROR((S10+(T10-U10)/2)*INDEX('Facility Master'!R:R,MATCH(RBL_TL_SNo,'Facility Master'!A:A,0))*(B10-B9)/DaysInYear,0) -> 0 | W10: =IFERROR(ROUND(MAX(S10+T10-U10,0),6),0) -> 0 | X10: =IFERROR(MAX(AB9,0),0) -> 0 | Y10: =IFERROR(IF(AND(INDEX('Facility Master'!X:X,MATCH(YBL_TL_SNo,'Facility Master'!A:A,0))<=B10,INDEX('Facility Master'!X:X,MATCH(YBL_TL_SNo,'Facility Master'!A:A,0))>B9),INDEX('Facility Master'!K:K,MATCH(YBL_TL_SNo,'Facility Master'!A:A,0)),0),0) -> 0 | Z10: =IFERROR(IF(B10<YBL_TL_RepStart,0,IF(B10>YBL_TL_Maturity,0,IF(COUNTIFS($B$5:$B10,">="&YBL_TL_RepStart,$B$5:$B10,"<="&YBL_TL_Maturity)<=8,INDEX('Facility Master'!K:K,MATCH(YBL_TL_SNo,'Facility Master'!A:A,0))*0.0125,IF(COUNTIFS($B$5:$B10,">="&YBL_TL_RepStart,$B$5:$B10,"<="&YBL_TL_Maturity)<=48,INDEX('Facility Master'!K:K,MATCH(YBL_TL_SNo,'Facility Master'!A:A,0))*0.0225,0)))),0) -> 0 | AA10: =IFERROR((X10+(Y10-Z10)/2)*INDEX('Facility Master'!R:R,MATCH(YBL_TL_SNo,'Facility Master'!A:A,0))*(B10-B9)/DaysInYear,0) -> 0 | AB10: =IFERROR(ROUND(MAX(X10+Y10-Z10,0),6),0) -> 0 | AC10: =IFERROR(MAX(AG9,0),0) -> 0 | AD10: =IFERROR(IF(AND(INDEX('Facility Master'!X:X,MATCH(IDFC_TL_SNo,'Facility Master'!A:A,0))<=B10,INDEX('Facility Master'!X:X,MATCH(IDFC_TL_SNo,'Facility Master'!A:A,0))>B9),INDEX('Facility Master'!K:K,MATCH(IDFC_TL_SNo,'Facility Master'!A:A,0)),0),0) -> 0 | AE10: =IFERROR(IF(B10<IDFC_TL_RepStart,0,IF(B10>IDFC_TL_Maturity,0,IF(COUNTIFS($B$5:$B10,">="&IDFC_TL_RepStart,$B$5:$B10,"<="&IDFC_TL_Maturity)<=8,INDEX('Facility Master'!K:K,MATCH(IDFC_TL_SNo,'Facility Master'!A:A,0))*0.0125,IF(COUNTIFS($B$5:$B10,">="&IDFC_TL_RepStart,$B$5:$B10,"<="&IDFC_TL_Maturity)<=48,INDEX('Facility Master'!K:K,MATCH(IDFC_TL_SNo,'Facility Master'!A:A,0))*0.0225,0)))),0) -> 0 | AF10: =IFERROR((AC10+(AD10-AE10)/2)*INDEX('Facility Master'!R:R,MATCH(IDFC_TL_SNo,'Facility Master'!A:A,0))*(B10-B9)/DaysInYear,0) -> 0 | AG10: =IFERROR(ROUND(MAX(AC10+AD10-AE10,0),6),0) -> 0 | AH10: =IFERROR(MAX(AL9,0),0) -> 0 | AI10: =IFERROR(IF(AND(INDEX('Facility Master'!X:X,MATCH(ICICI_TL_SNo,'Facility Master'!A:A,0))<=B10,INDEX('Facility Master'!X:X,MATCH(ICICI_TL_SNo,'Facility Master'!A:A,0))>B9),INDEX('Facility Master'!K:K,MATCH(ICICI_TL_SNo,'Facility Master'!A:A,0)),0),0) -> 0 | AJ10: =IFERROR(IF(B10<ICICI_TL_RepStart,0,IF(B10>ICICI_TL_Maturity,0,IF(COUNTIFS($B$5:$B10,">="&ICICI_TL_RepStart,$B$5:$B10,"<="&ICICI_TL_Maturity)<=8,INDEX('Facility Master'!K:K,MATCH(ICICI_TL_SNo,'Facility Master'!A:A,0))*0.0125,IF(COUNTIFS($B$5:$B10,">="&ICICI_TL_RepStart,$B$5:$B10,"<="&ICICI_TL_Maturity)<=48,INDEX('Facility Master'!K:K,MATCH(ICICI_TL_SNo,'Facility Master'!A:A,0))*0.0225,0)))),0) -> 0 | AK10: =IFERROR((AH10+(AI10-AJ10)/2)*INDEX('Facility Master'!R:R,MATCH(ICICI_TL_SNo,'Facility Master'!A:A,0))*(B10-B9)/DaysInYear,0) -> 0 | AL10: =IFERROR(ROUND(MAX(AH10+AI10-AJ10,0),6),0) -> 0 | AM10: =F10+K10+P10+Z10+AE10+AJ10 -> 0 | AN10: =G10+L10+Q10+AA10+AF10+AK10 -> 32.222685 | AO10: =AM10+AN10 -> 32.222685 | AP10: =H10+M10+R10+AB10+AG10+AL10 -> 1360
A11: 7 | B11: 45657 | C11: Q3 FY25 | D11: =IFERROR(MAX(H10,0),0) -> 1125 | E11: =IFERROR(IF(AND(INDEX('Facility Master'!X:X,MATCH(UBI_RTL1_SNo,'Facility Master'!A:A,0))<=B11,INDEX('Facility Master'!X:X,MATCH(UBI_RTL1_SNo,'Facility Master'!A:A,0))>B10),INDEX('Facility Master'!K:K,MATCH(UBI_RTL1_SNo,'Facility Master'!A:A,0)),0),0) -> 0 | F11: =IFERROR(IF(B11<UBI_RTL1_RepStart,0,IF(B11>UBI_RTL1_Maturity,0,IF(COUNTIFS($B$5:$B11,">="&UBI_RTL1_RepStart,$B$5:$B11,"<="&UBI_RTL1_Maturity)<=8,INDEX('Facility Master'!K:K,MATCH(UBI_RTL1_SNo,'Facility Master'!A:A,0))*0.0125,IF(COUNTIFS($B$5:$B11,">="&UBI_RTL1_RepStart,$B$5:$B11,"<="&UBI_RTL1_Maturity)<=48,INDEX('Facility Master'!K:K,MATCH(UBI_RTL1_SNo,'Facility Master'!A:A,0))*0.0225,0)))),0) -> 0 | G11: =IFERROR((D11+(E11-F11)/2)*INDEX('Facility Master'!R:R,MATCH(UBI_RTL1_SNo,'Facility Master'!A:A,0))*(B11-B10)/DaysInYear,0) -> 26.654795 | H11: =IFERROR(ROUND(MAX(D11+E11-F11,0),6),0) -> 1125 | I11: =IFERROR(MAX(M10,0),0) -> 0 | J11: =IFERROR(IF(AND(INDEX('Facility Master'!X:X,MATCH(UBI_RTL2_SNo,'Facility Master'!A:A,0))<=B11,INDEX('Facility Master'!X:X,MATCH(UBI_RTL2_SNo,'Facility Master'!A:A,0))>B10),INDEX('Facility Master'!K:K,MATCH(UBI_RTL2_SNo,'Facility Master'!A:A,0)),0),0) -> 0 | K11: =IFERROR(IF(B11<UBI_RTL2_RepStart,0,IF(B11>UBI_RTL2_Maturity,0,IF(COUNTIFS($B$5:$B11,">="&UBI_RTL2_RepStart,$B$5:$B11,"<="&UBI_RTL2_Maturity)<=8,INDEX('Facility Master'!K:K,MATCH(UBI_RTL2_SNo,'Facility Master'!A:A,0))*0.0125,IF(COUNTIFS($B$5:$B11,">="&UBI_RTL2_RepStart,$B$5:$B11,"<="&UBI_RTL2_Maturity)<=48,INDEX('Facility Master'!K:K,MATCH(UBI_RTL2_SNo,'Facility Master'!A:A,0))*0.0225,0)))),0) -> 0 | L11: =IFERROR((I11+(J11-K11)/2)*INDEX('Facility Master'!R:R,MATCH(UBI_RTL2_SNo,'Facility Master'!A:A,0))*(B11-B10)/DaysInYear,0) -> 0 | M11: =IFERROR(ROUND(MAX(I11+J11-K11,0),6),0) -> 0 | N11: =IFERROR(MAX(R10,0),0) -> 235 | O11: =IFERROR(IF(AND(INDEX('Facility Master'!X:X,MATCH(IB_TL_SNo,'Facility Master'!A:A,0))<=B11,INDEX('Facility Master'!X:X,MATCH(IB_TL_SNo,'Facility Master'!A:A,0))>B10),INDEX('Facility Master'!K:K,MATCH(IB_TL_SNo,'Facility Master'!A:A,0)),0),0) -> 0 | P11: =IFERROR(IF(B11<IB_TL_RepStart,0,IF(B11>IB_TL_Maturity,0,IF(COUNTIFS($B$5:$B11,">="&IB_TL_RepStart,$B$5:$B11,"<="&IB_TL_Maturity)<=8,INDEX('Facility Master'!K:K,MATCH(IB_TL_SNo,'Facility Master'!A:A,0))*0.0125,IF(COUNTIFS($B$5:$B11,">="&IB_TL_RepStart,$B$5:$B11,"<="&IB_TL_Maturity)<=48,INDEX('Facility Master'!K:K,MATCH(IB_TL_SNo,'Facility Master'!A:A,0))*0.0225,0)))),0) -> 0 | Q11: =IFERROR((N11+(O11-P11)/2)*INDEX('Facility Master'!R:R,MATCH(IB_TL_SNo,'Facility Master'!A:A,0))*(B11-B10)/DaysInYear,0) -> 5.5678904 | R11: =IFERROR(ROUND(MAX(N11+O11-P11,0),6),0) -> 235 | S11: =IFERROR(MAX(W10,0),0) -> 0 | T11: =IFERROR(IF(AND(INDEX('Facility Master'!X:X,MATCH(RBL_TL_SNo,'Facility Master'!A:A,0))<=B11,INDEX('Facility Master'!X:X,MATCH(RBL_TL_SNo,'Facility Master'!A:A,0))>B10),INDEX('Facility Master'!K:K,MATCH(RBL_TL_SNo,'Facility Master'!A:A,0)),0),0) -> 0 | U11: =IFERROR(IF(AND(RBL_TL_Maturity<=B11,RBL_TL_Maturity>B10),INDEX('Facility Master'!K:K,MATCH(RBL_TL_SNo,'Facility Master'!A:A,0)),0),0) -> 0 | V11: =IFERROR((S11+(T11-U11)/2)*INDEX('Facility Master'!R:R,MATCH(RBL_TL_SNo,'Facility Master'!A:A,0))*(B11-B10)/DaysInYear,0) -> 0 | W11: =IFERROR(ROUND(MAX(S11+T11-U11,0),6),0) -> 0 | X11: =IFERROR(MAX(AB10,0),0) -> 0 | Y11: =IFERROR(IF(AND(INDEX('Facility Master'!X:X,MATCH(YBL_TL_SNo,'Facility Master'!A:A,0))<=B11,INDEX('Facility Master'!X:X,MATCH(YBL_TL_SNo,'Facility Master'!A:A,0))>B10),INDEX('Facility Master'!K:K,MATCH(YBL_TL_SNo,'Facility Master'!A:A,0)),0),0) -> 0 | Z11: =IFERROR(IF(B11<YBL_TL_RepStart,0,IF(B11>YBL_TL_Maturity,0,IF(COUNTIFS($B$5:$B11,">="&YBL_TL_RepStart,$B$5:$B11,"<="&YBL_TL_Maturity)<=8,INDEX('Facility Master'!K:K,MATCH(YBL_TL_SNo,'Facility Master'!A:A,0))*0.0125,IF(COUNTIFS($B$5:$B11,">="&YBL_TL_RepStart,$B$5:$B11,"<="&YBL_TL_Maturity)<=48,INDEX('Facility Master'!K:K,MATCH(YBL_TL_SNo,'Facility Master'!A:A,0))*0.0225,0)))),0) -> 0 | AA11: =IFERROR((X11+(Y11-Z11)/2)*INDEX('Facility Master'!R:R,MATCH(YBL_TL_SNo,'Facility Master'!A:A,0))*(B11-B10)/DaysInYear,0) -> 0 | AB11: =IFERROR(ROUND(MAX(X11+Y11-Z11,0),6),0) -> 0 | AC11: =IFERROR(MAX(AG10,0),0) -> 0 | AD11: =IFERROR(IF(AND(INDEX('Facility Master'!X:X,MATCH(IDFC_TL_SNo,'Facility Master'!A:A,0))<=B11,INDEX('Facility Master'!X:X,MATCH(IDFC_TL_SNo,'Facility Master'!A:A,0))>B10),INDEX('Facility Master'!K:K,MATCH(IDFC_TL_SNo,'Facility Master'!A:A,0)),0),0) -> 0 | AE11: =IFERROR(IF(B11<IDFC_TL_RepStart,0,IF(B11>IDFC_TL_Maturity,0,IF(COUNTIFS($B$5:$B11,">="&IDFC_TL_RepStart,$B$5:$B11,"<="&IDFC_TL_Maturity)<=8,INDEX('Facility Master'!K:K,MATCH(IDFC_TL_SNo,'Facility Master'!A:A,0))*0.0125,IF(COUNTIFS($B$5:$B11,">="&IDFC_TL_RepStart,$B$5:$B11,"<="&IDFC_TL_Maturity)<=48,INDEX('Facility Master'!K:K,MATCH(IDFC_TL_SNo,'Facility Master'!A:A,0))*0.0225,0)))),0) -> 0 | AF11: =IFERROR((AC11+(AD11-AE11)/2)*INDEX('Facility Master'!R:R,MATCH(IDFC_TL_SNo,'Facility Master'!A:A,0))*(B11-B10)/DaysInYear,0) -> 0 | AG11: =IFERROR(ROUND(MAX(AC11+AD11-AE11,0),6),0) -> 0 | AH11: =IFERROR(MAX(AL10,0),0) -> 0 | AI11: =IFERROR(IF(AND(INDEX('Facility Master'!X:X,MATCH(ICICI_TL_SNo,'Facility Master'!A:A,0))<=B11,INDEX('Facility Master'!X:X,MATCH(ICICI_TL_SNo,'Facility Master'!A:A,0))>B10),INDEX('Facility Master'!K:K,MATCH(ICICI_TL_SNo,'Facility Master'!A:A,0)),0),0) -> 0 | AJ11: =IFERROR(IF(B11<ICICI_TL_RepStart,0,IF(B11>ICICI_TL_Maturity,0,IF(COUNTIFS($B$5:$B11,">="&ICICI_TL_RepStart,$B$5:$B11,"<="&ICICI_TL_Maturity)<=8,INDEX('Facility Master'!K:K,MATCH(ICICI_TL_SNo,'Facility Master'!A:A,0))*0.0125,IF(COUNTIFS($B$5:$B11,">="&ICICI_TL_RepStart,$B$5:$B11,"<="&ICICI_TL_Maturity)<=48,INDEX('Facility Master'!K:K,MATCH(ICICI_TL_SNo,'Facility Master'!A:A,0))*0.0225,0)))),0) -> 0 | AK11: =IFERROR((AH11+(AI11-AJ11)/2)*INDEX('Facility Master'!R:R,MATCH(ICICI_TL_SNo,'Facility Master'!A:A,0))*(B11-B10)/DaysInYear,0) -> 0 | AL11: =IFERROR(ROUND(MAX(AH11+AI11-AJ11,0),6),0) -> 0 | AM11: =F11+K11+P11+Z11+AE11+AJ11 -> 0 | AN11: =G11+L11+Q11+AA11+AF11+AK11 -> 32.222685 | AO11: =AM11+AN11 -> 32.222685 | AP11: =H11+M11+R11+AB11+AG11+AL11 -> 1360
A12: 8 | B12: 45747 | C12: Q4 FY25 | D12: =IFERROR(MAX(H11,0),0) -> 1125 | E12: =IFERROR(IF(AND(INDEX('Facility Master'!X:X,MATCH(UBI_RTL1_SNo,'Facility Master'!A:A,0))<=B12,INDEX('Facility Master'!X:X,MATCH(UBI_RTL1_SNo,'Facility Master'!A:A,0))>B11),INDEX('Facility Master'!K:K,MATCH(UBI_RTL1_SNo,'Facility Master'!A:A,0)),0),0) -> 0 | F12: =IFERROR(IF(B12<UBI_RTL1_RepStart,0,IF(B12>UBI_RTL1_Maturity,0,IF(COUNTIFS($B$5:$B12,">="&UBI_RTL1_RepStart,$B$5:$B12,"<="&UBI_RTL1_Maturity)<=8,INDEX('Facility Master'!K:K,MATCH(UBI_RTL1_SNo,'Facility Master'!A:A,0))*0.0125,IF(COUNTIFS($B$5:$B12,">="&UBI_RTL1_RepStart,$B$5:$B12,"<="&UBI_RTL1_Maturity)<=48,INDEX('Facility Master'!K:K,MATCH(UBI_RTL1_SNo,'Facility Master'!A:A,0))*0.0225,0)))),0) -> 0 | G12: =IFERROR((D12+(E12-F12)/2)*INDEX('Facility Master'!R:R,MATCH(UBI_RTL1_SNo,'Facility Master'!A:A,0))*(B12-B11)/DaysInYear,0) -> 26.075342 | H12: =IFERROR(ROUND(MAX(D12+E12-F12,0),6),0) -> 1125 | I12: =IFERROR(MAX(M11,0),0) -> 0 | J12: =IFERROR(IF(AND(INDEX('Facility Master'!X:X,MATCH(UBI_RTL2_SNo,'Facility Master'!A:A,0))<=B12,INDEX('Facility Master'!X:X,MATCH(UBI_RTL2_SNo,'Facility Master'!A:A,0))>B11),INDEX('Facility Master'!K:K,MATCH(UBI_RTL2_SNo,'Facility Master'!A:A,0)),0),0) -> 0 | K12: =IFERROR(IF(B12<UBI_RTL2_RepStart,0,IF(B12>UBI_RTL2_Maturity,0,IF(COUNTIFS($B$5:$B12,">="&UBI_RTL2_RepStart,$B$5:$B12,"<="&UBI_RTL2_Maturity)<=8,INDEX('Facility Master'!K:K,MATCH(UBI_RTL2_SNo,'Facility Master'!A:A,0))*0.0125,IF(COUNTIFS($B$5:$B12,">="&UBI_RTL2_RepStart,$B$5:$B12,"<="&UBI_RTL2_Maturity)<=48,INDEX('Facility Master'!K:K,MATCH(UBI_RTL2_SNo,'Facility Master'!A:A,0))*0.0225,0)))),0) -> 0 | L12: =IFERROR((I12+(J12-K12)/2)*INDEX('Facility Master'!R:R,MATCH(UBI_RTL2_SNo,'Facility Master'!A:A,0))*(B12-B11)/DaysInYear,0) -> 0 | M12: =IFERROR(ROUND(MAX(I12+J12-K12,0),6),0) -> 0 | N12: =IFERROR(MAX(R11,0),0) -> 235 | O12: =IFERROR(IF(AND(INDEX('Facility Master'!X:X,MATCH(IB_TL_SNo,'Facility Master'!A:A,0))<=B12,INDEX('Facility Master'!X:X,MATCH(IB_TL_SNo,'Facility Master'!A:A,0))>B11),INDEX('Facility Master'!K:K,MATCH(IB_TL_SNo,'Facility Master'!A:A,0)),0),0) -> 0 | P12: =IFERROR(IF(B12<IB_TL_RepStart,0,IF(B12>IB_TL_Maturity,0,IF(COUNTIFS($B$5:$B12,">="&IB_TL_RepStart,$B$5:$B12,"<="&IB_TL_Maturity)<=8,INDEX('Facility Master'!K:K,MATCH(IB_TL_SNo,'Facility Master'!A:A,0))*0.0125,IF(COUNTIFS($B$5:$B12,">="&IB_TL_RepStart,$B$5:$B12,"<="&IB_TL_Maturity)<=48,INDEX('Facility Master'!K:K,MATCH(IB_TL_SNo,'Facility Master'!A:A,0))*0.0225,0)))),0) -> 0 | Q12: =IFERROR((N12+(O12-P12)/2)*INDEX('Facility Master'!R:R,MATCH(IB_TL_SNo,'Facility Master'!A:A,0))*(B12-B11)/DaysInYear,0) -> 5.4468493 | R12: =IFERROR(ROUND(MAX(N12+O12-P12,0),6),0) -> 235 | S12: =IFERROR(MAX(W11,0),0) -> 0 | T12: =IFERROR(IF(AND(INDEX('Facility Master'!X:X,MATCH(RBL_TL_SNo,'Facility Master'!A:A,0))<=B12,INDEX('Facility Master'!X:X,MATCH(RBL_TL_SNo,'Facility Master'!A:A,0))>B11),INDEX('Facility Master'!K:K,MATCH(RBL_TL_SNo,'Facility Master'!A:A,0)),0),0) -> 0 | U12: =IFERROR(IF(AND(RBL_TL_Maturity<=B12,RBL_TL_Maturity>B11),INDEX('Facility Master'!K:K,MATCH(RBL_TL_SNo,'Facility Master'!A:A,0)),0),0) -> 0 | V12: =IFERROR((S12+(T12-U12)/2)*INDEX('Facility Master'!R:R,MATCH(RBL_TL_SNo,'Facility Master'!A:A,0))*(B12-B11)/DaysInYear,0) -> 0 | W12: =IFERROR(ROUND(MAX(S12+T12-U12,0),6),0) -> 0 | X12: =IFERROR(MAX(AB11,0),0) -> 0 | Y12: =IFERROR(IF(AND(INDEX('Facility Master'!X:X,MATCH(YBL_TL_SNo,'Facility Master'!A:A,0))<=B12,INDEX('Facility Master'!X:X,MATCH(YBL_TL_SNo,'Facility Master'!A:A,0))>B11),INDEX('Facility Master'!K:K,MATCH(YBL_TL_SNo,'Facility Master'!A:A,0)),0),0) -> 0 | Z12: =IFERROR(IF(B12<YBL_TL_RepStart,0,IF(B12>YBL_TL_Maturity,0,IF(COUNTIFS($B$5:$B12,">="&YBL_TL_RepStart,$B$5:$B12,"<="&YBL_TL_Maturity)<=8,INDEX('Facility Master'!K:K,MATCH(YBL_TL_SNo,'Facility Master'!A:A,0))*0.0125,IF(COUNTIFS($B$5:$B12,">="&YBL_TL_RepStart,$B$5:$B12,"<="&YBL_TL_Maturity)<=48,INDEX('Facility Master'!K:K,MATCH(YBL_TL_SNo,'Facility Master'!A:A,0))*0.0225,0)))),0) -> 0 | AA12: =IFERROR((X12+(Y12-Z12)/2)*INDEX('Facility Master'!R:R,MATCH(YBL_TL_SNo,'Facility Master'!A:A,0))*(B12-B11)/DaysInYear,0) -> 0 | AB12: =IFERROR(ROUND(MAX(X12+Y12-Z12,0),6),0) -> 0 | AC12: =IFERROR(MAX(AG11,0),0) -> 0 | AD12: =IFERROR(IF(AND(INDEX('Facility Master'!X:X,MATCH(IDFC_TL_SNo,'Facility Master'!A:A,0))<=B12,INDEX('Facility Master'!X:X,MATCH(IDFC_TL_SNo,'Facility Master'!A:A,0))>B11),INDEX('Facility Master'!K:K,MATCH(IDFC_TL_SNo,'Facility Master'!A:A,0)),0),0) -> 0 | AE12: =IFERROR(IF(B12<IDFC_TL_RepStart,0,IF(B12>IDFC_TL_Maturity,0,IF(COUNTIFS($B$5:$B12,">="&IDFC_TL_RepStart,$B$5:$B12,"<="&IDFC_TL_Maturity)<=8,INDEX('Facility Master'!K:K,MATCH(IDFC_TL_SNo,'Facility Master'!A:A,0))*0.0125,IF(COUNTIFS($B$5:$B12,">="&IDFC_TL_RepStart,$B$5:$B12,"<="&IDFC_TL_Maturity)<=48,INDEX('Facility Master'!K:K,MATCH(IDFC_TL_SNo,'Facility Master'!A:A,0))*0.0225,0)))),0) -> 0 | AF12: =IFERROR((AC12+(AD12-AE12)/2)*INDEX('Facility Master'!R:R,MATCH(IDFC_TL_SNo,'Facility Master'!A:A,0))*(B12-B11)/DaysInYear,0) -> 0 | AG12: =IFERROR(ROUND(MAX(AC12+AD12-AE12,0),6),0) -> 0 | AH12: =IFERROR(MAX(AL11,0),0) -> 0 | AI12: =IFERROR(IF(AND(INDEX('Facility Master'!X:X,MATCH(ICICI_TL_SNo,'Facility Master'!A:A,0))<=B12,INDEX('Facility Master'!X:X,MATCH(ICICI_TL_SNo,'Facility Master'!A:A,0))>B11),INDEX('Facility Master'!K:K,MATCH(ICICI_TL_SNo,'Facility Master'!A:A,0)),0),0) -> 0 | AJ12: =IFERROR(IF(B12<ICICI_TL_RepStart,0,IF(B12>ICICI_TL_Maturity,0,IF(COUNTIFS($B$5:$B12,">="&ICICI_TL_RepStart,$B$5:$B12,"<="&ICICI_TL_Maturity)<=8,INDEX('Facility Master'!K:K,MATCH(ICICI_TL_SNo,'Facility Master'!A:A,0))*0.0125,IF(COUNTIFS($B$5:$B12,">="&ICICI_TL_RepStart,$B$5:$B12,"<="&ICICI_TL_Maturity)<=48,INDEX('Facility Master'!K:K,MATCH(ICICI_TL_SNo,'Facility Master'!A:A,0))*0.0225,0)))),0) -> 0 | AK12: =IFERROR((AH12+(AI12-AJ12)/2)*INDEX('Facility Master'!R:R,MATCH(ICICI_TL_SNo,'Facility Master'!A:A,0))*(B12-B11)/DaysInYear,0) -> 0 | AL12: =IFERROR(ROUND(MAX(AH12+AI12-AJ12,0),6),0) -> 0 | AM12: =F12+K12+P12+Z12+AE12+AJ12 -> 0 | AN12: =G12+L12+Q12+AA12+AF12+AK12 -> 31.522192 | AO12: =AM12+AN12 -> 31.522192 | AP12: =H12+M12+R12+AB12+AG12+AL12 -> 1360
A13: 9 | B13: 45838 | C13: Q1 FY26 | D13: =IFERROR(MAX(H12,0),0) -> 1125 | E13: =IFERROR(IF(AND(INDEX('Facility Master'!X:X,MATCH(UBI_RTL1_SNo,'Facility Master'!A:A,0))<=B13,INDEX('Facility Master'!X:X,MATCH(UBI_RTL1_SNo,'Facility Master'!A:A,0))>B12),INDEX('Facility Master'!K:K,MATCH(UBI_RTL1_SNo,'Facility Master'!A:A,0)),0),0) -> 0 | F13: =IFERROR(IF(B13<UBI_RTL1_RepStart,0,IF(B13>UBI_RTL1_Maturity,0,IF(COUNTIFS($B$5:$B13,">="&UBI_RTL1_RepStart,$B$5:$B13,"<="&UBI_RTL1_Maturity)<=8,INDEX('Facility Master'!K:K,MATCH(UBI_RTL1_SNo,'Facility Master'!A:A,0))*0.0125,IF(COUNTIFS($B$5:$B13,">="&UBI_RTL1_RepStart,$B$5:$B13,"<="&UBI_RTL1_Maturity)<=48,INDEX('Facility Master'!K:K,MATCH(UBI_RTL1_SNo,'Facility Master'!A:A,0))*0.0225,0)))),0) -> 0 | G13: =IFERROR((D13+(E13-F13)/2)*INDEX('Facility Master'!R:R,MATCH(UBI_RTL1_SNo,'Facility Master'!A:A,0))*(B13-B12)/DaysInYear,0) -> 26.365068 | H13: =IFERROR(ROUND(MAX(D13+E13-F13,0),6),0) -> 1125 | I13: =IFERROR(MAX(M12,0),0) -> 0 | J13: =IFERROR(IF(AND(INDEX('Facility Master'!X:X,MATCH(UBI_RTL2_SNo,'Facility Master'!A:A,0))<=B13,INDEX('Facility Master'!X:X,MATCH(UBI_RTL2_SNo,'Facility Master'!A:A,0))>B12),INDEX('Facility Master'!K:K,MATCH(UBI_RTL2_SNo,'Facility Master'!A:A,0)),0),0) -> 0 | K13: =IFERROR(IF(B13<UBI_RTL2_RepStart,0,IF(B13>UBI_RTL2_Maturity,0,IF(COUNTIFS($B$5:$B13,">="&UBI_RTL2_RepStart,$B$5:$B13,"<="&UBI_RTL2_Maturity)<=8,INDEX('Facility Master'!K:K,MATCH(UBI_RTL2_SNo,'Facility Master'!A:A,0))*0.0125,IF(COUNTIFS($B$5:$B13,">="&UBI_RTL2_RepStart,$B$5:$B13,"<="&UBI_RTL2_Maturity)<=48,INDEX('Facility Master'!K:K,MATCH(UBI_RTL2_SNo,'Facility Master'!A:A,0))*0.0225,0)))),0) -> 0 | L13: =IFERROR((I13+(J13-K13)/2)*INDEX('Facility Master'!R:R,MATCH(UBI_RTL2_SNo,'Facility Master'!A:A,0))*(B13-B12)/DaysInYear,0) -> 0 | M13: =IFERROR(ROUND(MAX(I13+J13-K13,0),6),0) -> 0 | N13: =IFERROR(MAX(R12,0),0) -> 235 | O13: =IFERROR(IF(AND(INDEX('Facility Master'!X:X,MATCH(IB_TL_SNo,'Facility Master'!A:A,0))<=B13,INDEX('Facility Master'!X:X,MATCH(IB_TL_SNo,'Facility Master'!A:A,0))>B12),INDEX('Facility Master'!K:K,MATCH(IB_TL_SNo,'Facility Master'!A:A,0)),0),0) -> 0 | P13: =IFERROR(IF(B13<IB_TL_RepStart,0,IF(B13>IB_TL_Maturity,0,IF(COUNTIFS($B$5:$B13,">="&IB_TL_RepStart,$B$5:$B13,"<="&IB_TL_Maturity)<=8,INDEX('Facility Master'!K:K,MATCH(IB_TL_SNo,'Facility Master'!A:A,0))*0.0125,IF(COUNTIFS($B$5:$B13,">="&IB_TL_RepStart,$B$5:$B13,"<="&IB_TL_Maturity)<=48,INDEX('Facility Master'!K:K,MATCH(IB_TL_SNo,'Facility Master'!A:A,0))*0.0225,0)))),0) -> 0 | Q13: =IFERROR((N13+(O13-P13)/2)*INDEX('Facility Master'!R:R,MATCH(IB_TL_SNo,'Facility Master'!A:A,0))*(B13-B12)/DaysInYear,0) -> 5.5073699 | R13: =IFERROR(ROUND(MAX(N13+O13-P13,0),6),0) -> 235 | S13: =IFERROR(MAX(W12,0),0) -> 0 | T13: =IFERROR(IF(AND(INDEX('Facility Master'!X:X,MATCH(RBL_TL_SNo,'Facility Master'!A:A,0))<=B13,INDEX('Facility Master'!X:X,MATCH(RBL_TL_SNo,'Facility Master'!A:A,0))>B12),INDEX('Facility Master'!K:K,MATCH(RBL_TL_SNo,'Facility Master'!A:A,0)),0),0) -> 0 | U13: =IFERROR(IF(AND(RBL_TL_Maturity<=B13,RBL_TL_Maturity>B12),INDEX('Facility Master'!K:K,MATCH(RBL_TL_SNo,'Facility Master'!A:A,0)),0),0) -> 0 | V13: =IFERROR((S13+(T13-U13)/2)*INDEX('Facility Master'!R:R,MATCH(RBL_TL_SNo,'Facility Master'!A:A,0))*(B13-B12)/DaysInYear,0) -> 0 | W13: =IFERROR(ROUND(MAX(S13+T13-U13,0),6),0) -> 0 | X13: =IFERROR(MAX(AB12,0),0) -> 0 | Y13: =IFERROR(IF(AND(INDEX('Facility Master'!X:X,MATCH(YBL_TL_SNo,'Facility Master'!A:A,0))<=B13,INDEX('Facility Master'!X:X,MATCH(YBL_TL_SNo,'Facility Master'!A:A,0))>B12),INDEX('Facility Master'!K:K,MATCH(YBL_TL_SNo,'Facility Master'!A:A,0)),0),0) -> 0 | Z13: =IFERROR(IF(B13<YBL_TL_RepStart,0,IF(B13>YBL_TL_Maturity,0,IF(COUNTIFS($B$5:$B13,">="&YBL_TL_RepStart,$B$5:$B13,"<="&YBL_TL_Maturity)<=8,INDEX('Facility Master'!K:K,MATCH(YBL_TL_SNo,'Facility Master'!A:A,0))*0.0125,IF(COUNTIFS($B$5:$B13,">="&YBL_TL_RepStart,$B$5:$B13,"<="&YBL_TL_Maturity)<=48,INDEX('Facility Master'!K:K,MATCH(YBL_TL_SNo,'Facility Master'!A:A,0))*0.0225,0)))),0) -> 0 | AA13: =IFERROR((X13+(Y13-Z13)/2)*INDEX('Facility Master'!R:R,MATCH(YBL_TL_SNo,'Facility Master'!A:A,0))*(B13-B12)/DaysInYear,0) -> 0 | AB13: =IFERROR(ROUND(MAX(X13+Y13-Z13,0),6),0) -> 0 | AC13: =IFERROR(MAX(AG12,0),0) -> 0 | AD13: =IFERROR(IF(AND(INDEX('Facility Master'!X:X,MATCH(IDFC_TL_SNo,'Facility Master'!A:A,0))<=B13,INDEX('Facility Master'!X:X,MATCH(IDFC_TL_SNo,'Facility Master'!A:A,0))>B12),INDEX('Facility Master'!K:K,MATCH(IDFC_TL_SNo,'Facility Master'!A:A,0)),0),0) -> 0 | AE13: =IFERROR(IF(B13<IDFC_TL_RepStart,0,IF(B13>IDFC_TL_Maturity,0,IF(COUNTIFS($B$5:$B13,">="&IDFC_TL_RepStart,$B$5:$B13,"<="&IDFC_TL_Maturity)<=8,INDEX('Facility Master'!K:K,MATCH(IDFC_TL_SNo,'Facility Master'!A:A,0))*0.0125,IF(COUNTIFS($B$5:$B13,">="&IDFC_TL_RepStart,$B$5:$B13,"<="&IDFC_TL_Maturity)<=48,INDEX('Facility Master'!K:K,MATCH(IDFC_TL_SNo,'Facility Master'!A:A,0))*0.0225,0)))),0) -> 0 | AF13: =IFERROR((AC13+(AD13-AE13)/2)*INDEX('Facility Master'!R:R,MATCH(IDFC_TL_SNo,'Facility Master'!A:A,0))*(B13-B12)/DaysInYear,0) -> 0 | AG13: =IFERROR(ROUND(MAX(AC13+AD13-AE13,0),6),0) -> 0 | AH13: =IFERROR(MAX(AL12,0),0) -> 0 | AI13: =IFERROR(IF(AND(INDEX('Facility Master'!X:X,MATCH(ICICI_TL_SNo,'Facility Master'!A:A,0))<=B13,INDEX('Facility Master'!X:X,MATCH(ICICI_TL_SNo,'Facility Master'!A:A,0))>B12),INDEX('Facility Master'!K:K,MATCH(ICICI_TL_SNo,'Facility Master'!A:A,0)),0),0) -> 0 | AJ13: =IFERROR(IF(B13<ICICI_TL_RepStart,0,IF(B13>ICICI_TL_Maturity,0,IF(COUNTIFS($B$5:$B13,">="&ICICI_TL_RepStart,$B$5:$B13,"<="&ICICI_TL_Maturity)<=8,INDEX('Facility Master'!K:K,MATCH(ICICI_TL_SNo,'Facility Master'!A:A,0))*0.0125,IF(COUNTIFS($B$5:$B13,">="&ICICI_TL_RepStart,$B$5:$B13,"<="&ICICI_TL_Maturity)<=48,INDEX('Facility Master'!K:K,MATCH(ICICI_TL_SNo,'Facility Master'!A:A,0))*0.0225,0)))),0) -> 0 | AK13: =IFERROR((AH13+(AI13-AJ13)/2)*INDEX('Facility Master'!R:R,MATCH(ICICI_TL_SNo,'Facility Master'!A:A,0))*(B13-B12)/DaysInYear,0) -> 0 | AL13: =IFERROR(ROUND(MAX(AH13+AI13-AJ13,0),6),0) -> 0 | AM13: =F13+K13+P13+Z13+AE13+AJ13 -> 0 | AN13: =G13+L13+Q13+AA13+AF13+AK13 -> 31.872438 | AO13: =AM13+AN13 -> 31.872438 | AP13: =H13+M13+R13+AB13+AG13+AL13 -> 1360
